Workbook

Sheet PAINEL
A1: PAINEL FINANCEIRO E DE OCUPAÇÃO
A3: Ano | B3: 2026 | M3: A receber (R$) | N3: =SUMIFS(RESERVAS!$U$6:$U$203,RESERVAS!$I$6:$I$203,"<>Cancelada",RESERVAS!$I$6:$I$203,"<>Consulta") -> 48093.62
A5: Receita bruta (R$) | B5: =SUM(F13:F24) -> 28541.67 | D5: Custos diretos (R$) | E5: =SUM(G13:G24) -> 32.05 | G5: Despesas gerais (R$) | H5: =SUM(H13:H24) -> 0 | J5: Lucro final (R$) | K5: =SUM(I13:I24) -> 28509.62
A8: Diárias alugadas | B8: =SUM(C13:C24) -> 53 | D8: Dias disponíveis | E8: =SUM(D13:D24) -> 677 | G8: Ocupação anual | H8: =IF(SUM(B13:B24)=0,0,SUM(C13:C24)/SUM(B13:B24)) -> 0.07260274 | J8: Diária média (R$) | K8: =IF(B8=0,0,B5/B8) -> 538.52208
A12: Mês | B12: Dias | C12: Alugadas | D12: Disponíveis | E12: Ocupação | F12: Receita (R$) | G12: Custos diretos (R$) | H12: Despesas gerais (R$) | I12: Lucro final (R$) | J12: Margem | L12: EXEMPLO CADASTRADO
A13: Janeiro | B13: =DAY(EOMONTH(DATE($B$3,1,1),0))*2 -> 62 | C13: =SUMPRODUCT((RESERVAS!$C$6:$C$203<DATE($B$3,2,1))*(RESERVAS!$D$6:$D$203>DATE($B$3,1,1))*(RESERVAS!$I$6:$I$203<>"Cancelada")*(RESERVAS!$I$6:$I$203<>"Consulta")*(((RESERVAS!$D$6:$D$203<DATE($B$3,2,1))*RESERVAS!$D$6:$D$203+(RESERVAS!$D$6:$D$203>=DATE($B$3,2,1))*DATE($B$3,2,1))-((RESERVAS!$C$6:$C$203>DATE($B$3,1,1))*RESERVAS!$C$6:$C$203+(RESERVAS!$C$6:$C$203<=DATE($B$3,1,1))*DATE($B$3,1,1)))) -> 0 | D13: =MAX(0,B13-C13) -> 62 | E13: =IF(B13=0,0,C13/B13) -> 0 | F13: =SUMPRODUCT((RESERVAS!$C$6:$C$203<DATE($B$3,2,1))*(RESERVAS!$D$6:$D$203>DATE($B$3,1,1))*(RESERVAS!$I$6:$I$203<>"Cancelada")*(RESERVAS!$I$6:$I$203<>"Consulta")*RESERVAS!$F$6:$F$203*(((RESERVAS!$D$6:$D$203<DATE($B$3,2,1))*RESERVAS!$D$6:$D$203+(RESERVAS!$D$6:$D$203>=DATE($B$3,2,1))*DATE($B$3,2,1))-((RESERVAS!$C$6:$C$203>DATE($B$3,1,1))*RESERVAS!$C$6:$C$203+(RESERVAS!$C$6:$C$203<=DATE($B$3,1,1))*DATE($B$3,1,1)))) -> 0 | G13: =SUMPRODUCT((RESERVAS!$C$6:$C$203<DATE($B$3,2,1))*(RESERVAS!$D$6:$D$203>DATE($B$3,1,1))*(RESERVAS!$I$6:$I$203<>"Cancelada")*(RESERVAS!$I$6:$I$203<>"Consulta")*RESERVAS!$T$6:$T$203*(((RESERVAS!$D$6:$D$203<DATE($B$3,2,1))*RESERVAS!$D$6:$D$203+(RESERVAS!$D$6:$D$203>=DATE($B$3,2,1))*DATE($B$3,2,1))-((RESERVAS!$C$6:$C$203>DATE($B$3,1,1))*RESERVAS!$C$6:$C$203+(RESERVAS!$C$6:$C$203<=DATE($B$3,1,1))*DATE($B$3,1,1)))) -> 0 | H13: =SUMIFS('DESPESAS CASA'!$D$6:$D$305,'DESPESAS CASA'!$A$6:$A$305,">="&DATE($B$3,1,1),'DESPESAS CASA'!$A$6:$A$305,"<"&DATE($B$3,2,1),'DESPESAS CASA'!$E$6:$E$305,"") -> 0 | I13: =F13-G13-H13 -> 0 | J13: =IF(F13=0,0,I13/F13) -> 0 | L13: Período | M13: 25/12/2026 a 04/01/2027
A14: Fevereiro | B14: =DAY(EOMONTH(DATE($B$3,2,1),0))*2 -> 56 | C14: =SUMPRODUCT((RESERVAS!$C$6:$C$203<DATE($B$3,3,1))*(RESERVAS!$D$6:$D$203>DATE($B$3,2,1))*(RESERVAS!$I$6:$I$203<>"Cancelada")*(RESERVAS!$I$6:$I$203<>"Consulta")*(((RESERVAS!$D$6:$D$203<DATE($B$3,3,1))*RESERVAS!$D$6:$D$203+(RESERVAS!$D$6:$D$203>=DATE($B$3,3,1))*DATE($B$3,3,1))-((RESERVAS!$C$6:$C$203>DATE($B$3,2,1))*RESERVAS!$C$6:$C$203+(RESERVAS!$C$6:$C$203<=DATE($B$3,2,1))*DATE($B$3,2,1)))) -> 0 | D14: =MAX(0,B14-C14) -> 56 | E14: =IF(B14=0,0,C14/B14) -> 0 | F14: =SUMPRODUCT((RESERVAS!$C$6:$C$203<DATE($B$3,3,1))*(RESERVAS!$D$6:$D$203>DATE($B$3,2,1))*(RESERVAS!$I$6:$I$203<>"Cancelada")*(RESERVAS!$I$6:$I$203<>"Consulta")*RESERVAS!$F$6:$F$203*(((RESERVAS!$D$6:$D$203<DATE($B$3,3,1))*RESERVAS!$D$6:$D$203+(RESERVAS!$D$6:$D$203>=DATE($B$3,3,1))*DATE($B$3,3,1))-((RESERVAS!$C$6:$C$203>DATE($B$3,2,1))*RESERVAS!$C$6:$C$203+(RESERVAS!$C$6:$C$203<=DATE($B$3,2,1))*DATE($B$3,2,1)))) -> 0 | G14: =SUMPRODUCT((RESERVAS!$C$6:$C$203<DATE($B$3,3,1))*(RESERVAS!$D$6:$D$203>DATE($B$3,2,1))*(RESERVAS!$I$6:$I$203<>"Cancelada")*(RESERVAS!$I$6:$I$203<>"Consulta")*RESERVAS!$T$6:$T$203*(((RESERVAS!$D$6:$D$203<DATE($B$3,3,1))*RESERVAS!$D$6:$D$203+(RESERVAS!$D$6:$D$203>=DATE($B$3,3,1))*DATE($B$3,3,1))-((RESERVAS!$C$6:$C$203>DATE($B$3,2,1))*RESERVAS!$C$6:$C$203+(RESERVAS!$C$6:$C$203<=DATE($B$3,2,1))*DATE($B$3,2,1)))) -> 0 | H14: =SUMIFS('DESPESAS CASA'!$D$6:$D$305,'DESPESAS CASA'!$A$6:$A$305,">="&DATE($B$3,2,1),'DESPESAS CASA'!$A$6:$A$305,"<"&DATE($B$3,3,1),'DESPESAS CASA'!$E$6:$E$305,"") -> 0 | I14: =F14-G14-H14 -> 0 | J14: =IF(F14=0,0,I14/F14) -> 0 | L14: Diárias | M14: 10
A15: Março | B15: =DAY(EOMONTH(DATE($B$3,3,1),0))*2 -> 62 | C15: =SUMPRODUCT((RESERVAS!$C$6:$C$203<DATE($B$3,4,1))*(RESERVAS!$D$6:$D$203>DATE($B$3,3,1))*(RESERVAS!$I$6:$I$203<>"Cancelada")*(RESERVAS!$I$6:$I$203<>"Consulta")*(((RESERVAS!$D$6:$D$203<DATE($B$3,4,1))*RESERVAS!$D$6:$D$203+(RESERVAS!$D$6:$D$203>=DATE($B$3,4,1))*DATE($B$3,4,1))-((RESERVAS!$C$6:$C$203>DATE($B$3,3,1))*RESERVAS!$C$6:$C$203+(RESERVAS!$C$6:$C$203<=DATE($B$3,3,1))*DATE($B$3,3,1)))) -> 0 | D15: =MAX(0,B15-C15) -> 62 | E15: =IF(B15=0,0,C15/B15) -> 0 | F15: =SUMPRODUCT((RESERVAS!$C$6:$C$203<DATE($B$3,4,1))*(RESERVAS!$D$6:$D$203>DATE($B$3,3,1))*(RESERVAS!$I$6:$I$203<>"Cancelada")*(RESERVAS!$I$6:$I$203<>"Consulta")*RESERVAS!$F$6:$F$203*(((RESERVAS!$D$6:$D$203<DATE($B$3,4,1))*RESERVAS!$D$6:$D$203+(RESERVAS!$D$6:$D$203>=DATE($B$3,4,1))*DATE($B$3,4,1))-((RESERVAS!$C$6:$C$203>DATE($B$3,3,1))*RESERVAS!$C$6:$C$203+(RESERVAS!$C$6:$C$203<=DATE($B$3,3,1))*DATE($B$3,3,1)))) -> 0 | G15: =SUMPRODUCT((RESERVAS!$C$6:$C$203<DATE($B$3,4,1))*(RESERVAS!$D$6:$D$203>DATE($B$3,3,1))*(RESERVAS!$I$6:$I$203<>"Cancelada")*(RESERVAS!$I$6:$I$203<>"Consulta")*RESERVAS!$T$6:$T$203*(((RESERVAS!$D$6:$D$203<DATE($B$3,4,1))*RESERVAS!$D$6:$D$203+(RESERVAS!$D$6:$D$203>=DATE($B$3,4,1))*DATE($B$3,4,1))-((RESERVAS!$C$6:$C$203>DATE($B$3,3,1))*RESERVAS!$C$6:$C$203+(RESERVAS!$C$6:$C$203<=DATE($B$3,3,1))*DATE($B$3,3,1)))) -> 0 | H15: =SUMIFS('DESPESAS CASA'!$D$6:$D$305,'DESPESAS CASA'!$A$6:$A$305,">="&DATE($B$3,3,1),'DESPESAS CASA'!$A$6:$A$305,"<"&DATE($B$3,4,1),'DESPESAS CASA'!$E$6:$E$305,"") -> 0 | I15: =F15-G15-H15 -> 0 | J15: =IF(F15=0,0,I15/F15) -> 0 | L15: Valor diária | M15: 1100
A16: Abril | B16: =DAY(EOMONTH(DATE($B$3,4,1),0))*2 -> 60 | C16: =SUMPRODUCT((RESERVAS!$C$6:$C$203<DATE($B$3,5,1))*(RESERVAS!$D$6:$D$203>DATE($B$3,4,1))*(RESERVAS!$I$6:$I$203<>"Cancelada")*(RESERVAS!$I$6:$I$203<>"Consulta")*(((RESERVAS!$D$6:$D$203<DATE($B$3,5,1))*RESERVAS!$D$6:$D$203+(RESERVAS!$D$6:$D$203>=DATE($B$3,5,1))*DATE($B$3,5,1))-((RESERVAS!$C$6:$C$203>DATE($B$3,4,1))*RESERVAS!$C$6:$C$203+(RESERVAS!$C$6:$C$203<=DATE($B$3,4,1))*DATE($B$3,4,1)))) -> 0 | D16: =MAX(0,B16-C16) -> 60 | E16: =IF(B16=0,0,C16/B16) -> 0 | F16: =SUMPRODUCT((RESERVAS!$C$6:$C$203<DATE($B$3,5,1))*(RESERVAS!$D$6:$D$203>DATE($B$3,4,1))*(RESERVAS!$I$6:$I$203<>"Cancelada")*(RESERVAS!$I$6:$I$203<>"Consulta")*RESERVAS!$F$6:$F$203*(((RESERVAS!$D$6:$D$203<DATE($B$3,5,1))*RESERVAS!$D$6:$D$203+(RESERVAS!$D$6:$D$203>=DATE($B$3,5,1))*DATE($B$3,5,1))-((RESERVAS!$C$6:$C$203>DATE($B$3,4,1))*RESERVAS!$C$6:$C$203+(RESERVAS!$C$6:$C$203<=DATE($B$3,4,1))*DATE($B$3,4,1)))) -> 0 | G16: =SUMPRODUCT((RESERVAS!$C$6:$C$203<DATE($B$3,5,1))*(RESERVAS!$D$6:$D$203>DATE($B$3,4,1))*(RESERVAS!$I$6:$I$203<>"Cancelada")*(RESERVAS!$I$6:$I$203<>"Consulta")*RESERVAS!$T$6:$T$203*(((RESERVAS!$D$6:$D$203<DATE($B$3,5,1))*RESERVAS!$D$6:$D$203+(RESERVAS!$D$6:$D$203>=DATE($B$3,5,1))*DATE($B$3,5,1))-((RESERVAS!$C$6:$C$203>DATE($B$3,4,1))*RESERVAS!$C$6:$C$203+(RESERVAS!$C$6:$C$203<=DATE($B$3,4,1))*DATE($B$3,4,1)))) -> 0 | H16: =SUMIFS('DESPESAS CASA'!$D$6:$D$305,'DESPESAS CASA'!$A$6:$A$305,">="&DATE($B$3,4,1),'DESPESAS CASA'!$A$6:$A$305,"<"&DATE($B$3,5,1),'DESPESAS CASA'!$E$6:$E$305,"") -> 0 | I16: =F16-G16-H16 -> 0 | J16: =IF(F16=0,0,I16/F16) -> 0 | L16: Receita total | M16: 11000
A17: Maio | B17: =DAY(EOMONTH(DATE($B$3,5,1),0))*2 -> 62 | C17: =SUMPRODUCT((RESERVAS!$C$6:$C$203<DATE($B$3,6,1))*(RESERVAS!$D$6:$D$203>DATE($B$3,5,1))*(RESERVAS!$I$6:$I$203<>"Cancelada")*(RESERVAS!$I$6:$I$203<>"Consulta")*(((RESERVAS!$D$6:$D$203<DATE($B$3,6,1))*RESERVAS!$D$6:$D$203+(RESERVAS!$D$6:$D$203>=DATE($B$3,6,1))*DATE($B$3,6,1))-((RESERVAS!$C$6:$C$203>DATE($B$3,5,1))*RESERVAS!$C$6:$C$203+(RESERVAS!$C$6:$C$203<=DATE($B$3,5,1))*DATE($B$3,5,1)))) -> 0 | D17: =MAX(0,B17-C17) -> 62 | E17: =IF(B17=0,0,C17/B17) -> 0 | F17: =SUMPRODUCT((RESERVAS!$C$6:$C$203<DATE($B$3,6,1))*(RESERVAS!$D$6:$D$203>DATE($B$3,5,1))*(RESERVAS!$I$6:$I$203<>"Cancelada")*(RESERVAS!$I$6:$I$203<>"Consulta")*RESERVAS!$F$6:$F$203*(((RESERVAS!$D$6:$D$203<DATE($B$3,6,1))*RESERVAS!$D$6:$D$203+(RESERVAS!$D$6:$D$203>=DATE($B$3,6,1))*DATE($B$3,6,1))-((RESERVAS!$C$6:$C$203>DATE($B$3,5,1))*RESERVAS!$C$6:$C$203+(RESERVAS!$C$6:$C$203<=DATE($B$3,5,1))*DATE($B$3,5,1)))) -> 0 | G17: =SUMPRODUCT((RESERVAS!$C$6:$C$203<DATE($B$3,6,1))*(RESERVAS!$D$6:$D$203>DATE($B$3,5,1))*(RESERVAS!$I$6:$I$203<>"Cancelada")*(RESERVAS!$I$6:$I$203<>"Consulta")*RESERVAS!$T$6:$T$203*(((RESERVAS!$D$6:$D$203<DATE($B$3,6,1))*RESERVAS!$D$6:$D$203+(RESERVAS!$D$6:$D$203>=DATE($B$3,6,1))*DATE($B$3,6,1))-((RESERVAS!$C$6:$C$203>DATE($B$3,5,1))*RESERVAS!$C$6:$C$203+(RESERVAS!$C$6:$C$203<=DATE($B$3,5,1))*DATE($B$3,5,1)))) -> 0 | H17: =SUMIFS('DESPESAS CASA'!$D$6:$D$305,'DESPESAS CASA'!$A$6:$A$305,">="&DATE($B$3,5,1),'DESPESAS CASA'!$A$6:$A$305,"<"&DATE($B$3,6,1),'DESPESAS CASA'!$E$6:$E$305,"") -> 0 | I17: =F17-G17-H17 -> 0 | J17: =IF(F17=0,0,I17/F17) -> 0 | L17: Rateio | M17: Dez/26: R$ 7.700 | Jan/27: R$ 3.300
A18: Junho | B18: =DAY(EOMONTH(DATE($B$3,6,1),0))*2 -> 60 | C18: =SUMPRODUCT((RESERVAS!$C$6:$C$203<DATE($B$3,7,1))*(RESERVAS!$D$6:$D$203>DATE($B$3,6,1))*(RESERVAS!$I$6:$I$203<>"Cancelada")*(RESERVAS!$I$6:$I$203<>"Consulta")*(((RESERVAS!$D$6:$D$203<DATE($B$3,7,1))*RESERVAS!$D$6:$D$203+(RESERVAS!$D$6:$D$203>=DATE($B$3,7,1))*DATE($B$3,7,1))-((RESERVAS!$C$6:$C$203>DATE($B$3,6,1))*RESERVAS!$C$6:$C$203+(RESERVAS!$C$6:$C$203<=DATE($B$3,6,1))*DATE($B$3,6,1)))) -> 0 | D18: =MAX(0,B18-C18) -> 60 | E18: =IF(B18=0,0,C18/B18) -> 0 | F18: =SUMPRODUCT((RESERVAS!$C$6:$C$203<DATE($B$3,7,1))*(RESERVAS!$D$6:$D$203>DATE($B$3,6,1))*(RESERVAS!$I$6:$I$203<>"Cancelada")*(RESERVAS!$I$6:$I$203<>"Consulta")*RESERVAS!$F$6:$F$203*(((RESERVAS!$D$6:$D$203<DATE($B$3,7,1))*RESERVAS!$D$6:$D$203+(RESERVAS!$D$6:$D$203>=DATE($B$3,7,1))*DATE($B$3,7,1))-((RESERVAS!$C$6:$C$203>DATE($B$3,6,1))*RESERVAS!$C$6:$C$203+(RESERVAS!$C$6:$C$203<=DATE($B$3,6,1))*DATE($B$3,6,1)))) -> 0 | G18: =SUMPRODUCT((RESERVAS!$C$6:$C$203<DATE($B$3,7,1))*(RESERVAS!$D$6:$D$203>DATE($B$3,6,1))*(RESERVAS!$I$6:$I$203<>"Cancelada")*(RESERVAS!$I$6:$I$203<>"Consulta")*RESERVAS!$T$6:$T$203*(((RESERVAS!$D$6:$D$203<DATE($B$3,7,1))*RESERVAS!$D$6:$D$203+(RESERVAS!$D$6:$D$203>=DATE($B$3,7,1))*DATE($B$3,7,1))-((RESERVAS!$C$6:$C$203>DATE($B$3,6,1))*RESERVAS!$C$6:$C$203+(RESERVAS!$C$6:$C$203<=DATE($B$3,6,1))*DATE($B$3,6,1)))) -> 0 | H18: =SUMIFS('DESPESAS CASA'!$D$6:$D$305,'DESPESAS CASA'!$A$6:$A$305,">="&DATE($B$3,6,1),'DESPESAS CASA'!$A$6:$A$305,"<"&DATE($B$3,7,1),'DESPESAS CASA'!$E$6:$E$305,"") -> 0 | I18: =F18-G18-H18 -> 0 | J18: =IF(F18=0,0,I18/F18) -> 0
A19: Julho | B19: =DAY(EOMONTH(DATE($B$3,7,1),0))*2 -> 62 | C19: =SUMPRODUCT((RESERVAS!$C$6:$C$203<DATE($B$3,8,1))*(RESERVAS!$D$6:$D$203>DATE($B$3,7,1))*(RESERVAS!$I$6:$I$203<>"Cancelada")*(RESERVAS!$I$6:$I$203<>"Consulta")*(((RESERVAS!$D$6:$D$203<DATE($B$3,8,1))*RESERVAS!$D$6:$D$203+(RESERVAS!$D$6:$D$203>=DATE($B$3,8,1))*DATE($B$3,8,1))-((RESERVAS!$C$6:$C$203>DATE($B$3,7,1))*RESERVAS!$C$6:$C$203+(RESERVAS!$C$6:$C$203<=DATE($B$3,7,1))*DATE($B$3,7,1)))) -> 0 | D19: =MAX(0,B19-C19) -> 62 | E19: =IF(B19=0,0,C19/B19) -> 0 | F19: =SUMPRODUCT((RESERVAS!$C$6:$C$203<DATE($B$3,8,1))*(RESERVAS!$D$6:$D$203>DATE($B$3,7,1))*(RESERVAS!$I$6:$I$203<>"Cancelada")*(RESERVAS!$I$6:$I$203<>"Consulta")*RESERVAS!$F$6:$F$203*(((RESERVAS!$D$6:$D$203<DATE($B$3,8,1))*RESERVAS!$D$6:$D$203+(RESERVAS!$D$6:$D$203>=DATE($B$3,8,1))*DATE($B$3,8,1))-((RESERVAS!$C$6:$C$203>DATE($B$3,7,1))*RESERVAS!$C$6:$C$203+(RESERVAS!$C$6:$C$203<=DATE($B$3,7,1))*DATE($B$3,7,1)))) -> 0 | G19: =SUMPRODUCT((RESERVAS!$C$6:$C$203<DATE($B$3,8,1))*(RESERVAS!$D$6:$D$203>DATE($B$3,7,1))*(RESERVAS!$I$6:$I$203<>"Cancelada")*(RESERVAS!$I$6:$I$203<>"Consulta")*RESERVAS!$T$6:$T$203*(((RESERVAS!$D$6:$D$203<DATE($B$3,8,1))*RESERVAS!$D$6:$D$203+(RESERVAS!$D$6:$D$203>=DATE($B$3,8,1))*DATE($B$3,8,1))-((RESERVAS!$C$6:$C$203>DATE($B$3,7,1))*RESERVAS!$C$6:$C$203+(RESERVAS!$C$6:$C$203<=DATE($B$3,7,1))*DATE($B$3,7,1)))) -> 0 | H19: =SUMIFS('DESPESAS CASA'!$D$6:$D$305,'DESPESAS CASA'!$A$6:$A$305,">="&DATE($B$3,7,1),'DESPESAS CASA'!$A$6:$A$305,"<"&DATE($B$3,8,1),'DESPESAS CASA'!$E$6:$E$305,"") -> 0 | I19: =F19-G19-H19 -> 0 | J19: =IF(F19=0,0,I19/F19) -> 0
A20: Agosto | B20: =DAY(EOMONTH(DATE($B$3,8,1),0))*2 -> 62 | C20: =SUMPRODUCT((RESERVAS!$C$6:$C$203<DATE($B$3,9,1))*(RESERVAS!$D$6:$D$203>DATE($B$3,8,1))*(RESERVAS!$I$6:$I$203<>"Cancelada")*(RESERVAS!$I$6:$I$203<>"Consulta")*(((RESERVAS!$D$6:$D$203<DATE($B$3,9,1))*RESERVAS!$D$6:$D$203+(RESERVAS!$D$6:$D$203>=DATE($B$3,9,1))*DATE($B$3,9,1))-((RESERVAS!$C$6:$C$203>DATE($B$3,8,1))*RESERVAS!$C$6:$C$203+(RESERVAS!$C$6:$C$203<=DATE($B$3,8,1))*DATE($B$3,8,1)))) -> 0 | D20: =MAX(0,B20-C20) -> 62 | E20: =IF(B20=0,0,C20/B20) -> 0 | F20: =SUMPRODUCT((RESERVAS!$C$6:$C$203<DATE($B$3,9,1))*(RESERVAS!$D$6:$D$203>DATE($B$3,8,1))*(RESERVAS!$I$6:$I$203<>"Cancelada")*(RESERVAS!$I$6:$I$203<>"Consulta")*RESERVAS!$F$6:$F$203*(((RESERVAS!$D$6:$D$203<DATE($B$3,9,1))*RESERVAS!$D$6:$D$203+(RESERVAS!$D$6:$D$203>=DATE($B$3,9,1))*DATE($B$3,9,1))-((RESERVAS!$C$6:$C$203>DATE($B$3,8,1))*RESERVAS!$C$6:$C$203+(RESERVAS!$C$6:$C$203<=DATE($B$3,8,1))*DATE($B$3,8,1)))) -> 0 | G20: =SUMPRODUCT((RESERVAS!$C$6:$C$203<DATE($B$3,9,1))*(RESERVAS!$D$6:$D$203>DATE($B$3,8,1))*(RESERVAS!$I$6:$I$203<>"Cancelada")*(RESERVAS!$I$6:$I$203<>"Consulta")*RESERVAS!$T$6:$T$203*(((RESERVAS!$D$6:$D$203<DATE($B$3,9,1))*RESERVAS!$D$6:$D$203+(RESERVAS!$D$6:$D$203>=DATE($B$3,9,1))*DATE($B$3,9,1))-((RESERVAS!$C$6:$C$203>DATE($B$3,8,1))*RESERVAS!$C$6:$C$203+(RESERVAS!$C$6:$C$203<=DATE($B$3,8,1))*DATE($B$3,8,1)))) -> 0 | H20: =SUMIFS('DESPESAS CASA'!$D$6:$D$305,'DESPESAS CASA'!$A$6:$A$305,">="&DATE($B$3,8,1),'DESPESAS CASA'!$A$6:$A$305,"<"&DATE($B$3,9,1),'DESPESAS CASA'!$E$6:$E$305,"") -> 0 | I20: =F20-G20-H20 -> 0 | J20: =IF(F20=0,0,I20/F20) -> 0
A21: Setembro | B21: =DAY(EOMONTH(DATE($B$3,9,1),0))*2 -> 60 | C21: =SUMPRODUCT((RESERVAS!$C$6:$C$203<DATE($B$3,10,1))*(RESERVAS!$D$6:$D$203>DATE($B$3,9,1))*(RESERVAS!$I$6:$I$203<>"Cancelada")*(RESERVAS!$I$6:$I$203<>"Consulta")*(((RESERVAS!$D$6:$D$203<DATE($B$3,10,1))*RESERVAS!$D$6:$D$203+(RESERVAS!$D$6:$D$203>=DATE($B$3,10,1))*DATE($B$3,10,1))-((RESERVAS!$C$6:$C$203>DATE($B$3,9,1))*RESERVAS!$C$6:$C$203+(RESERVAS!$C$6:$C$203<=DATE($B$3,9,1))*DATE($B$3,9,1)))) -> 8 | D21: =MAX(0,B21-C21) -> 52 | E21: =IF(B21=0,0,C21/B21) -> 0.13333333 | F21: =SUMPRODUCT((RESERVAS!$C$6:$C$203<DATE($B$3,10,1))*(RESERVAS!$D$6:$D$203>DATE($B$3,9,1))*(RESERVAS!$I$6:$I$203<>"Cancelada")*(RESERVAS!$I$6:$I$203<>"Consulta")*RESERVAS!$F$6:$F$203*(((RESERVAS!$D$6:$D$203<DATE($B$3,10,1))*RESERVAS!$D$6:$D$203+(RESERVAS!$D$6:$D$203>=DATE($B$3,10,1))*DATE($B$3,10,1))-((RESERVAS!$C$6:$C$203>DATE($B$3,9,1))*RESERVAS!$C$6:$C$203+(RESERVAS!$C$6:$C$203<=DATE($B$3,9,1))*DATE($B$3,9,1)))) -> 2800 | G21: =SUMPRODUCT((RESERVAS!$C$6:$C$203<DATE($B$3,10,1))*(RESERVAS!$D$6:$D$203>DATE($B$3,9,1))*(RESERVAS!$I$6:$I$203<>"Cancelada")*(RESERVAS!$I$6:$I$203<>"Consulta")*RESERVAS!$T$6:$T$203*(((RESERVAS!$D$6:$D$203<DATE($B$3,10,1))*RESERVAS!$D$6:$D$203+(RESERVAS!$D$6:$D$203>=DATE($B$3,10,1))*DATE($B$3,10,1))-((RESERVAS!$C$6:$C$203>DATE($B$3,9,1))*RESERVAS!$C$6:$C$203+(RESERVAS!$C$6:$C$203<=DATE($B$3,9,1))*DATE($B$3,9,1)))) -> 32.05 | H21: =SUMIFS('DESPESAS CASA'!$D$6:$D$305,'DESPESAS CASA'!$A$6:$A$305,">="&DATE($B$3,9,1),'DESPESAS CASA'!$A$6:$A$305,"<"&DATE($B$3,10,1),'DESPESAS CASA'!$E$6:$E$305,"") -> 0 | I21: =F21-G21-H21 -> 2767.95 | J21: =IF(F21=0,0,I21/F21) -> 0.98855357
A22: Outubro | B22: =DAY(EOMONTH(DATE($B$3,10,1),0))*2 -> 62 | C22: =SUMPRODUCT((RESERVAS!$C$6:$C$203<DATE($B$3,11,1))*(RESERVAS!$D$6:$D$203>DATE($B$3,10,1))*(RESERVAS!$I$6:$I$203<>"Cancelada")*(RESERVAS!$I$6:$I$203<>"Consulta")*(((RESERVAS!$D$6:$D$203<DATE($B$3,11,1))*RESERVAS!$D$6:$D$203+(RESERVAS!$D$6:$D$203>=DATE($B$3,11,1))*DATE($B$3,11,1))-((RESERVAS!$C$6:$C$203>DATE($B$3,10,1))*RESERVAS!$C$6:$C$203+(RESERVAS!$C$6:$C$203<=DATE($B$3,10,1))*DATE($B$3,10,1)))) -> 12 | D22: =MAX(0,B22-C22) -> 50 | E22: =IF(B22=0,0,C22/B22) -> 0.19354839 | F22: =SUMPRODUCT((RESERVAS!$C$6:$C$203<DATE($B$3,11,1))*(RESERVAS!$D$6:$D$203>DATE($B$3,10,1))*(RESERVAS!$I$6:$I$203<>"Cancelada")*(RESERVAS!$I$6:$I$203<>"Consulta")*RESERVAS!$F$6:$F$203*(((RESERVAS!$D$6:$D$203<DATE($B$3,11,1))*RESERVAS!$D$6:$D$203+(RESERVAS!$D$6:$D$203>=DATE($B$3,11,1))*DATE($B$3,11,1))-((RESERVAS!$C$6:$C$203>DATE($B$3,10,1))*RESERVAS!$C$6:$C$203+(RESERVAS!$C$6:$C$203<=DATE($B$3,10,1))*DATE($B$3,10,1)))) -> 4909.675 | G22: =SUMPRODUCT((RESERVAS!$C$6:$C$203<DATE($B$3,11,1))*(RESERVAS!$D$6:$D$203>DATE($B$3,10,1))*(RESERVAS!$I$6:$I$203<>"Cancelada")*(RESERVAS!$I$6:$I$203<>"Consulta")*RESERVAS!$T$6:$T$203*(((RESERVAS!$D$6:$D$203<DATE($B$3,11,1))*RESERVAS!$D$6:$D$203+(RESERVAS!$D$6:$D$203>=DATE($B$3,11,1))*DATE($B$3,11,1))-((RESERVAS!$C$6:$C$203>DATE($B$3,10,1))*RESERVAS!$C$6:$C$203+(RESERVAS!$C$6:$C$203<=DATE($B$3,10,1))*DATE($B$3,10,1)))) -> 0 | H22: =SUMIFS('DESPESAS CASA'!$D$6:$D$305,'DESPESAS CASA'!$A$6:$A$305,">="&DATE($B$3,10,1),'DESPESAS CASA'!$A$6:$A$305,"<"&DATE($B$3,11,1),'DESPESAS CASA'!$E$6:$E$305,"") -> 0 | I22: =F22-G22-H22 -> 4909.675 | J22: =IF(F22=0,0,I22/F22) -> 1
A23: Novembro | B23: =DAY(EOMONTH(DATE($B$3,11,1),0))*2 -> 60 | C23: =SUMPRODUCT((RESERVAS!$C$6:$C$203<DATE($B$3,12,1))*(RESERVAS!$D$6:$D$203>DATE($B$3,11,1))*(RESERVAS!$I$6:$I$203<>"Cancelada")*(RESERVAS!$I$6:$I$203<>"Consulta")*(((RESERVAS!$D$6:$D$203<DATE($B$3,12,1))*RESERVAS!$D$6:$D$203+(RESERVAS!$D$6:$D$203>=DATE($B$3,12,1))*DATE($B$3,12,1))-((RESERVAS!$C$6:$C$203>DATE($B$3,11,1))*RESERVAS!$C$6:$C$203+(RESERVAS!$C$6:$C$203<=DATE($B$3,11,1))*DATE($B$3,11,1)))) -> 17 | D23: =MAX(0,B23-C23) -> 43 | E23: =IF(B23=0,0,C23/B23) -> 0.28333333 | F23: =SUMPRODUCT((RESERVAS!$C$6:$C$203<DATE($B$3,12,1))*(RESERVAS!$D$6:$D$203>DATE($B$3,11,1))*(RESERVAS!$I$6:$I$203<>"Cancelada")*(RESERVAS!$I$6:$I$203<>"Consulta")*RESERVAS!$F$6:$F$203*(((RESERVAS!$D$6:$D$203<DATE($B$3,12,1))*RESERVAS!$D$6:$D$203+(RESERVAS!$D$6:$D$203>=DATE($B$3,12,1))*DATE($B$3,12,1))-((RESERVAS!$C$6:$C$203>DATE($B$3,11,1))*RESERVAS!$C$6:$C$203+(RESERVAS!$C$6:$C$203<=DATE($B$3,11,1))*DATE($B$3,11,1)))) -> 7431.995 | G23: =SUMPRODUCT((RESERVAS!$C$6:$C$203<DATE($B$3,12,1))*(RESERVAS!$D$6:$D$203>DATE($B$3,11,1))*(RESERVAS!$I$6:$I$203<>"Cancelada")*(RESERVAS!$I$6:$I$203<>"Consulta")*RESERVAS!$T$6:$T$203*(((RESERVAS!$D$6:$D$203<DATE($B$3,12,1))*RESERVAS!$D$6:$D$203+(RESERVAS!$D$6:$D$203>=DATE($B$3,12,1))*DATE($B$3,12,1))-((RESERVAS!$C$6:$C$203>DATE($B$3,11,1))*RESERVAS!$C$6:$C$203+(RESERVAS!$C$6:$C$203<=DATE($B$3,11,1))*DATE($B$3,11,1)))) -> 0 | H23: =SUMIFS('DESPESAS CASA'!$D$6:$D$305,'DESPESAS CASA'!$A$6:$A$305,">="&DATE($B$3,11,1),'DESPESAS CASA'!$A$6:$A$305,"<"&DATE($B$3,12,1),'DESPESAS CASA'!$E$6:$E$305,"") -> 0 | I23: =F23-G23-H23 -> 7431.995 | J23: =IF(F23=0,0,I23/F23) -> 1
A24: Dezembro | B24: =DAY(EOMONTH(DATE($B$3,12,1),0))*2 -> 62 | C24: =SUMPRODUCT((RESERVAS!$C$6:$C$203<DATE($B$3,13,1))*(RESERVAS!$D$6:$D$203>DATE($B$3,12,1))*(RESERVAS!$I$6:$I$203<>"Cancelada")*(RESERVAS!$I$6:$I$203<>"Consulta")*(((RESERVAS!$D$6:$D$203<DATE($B$3,13,1))*RESERVAS!$D$6:$D$203+(RESERVAS!$D$6:$D$203>=DATE($B$3,13,1))*DATE($B$3,13,1))-((RESERVAS!$C$6:$C$203>DATE($B$3,12,1))*RESERVAS!$C$6:$C$203+(RESERVAS!$C$6:$C$203<=DATE($B$3,12,1))*DATE($B$3,12,1)))) -> 16 | D24: =MAX(0,B24-C24) -> 46 | E24: =IF(B24=0,0,C24/B24) -> 0.25806452 | F24: =SUMPRODUCT((RESERVAS!$C$6:$C$203<DATE($B$3,13,1))*(RESERVAS!$D$6:$D$203>DATE($B$3,12,1))*(RESERVAS!$I$6:$I$203<>"Cancelada")*(RESERVAS!$I$6:$I$203<>"Consulta")*RESERVAS!$F$6:$F$203*(((RESERVAS!$D$6:$D$203<DATE($B$3,13,1))*RESERVAS!$D$6:$D$203+(RESERVAS!$D$6:$D$203>=DATE($B$3,13,1))*DATE($B$3,13,1))-((RESERVAS!$C$6:$C$203>DATE($B$3,12,1))*RESERVAS!$C$6:$C$203+(RESERVAS!$C$6:$C$203<=DATE($B$3,12,1))*DATE($B$3,12,1)))) -> 13400 | G24: =SUMPRODUCT((RESERVAS!$C$6:$C$203<DATE($B$3,13,1))*(RESERVAS!$D$6:$D$203>DATE($B$3,12,1))*(RESERVAS!$I$6:$I$203<>"Cancelada")*(RESERVAS!$I$6:$I$203<>"Consulta")*RESERVAS!$T$6:$T$203*(((RESERVAS!$D$6:$D$203<DATE($B$3,13,1))*RESERVAS!$D$6:$D$203+(RESERVAS!$D$6:$D$203>=DATE($B$3,13,1))*DATE($B$3,13,1))-((RESERVAS!$C$6:$C$203>DATE($B$3,12,1))*RESERVAS!$C$6:$C$203+(RESERVAS!$C$6:$C$203<=DATE($B$3,12,1))*DATE($B$3,12,1)))) -> 0 | H24: =SUMIFS('DESPESAS CASA'!$D$6:$D$305,'DESPESAS CASA'!$A$6:$A$305,">="&DATE($B$3,12,1),'DESPESAS CASA'!$A$6:$A$305,"<"&DATE($B$3,13,1),'DESPESAS CASA'!$E$6:$E$305,"") -> 0 | I24: =F24-G24-H24 -> 13400 | J24: =IF(F24=0,0,I24/F24) -> 1

Sheet AGENDA
A1: AGENDA — DISPONIBILIDADE DA CASA
A2: Mês | B2: Setembro | D2: Ano | E2: 2026 | J2: Nº mês | K2: =MATCH(B2,LISTAS!$A$4:$A$15,0) -> 9
A4: SEG | B4: TER | C4: QUA | D4: QUI | E4: SEX | F4: SÁB | G4: DOM | I4: RESUMO DO MÊS
A5: =IF(MONTH((DATE($E$2,$K$2,1)-WEEKDAY(DATE($E$2,$K$2,1),2)+1+0))<>$K$2,"",TEXT((DATE($E$2,$K$2,1)-WEEKDAY(DATE($E$2,$K$2,1),2)+1+0),"dd")&CHAR(10)&IF(COUNTIFS(RESERVAS!$C$6:$C$203,"<="&(DATE($E$2,$K$2,1)-WEEKDAY(DATE($E$2,$K$2,1),2)+1+0),RESERVAS!$D$6:$D$203,">"&(DATE($E$2,$K$2,1)-WEEKDAY(DATE($E$2,$K$2,1),2)+1+0),RESERVAS!$I$6:$I$203,"<>Cancelada",RESERVAS!$I$6:$I$203,"<>Consulta")=0,"DISPONÍVEL",IF(COUNTIFS(RESERVAS!$C$6:$C$203,"<="&(DATE($E$2,$K$2,1)-WEEKDAY(DATE($E$2,$K$2,1),2)+1+0),RESERVAS!$D$6:$D$203,">"&(DATE($E$2,$K$2,1)-WEEKDAY(DATE($E$2,$K$2,1),2)+1+0),RESERVAS!$I$6:$I$203,"<>Cancelada",RESERVAS!$I$6:$I$203,"<>Consulta")=1,"ALUGADA","CONFLITO"))&IF(COUNTIFS(RESERVAS!$C$6:$C$203,"<="&(DATE($E$2,$K$2,1)-WEEKDAY(DATE($E$2,$K$2,1),2)+1+0),RESERVAS!$D$6:$D$203,">"&(DATE($E$2,$K$2,1)-WEEKDAY(DATE($E$2,$K$2,1),2)+1+0),RESERVAS!$I$6:$I$203,"<>Cancelada",RESERVAS!$I$6:$I$203,"<>Consulta")=0,"",CHAR(10)&IFERROR(LOOKUP(2,1/((RESERVAS!$C$6:$C$203<=(DATE($E$2,$K$2,1)-WEEKDAY(DATE($E$2,$K$2,1),2)+1+0))*(RESERVAS!$D$6:$D$203>(DATE($E$2,$K$2,1)-WEEKDAY(DATE($E$2,$K$2,1),2)+1+0))*(RESERVAS!$I$6:$I$203<>"Cancelada")*(RESERVAS!$I$6:$I$203<>"Consulta")),RESERVAS!$B$6:$B$203),""))) | B5: =IF(MONTH((DATE($E$2,$K$2,1)-WEEKDAY(DATE($E$2,$K$2,1),2)+1+1))<>$K$2,"",TEXT((DATE($E$2,$K$2,1)-WEEKDAY(DATE($E$2,$K$2,1),2)+1+1),"dd")&CHAR(10)&IF(COUNTIFS(RESERVAS!$C$6:$C$203,"<="&(DATE($E$2,$K$2,1)-WEEKDAY(DATE($E$2,$K$2,1),2)+1+1),RESERVAS!$D$6:$D$203,">"&(DATE($E$2,$K$2,1)-WEEKDAY(DATE($E$2,$K$2,1),2)+1+1),RESERVAS!$I$6:$I$203,"<>Cancelada",RESERVAS!$I$6:$I$203,"<>Consulta")=0,"DISPONÍVEL",IF(COUNTIFS(RESERVAS!$C$6:$C$203,"<="&(DATE($E$2,$K$2,1)-WEEKDAY(DATE($E$2,$K$2,1),2)+1+1),RESERVAS!$D$6:$D$203,">"&(DATE($E$2,$K$2,1)-WEEKDAY(DATE($E$2,$K$2,1),2)+1+1),RESERVAS!$I$6:$I$203,"<>Cancelada",RESERVAS!$I$6:$I$203,"<>Consulta")=1,"ALUGADA","CONFLITO"))&IF(COUNTIFS(RESERVAS!$C$6:$C$203,"<="&(DATE($E$2,$K$2,1)-WEEKDAY(DATE($E$2,$K$2,1),2)+1+1),RESERVAS!$D$6:$D$203,">"&(DATE($E$2,$K$2,1)-WEEKDAY(DATE($E$2,$K$2,1),2)+1+1),RESERVAS!$I$6:$I$203,"<>Cancelada",RESERVAS!$I$6:$I$203,"<>Consulta")=0,"",CHAR(10)&IFERROR(LOOKUP(2,1/((RESERVAS!$C$6:$C$203<=(DATE($E$2,$K$2,1)-WEEKDAY(DATE($E$2,$K$2,1),2)+1+1))*(RESERVAS!$D$6:$D$203>(DATE($E$2,$K$2,1)-WEEKDAY(DATE($E$2,$K$2,1),2)+1+1))*(RESERVAS!$I$6:$I$203<>"Cancelada")*(RESERVAS!$I$6:$I$203<>"Consulta")),RESERVAS!$B$6:$B$203),""))) -> 01 DISPONÍVEL | C5: =IF(MONTH((DATE($E$2,$K$2,1)-WEEKDAY(DATE($E$2,$K$2,1),2)+1+2))<>$K$2,"",TEXT((DATE($E$2,$K$2,1)-WEEKDAY(DATE($E$2,$K$2,1),2)+1+2),"dd")&CHAR(10)&IF(COUNTIFS(RESERVAS!$C$6:$C$203,"<="&(DATE($E$2,$K$2,1)-WEEKDAY(DATE($E$2,$K$2,1),2)+1+2),RESERVAS!$D$6:$D$203,">"&(DATE($E$2,$K$2,1)-WEEKDAY(DATE($E$2,$K$2,1),2)+1+2),RESERVAS!$I$6:$I$203,"<>Cancelada",RESERVAS!$I$6:$I$203,"<>Consulta")=0,"DISPONÍVEL",IF(COUNTIFS(RESERVAS!$C$6:$C$203,"<="&(DATE($E$2,$K$2,1)-WEEKDAY(DATE($E$2,$K$2,1),2)+1+2),RESERVAS!$D$6:$D$203,">"&(DATE($E$2,$K$2,1)-WEEKDAY(DATE($E$2,$K$2,1),2)+1+2),RESERVAS!$I$6:$I$203,"<>Cancelada",RESERVAS!$I$6:$I$203,"<>Consulta")=1,"ALUGADA","CONFLITO"))&IF(COUNTIFS(RESERVAS!$C$6:$C$203,"<="&(DATE($E$2,$K$2,1)-WEEKDAY(DATE($E$2,$K$2,1),2)+1+2),RESERVAS!$D$6:$D$203,">"&(DATE($E$2,$K$2,1)-WEEKDAY(DATE($E$2,$K$2,1),2)+1+2),RESERVAS!$I$6:$I$203,"<>Cancelada",RESERVAS!$I$6:$I$203,"<>Consulta")=0,"",CHAR(10)&IFERROR(LOOKUP(2,1/((RESERVAS!$C$6:$C$203<=(DATE($E$2,$K$2,1)-WEEKDAY(DATE($E$2,$K$2,1),2)+1+2))*(RESERVAS!$D$6:$D$203>(DATE($E$2,$K$2,1)-WEEKDAY(DATE($E$2,$K$2,1),2)+1+2))*(RESERVAS!$I$6:$I$203<>"Cancelada")*(RESERVAS!$I$6:$I$203<>"Consulta")),RESERVAS!$B$6:$B$203),""))) -> 02 DISPONÍVEL | D5: =IF(MONTH((DATE($E$2,$K$2,1)-WEEKDAY(DATE($E$2,$K$2,1),2)+1+3))<>$K$2,"",TEXT((DATE($E$2,$K$2,1)-WEEKDAY(DATE($E$2,$K$2,1),2)+1+3),"dd")&CHAR(10)&IF(COUNTIFS(RESERVAS!$C$6:$C$203,"<="&(DATE($E$2,$K$2,1)-WEEKDAY(DATE($E$2,$K$2,1),2)+1+3),RESERVAS!$D$6:$D$203,">"&(DATE($E$2,$K$2,1)-WEEKDAY(DATE($E$2,$K$2,1),2)+1+3),RESERVAS!$I$6:$I$203,"<>Cancelada",RESERVAS!$I$6:$I$203,"<>Consulta")=0,"DISPONÍVEL",IF(COUNTIFS(RESERVAS!$C$6:$C$203,"<="&(DATE($E$2,$K$2,1)-WEEKDAY(DATE($E$2,$K$2,1),2)+1+3),RESERVAS!$D$6:$D$203,">"&(DATE($E$2,$K$2,1)-WEEKDAY(DATE($E$2,$K$2,1),2)+1+3),RESERVAS!$I$6:$I$203,"<>Cancelada",RESERVAS!$I$6:$I$203,"<>Consulta")=1,"ALUGADA","CONFLITO"))&IF(COUNTIFS(RESERVAS!$C$6:$C$203,"<="&(DATE($E$2,$K$2,1)-WEEKDAY(DATE($E$2,$K$2,1),2)+1+3),RESERVAS!$D$6:$D$203,">"&(DATE($E$2,$K$2,1)-WEEKDAY(DATE($E$2,$K$2,1),2)+1+3),RESERVAS!$I$6:$I$203,"<>Cancelada",RESERVAS!$I$6:$I$203,"<>Consulta")=0,"",CHAR(10)&IFERROR(LOOKUP(2,1/((RESERVAS!$C$6:$C$203<=(DATE($E$2,$K$2,1)-WEEKDAY(DATE($E$2,$K$2,1),2)+1+3))*(RESERVAS!$D$6:$D$203>(DATE($E$2,$K$2,1)-WEEKDAY(DATE($E$2,$K$2,1),2)+1+3))*(RESERVAS!$I$6:$I$203<>"Cancelada")*(RESERVAS!$I$6:$I$203<>"Consulta")),RESERVAS!$B$6:$B$203),""))) -> 03 DISPONÍVEL | E5: =IF(MONTH((DATE($E$2,$K$2,1)-WEEKDAY(DATE($E$2,$K$2,1),2)+1+4))<>$K$2,"",TEXT((DATE($E$2,$K$2,1)-WEEKDAY(DATE($E$2,$K$2,1),2)+1+4),"dd")&CHAR(10)&IF(COUNTIFS(RESERVAS!$C$6:$C$203,"<="&(DATE($E$2,$K$2,1)-WEEKDAY(DATE($E$2,$K$2,1),2)+1+4),RESERVAS!$D$6:$D$203,">"&(DATE($E$2,$K$2,1)-WEEKDAY(DATE($E$2,$K$2,1),2)+1+4),RESERVAS!$I$6:$I$203,"<>Cancelada",RESERVAS!$I$6:$I$203,"<>Consulta")=0,"DISPONÍVEL",IF(COUNTIFS(RESERVAS!$C$6:$C$203,"<="&(DATE($E$2,$K$2,1)-WEEKDAY(DATE($E$2,$K$2,1),2)+1+4),RESERVAS!$D$6:$D$203,">"&(DATE($E$2,$K$2,1)-WEEKDAY(DATE($E$2,$K$2,1),2)+1+4),RESERVAS!$I$6:$I$203,"<>Cancelada",RESERVAS!$I$6:$I$203,"<>Consulta")=1,"ALUGADA","CONFLITO"))&IF(COUNTIFS(RESERVAS!$C$6:$C$203,"<="&(DATE($E$2,$K$2,1)-WEEKDAY(DATE($E$2,$K$2,1),2)+1+4),RESERVAS!$D$6:$D$203,">"&(DATE($E$2,$K$2,1)-WEEKDAY(DATE($E$2,$K$2,1),2)+1+4),RESERVAS!$I$6:$I$203,"<>Cancelada",RESERVAS!$I$6:$I$203,"<>Consulta")=0,"",CHAR(10)&IFERROR(LOOKUP(2,1/((RESERVAS!$C$6:$C$203<=(DATE($E$2,$K$2,1)-WEEKDAY(DATE($E$2,$K$2,1),2)+1+4))*(RESERVAS!$D$6:$D$203>(DATE($E$2,$K$2,1)-WEEKDAY(DATE($E$2,$K$2,1),2)+1+4))*(RESERVAS!$I$6:$I$203<>"Cancelada")*(RESERVAS!$I$6:$I$203<>"Consulta")),RESERVAS!$B$6:$B$203),""))) -> 04 ALUGADA Regina - 7 de Setembro | F5: =IF(MONTH((DATE($E$2,$K$2,1)-WEEKDAY(DATE($E$2,$K$2,1),2)+1+5))<>$K$2,"",TEXT((DATE($E$2,$K$2,1)-WEEKDAY(DATE($E$2,$K$2,1),2)+1+5),"dd")&CHAR(10)&IF(COUNTIFS(RESERVAS!$C$6:$C$203,"<="&(DATE($E$2,$K$2,1)-WEEKDAY(DATE($E$2,$K$2,1),2)+1+5),RESERVAS!$D$6:$D$203,">"&(DATE($E$2,$K$2,1)-WEEKDAY(DATE($E$2,$K$2,1),2)+1+5),RESERVAS!$I$6:$I$203,"<>Cancelada",RESERVAS!$I$6:$I$203,"<>Consulta")=0,"DISPONÍVEL",IF(COUNTIFS(RESERVAS!$C$6:$C$203,"<="&(DATE($E$2,$K$2,1)-WEEKDAY(DATE($E$2,$K$2,1),2)+1+5),RESERVAS!$D$6:$D$203,">"&(DATE($E$2,$K$2,1)-WEEKDAY(DATE($E$2,$K$2,1),2)+1+5),RESERVAS!$I$6:$I$203,"<>Cancelada",RESERVAS!$I$6:$I$203,"<>Consulta")=1,"ALUGADA","CONFLITO"))&IF(COUNTIFS(RESERVAS!$C$6:$C$203,"<="&(DATE($E$2,$K$2,1)-WEEKDAY(DATE($E$2,$K$2,1),2)+1+5),RESERVAS!$D$6:$D$203,">"&(DATE($E$2,$K$2,1)-WEEKDAY(DATE($E$2,$K$2,1),2)+1+5),RESERVAS!$I$6:$I$203,"<>Cancelada",RESERVAS!$I$6:$I$203,"<>Consulta")=0,"",CHAR(10)&IFERROR(LOOKUP(2,1/((RESERVAS!$C$6:$C$203<=(DATE($E$2,$K$2,1)-WEEKDAY(DATE($E$2,$K$2,1),2)+1+5))*(RESERVAS!$D$6:$D$203>(DATE($E$2,$K$2,1)-WEEKDAY(DATE($E$2,$K$2,1),2)+1+5))*(RESERVAS!$I$6:$I$203<>"Cancelada")*(RESERVAS!$I$6:$I$203<>"Consulta")),RESERVAS!$B$6:$B$203),""))) -> 05 ALUGADA Regina - 7 de Setembro | G5: =IF(MONTH((DATE($E$2,$K$2,1)-WEEKDAY(DATE($E$2,$K$2,1),2)+1+6))<>$K$2,"",TEXT((DATE($E$2,$K$2,1)-WEEKDAY(DATE($E$2,$K$2,1),2)+1+6),"dd")&CHAR(10)&IF(COUNTIFS(RESERVAS!$C$6:$C$203,"<="&(DATE($E$2,$K$2,1)-WEEKDAY(DATE($E$2,$K$2,1),2)+1+6),RESERVAS!$D$6:$D$203,">"&(DATE($E$2,$K$2,1)-WEEKDAY(DATE($E$2,$K$2,1),2)+1+6),RESERVAS!$I$6:$I$203,"<>Cancelada",RESERVAS!$I$6:$I$203,"<>Consulta")=0,"DISPONÍVEL",IF(COUNTIFS(RESERVAS!$C$6:$C$203,"<="&(DATE($E$2,$K$2,1)-WEEKDAY(DATE($E$2,$K$2,1),2)+1+6),RESERVAS!$D$6:$D$203,">"&(DATE($E$2,$K$2,1)-WEEKDAY(DATE($E$2,$K$2,1),2)+1+6),RESERVAS!$I$6:$I$203,"<>Cancelada",RESERVAS!$I$6:$I$203,"<>Consulta")=1,"ALUGADA","CONFLITO"))&IF(COUNTIFS(RESERVAS!$C$6:$C$203,"<="&(DATE($E$2,$K$2,1)-WEEKDAY(DATE($E$2,$K$2,1),2)+1+6),RESERVAS!$D$6:$D$203,">"&(DATE($E$2,$K$2,1)-WEEKDAY(DATE($E$2,$K$2,1),2)+1+6),RESERVAS!$I$6:$I$203,"<>Cancelada",RESERVAS!$I$6:$I$203,"<>Consulta")=0,"",CHAR(10)&IFERROR(LOOKUP(2,1/((RESERVAS!$C$6:$C$203<=(DATE($E$2,$K$2,1)-WEEKDAY(DATE($E$2,$K$2,1),2)+1+6))*(RESERVAS!$D$6:$D$203>(DATE($E$2,$K$2,1)-WEEKDAY(DATE($E$2,$K$2,1),2)+1+6))*(RESERVAS!$I$6:$I$203<>"Cancelada")*(RESERVAS!$I$6:$I$203<>"Consulta")),RESERVAS!$B$6:$B$203),""))) -> 06 ALUGADA Regina - 7 de Setembro | I5: Receita (R$) | J5: =SUMPRODUCT((RESERVAS!$C$6:$C$203<DATE($E$2,$K$2+1,1))*(RESERVAS!$D$6:$D$203>DATE($E$2,$K$2,1))*(RESERVAS!$I$6:$I$203<>"Cancelada")*(RESERVAS!$I$6:$I$203<>"Consulta")*RESERVAS!$F$6:$F$203*(((RESERVAS!$D$6:$D$203<DATE($E$2,$K$2+1,1))*RESERVAS!$D$6:$D$203+(RESERVAS!$D$6:$D$203>=DATE($E$2,$K$2+1,1))*DATE($E$2,$K$2+1,1))-((RESERVAS!$C$6:$C$203>DATE($E$2,$K$2,1))*RESERVAS!$C$6:$C$203+(RESERVAS!$C$6:$C$203<=DATE($E$2,$K$2,1))*DATE($E$2,$K$2,1)))) -> 2800
A6: =IF(MONTH((DATE($E$2,$K$2,1)-WEEKDAY(DATE($E$2,$K$2,1),2)+1+7))<>$K$2,"",TEXT((DATE($E$2,$K$2,1)-WEEKDAY(DATE($E$2,$K$2,1),2)+1+7),"dd")&CHAR(10)&IF(COUNTIFS(RESERVAS!$C$6:$C$203,"<="&(DATE($E$2,$K$2,1)-WEEKDAY(DATE($E$2,$K$2,1),2)+1+7),RESERVAS!$D$6:$D$203,">"&(DATE($E$2,$K$2,1)-WEEKDAY(DATE($E$2,$K$2,1),2)+1+7),RESERVAS!$I$6:$I$203,"<>Cancelada",RESERVAS!$I$6:$I$203,"<>Consulta")=0,"DISPONÍVEL",IF(COUNTIFS(RESERVAS!$C$6:$C$203,"<="&(DATE($E$2,$K$2,1)-WEEKDAY(DATE($E$2,$K$2,1),2)+1+7),RESERVAS!$D$6:$D$203,">"&(DATE($E$2,$K$2,1)-WEEKDAY(DATE($E$2,$K$2,1),2)+1+7),RESERVAS!$I$6:$I$203,"<>Cancelada",RESERVAS!$I$6:$I$203,"<>Consulta")=1,"ALUGADA","CONFLITO"))&IF(COUNTIFS(RESERVAS!$C$6:$C$203,"<="&(DATE($E$2,$K$2,1)-WEEKDAY(DATE($E$2,$K$2,1),2)+1+7),RESERVAS!$D$6:$D$203,">"&(DATE($E$2,$K$2,1)-WEEKDAY(DATE($E$2,$K$2,1),2)+1+7),RESERVAS!$I$6:$I$203,"<>Cancelada",RESERVAS!$I$6:$I$203,"<>Consulta")=0,"",CHAR(10)&IFERROR(LOOKUP(2,1/((RESERVAS!$C$6:$C$203<=(DATE($E$2,$K$2,1)-WEEKDAY(DATE($E$2,$K$2,1),2)+1+7))*(RESERVAS!$D$6:$D$203>(DATE($E$2,$K$2,1)-WEEKDAY(DATE($E$2,$K$2,1),2)+1+7))*(RESERVAS!$I$6:$I$203<>"Cancelada")*(RESERVAS!$I$6:$I$203<>"Consulta")),RESERVAS!$B$6:$B$203),""))) -> 07 ALUGADA Regina - 7 de Setembro | B6: =IF(MONTH((DATE($E$2,$K$2,1)-WEEKDAY(DATE($E$2,$K$2,1),2)+1+8))<>$K$2,"",TEXT((DATE($E$2,$K$2,1)-WEEKDAY(DATE($E$2,$K$2,1),2)+1+8),"dd")&CHAR(10)&IF(COUNTIFS(RESERVAS!$C$6:$C$203,"<="&(DATE($E$2,$K$2,1)-WEEKDAY(DATE($E$2,$K$2,1),2)+1+8),RESERVAS!$D$6:$D$203,">"&(DATE($E$2,$K$2,1)-WEEKDAY(DATE($E$2,$K$2,1),2)+1+8),RESERVAS!$I$6:$I$203,"<>Cancelada",RESERVAS!$I$6:$I$203,"<>Consulta")=0,"DISPONÍVEL",IF(COUNTIFS(RESERVAS!$C$6:$C$203,"<="&(DATE($E$2,$K$2,1)-WEEKDAY(DATE($E$2,$K$2,1),2)+1+8),RESERVAS!$D$6:$D$203,">"&(DATE($E$2,$K$2,1)-WEEKDAY(DATE($E$2,$K$2,1),2)+1+8),RESERVAS!$I$6:$I$203,"<>Cancelada",RESERVAS!$I$6:$I$203,"<>Consulta")=1,"ALUGADA","CONFLITO"))&IF(COUNTIFS(RESERVAS!$C$6:$C$203,"<="&(DATE($E$2,$K$2,1)-WEEKDAY(DATE($E$2,$K$2,1),2)+1+8),RESERVAS!$D$6:$D$203,">"&(DATE($E$2,$K$2,1)-WEEKDAY(DATE($E$2,$K$2,1),2)+1+8),RESERVAS!$I$6:$I$203,"<>Cancelada",RESERVAS!$I$6:$I$203,"<>Consulta")=0,"",CHAR(10)&IFERROR(LOOKUP(2,1/((RESERVAS!$C$6:$C$203<=(DATE($E$2,$K$2,1)-WEEKDAY(DATE($E$2,$K$2,1),2)+1+8))*(RESERVAS!$D$6:$D$203>(DATE($E$2,$K$2,1)-WEEKDAY(DATE($E$2,$K$2,1),2)+1+8))*(RESERVAS!$I$6:$I$203<>"Cancelada")*(RESERVAS!$I$6:$I$203<>"Consulta")),RESERVAS!$B$6:$B$203),""))) -> 08 DISPONÍVEL | C6: =IF(MONTH((DATE($E$2,$K$2,1)-WEEKDAY(DATE($E$2,$K$2,1),2)+1+9))<>$K$2,"",TEXT((DATE($E$2,$K$2,1)-WEEKDAY(DATE($E$2,$K$2,1),2)+1+9),"dd")&CHAR(10)&IF(COUNTIFS(RESERVAS!$C$6:$C$203,"<="&(DATE($E$2,$K$2,1)-WEEKDAY(DATE($E$2,$K$2,1),2)+1+9),RESERVAS!$D$6:$D$203,">"&(DATE($E$2,$K$2,1)-WEEKDAY(DATE($E$2,$K$2,1),2)+1+9),RESERVAS!$I$6:$I$203,"<>Cancelada",RESERVAS!$I$6:$I$203,"<>Consulta")=0,"DISPONÍVEL",IF(COUNTIFS(RESERVAS!$C$6:$C$203,"<="&(DATE($E$2,$K$2,1)-WEEKDAY(DATE($E$2,$K$2,1),2)+1+9),RESERVAS!$D$6:$D$203,">"&(DATE($E$2,$K$2,1)-WEEKDAY(DATE($E$2,$K$2,1),2)+1+9),RESERVAS!$I$6:$I$203,"<>Cancelada",RESERVAS!$I$6:$I$203,"<>Consulta")=1,"ALUGADA","CONFLITO"))&IF(COUNTIFS(RESERVAS!$C$6:$C$203,"<="&(DATE($E$2,$K$2,1)-WEEKDAY(DATE($E$2,$K$2,1),2)+1+9),RESERVAS!$D$6:$D$203,">"&(DATE($E$2,$K$2,1)-WEEKDAY(DATE($E$2,$K$2,1),2)+1+9),RESERVAS!$I$6:$I$203,"<>Cancelada",RESERVAS!$I$6:$I$203,"<>Consulta")=0,"",CHAR(10)&IFERROR(LOOKUP(2,1/((RESERVAS!$C$6:$C$203<=(DATE($E$2,$K$2,1)-WEEKDAY(DATE($E$2,$K$2,1),2)+1+9))*(RESERVAS!$D$6:$D$203>(DATE($E$2,$K$2,1)-WEEKDAY(DATE($E$2,$K$2,1),2)+1+9))*(RESERVAS!$I$6:$I$203<>"Cancelada")*(RESERVAS!$I$6:$I$203<>"Consulta")),RESERVAS!$B$6:$B$203),""))) -> 09 DISPONÍVEL | D6: =IF(MONTH((DATE($E$2,$K$2,1)-WEEKDAY(DATE($E$2,$K$2,1),2)+1+10))<>$K$2,"",TEXT((DATE($E$2,$K$2,1)-WEEKDAY(DATE($E$2,$K$2,1),2)+1+10),"dd")&CHAR(10)&IF(COUNTIFS(RESERVAS!$C$6:$C$203,"<="&(DATE($E$2,$K$2,1)-WEEKDAY(DATE($E$2,$K$2,1),2)+1+10),RESERVAS!$D$6:$D$203,">"&(DATE($E$2,$K$2,1)-WEEKDAY(DATE($E$2,$K$2,1),2)+1+10),RESERVAS!$I$6:$I$203,"<>Cancelada",RESERVAS!$I$6:$I$203,"<>Consulta")=0,"DISPONÍVEL",IF(COUNTIFS(RESERVAS!$C$6:$C$203,"<="&(DATE($E$2,$K$2,1)-WEEKDAY(DATE($E$2,$K$2,1),2)+1+10),RESERVAS!$D$6:$D$203,">"&(DATE($E$2,$K$2,1)-WEEKDAY(DATE($E$2,$K$2,1),2)+1+10),RESERVAS!$I$6:$I$203,"<>Cancelada",RESERVAS!$I$6:$I$203,"<>Consulta")=1,"ALUGADA","CONFLITO"))&IF(COUNTIFS(RESERVAS!$C$6:$C$203,"<="&(DATE($E$2,$K$2,1)-WEEKDAY(DATE($E$2,$K$2,1),2)+1+10),RESERVAS!$D$6:$D$203,">"&(DATE($E$2,$K$2,1)-WEEKDAY(DATE($E$2,$K$2,1),2)+1+10),RESERVAS!$I$6:$I$203,"<>Cancelada",RESERVAS!$I$6:$I$203,"<>Consulta")=0,"",CHAR(10)&IFERROR(LOOKUP(2,1/((RESERVAS!$C$6:$C$203<=(DATE($E$2,$K$2,1)-WEEKDAY(DATE($E$2,$K$2,1),2)+1+10))*(RESERVAS!$D$6:$D$203>(DATE($E$2,$K$2,1)-WEEKDAY(DATE($E$2,$K$2,1),2)+1+10))*(RESERVAS!$I$6:$I$203<>"Cancelada")*(RESERVAS!$I$6:$I$203<>"Consulta")),RESERVAS!$B$6:$B$203),""))) -> 10 DISPONÍVEL | E6: =IF(MONTH((DATE($E$2,$K$2,1)-WEEKDAY(DATE($E$2,$K$2,1),2)+1+11))<>$K$2,"",TEXT((DATE($E$2,$K$2,1)-WEEKDAY(DATE($E$2,$K$2,1),2)+1+11),"dd")&CHAR(10)&IF(COUNTIFS(RESERVAS!$C$6:$C$203,"<="&(DATE($E$2,$K$2,1)-WEEKDAY(DATE($E$2,$K$2,1),2)+1+11),RESERVAS!$D$6:$D$203,">"&(DATE($E$2,$K$2,1)-WEEKDAY(DATE($E$2,$K$2,1),2)+1+11),RESERVAS!$I$6:$I$203,"<>Cancelada",RESERVAS!$I$6:$I$203,"<>Consulta")=0,"DISPONÍVEL",IF(COUNTIFS(RESERVAS!$C$6:$C$203,"<="&(DATE($E$2,$K$2,1)-WEEKDAY(DATE($E$2,$K$2,1),2)+1+11),RESERVAS!$D$6:$D$203,">"&(DATE($E$2,$K$2,1)-WEEKDAY(DATE($E$2,$K$2,1),2)+1+11),RESERVAS!$I$6:$I$203,"<>Cancelada",RESERVAS!$I$6:$I$203,"<>Consulta")=1,"ALUGADA","CONFLITO"))&IF(COUNTIFS(RESERVAS!$C$6:$C$203,"<="&(DATE($E$2,$K$2,1)-WEEKDAY(DATE($E$2,$K$2,1),2)+1+11),RESERVAS!$D$6:$D$203,">"&(DATE($E$2,$K$2,1)-WEEKDAY(DATE($E$2,$K$2,1),2)+1+11),RESERVAS!$I$6:$I$203,"<>Cancelada",RESERVAS!$I$6:$I$203,"<>Consulta")=0,"",CHAR(10)&IFERROR(LOOKUP(2,1/((RESERVAS!$C$6:$C$203<=(DATE($E$2,$K$2,1)-WEEKDAY(DATE($E$2,$K$2,1),2)+1+11))*(RESERVAS!$D$6:$D$203>(DATE($E$2,$K$2,1)-WEEKDAY(DATE($E$2,$K$2,1),2)+1+11))*(RESERVAS!$I$6:$I$203<>"Cancelada")*(RESERVAS!$I$6:$I$203<>"Consulta")),RESERVAS!$B$6:$B$203),""))) -> 11 ALUGADA Louis Renan - Férias | F6: =IF(MONTH((DATE($E$2,$K$2,1)-WEEKDAY(DATE($E$2,$K$2,1),2)+1+12))<>$K$2,"",TEXT((DATE($E$2,$K$2,1)-WEEKDAY(DATE($E$2,$K$2,1),2)+1+12),"dd")&CHAR(10)&IF(COUNTIFS(RESERVAS!$C$6:$C$203,"<="&(DATE($E$2,$K$2,1)-WEEKDAY(DATE($E$2,$K$2,1),2)+1+12),RESERVAS!$D$6:$D$203,">"&(DATE($E$2,$K$2,1)-WEEKDAY(DATE($E$2,$K$2,1),2)+1+12),RESERVAS!$I$6:$I$203,"<>Cancelada",RESERVAS!$I$6:$I$203,"<>Consulta")=0,"DISPONÍVEL",IF(COUNTIFS(RESERVAS!$C$6:$C$203,"<="&(DATE($E$2,$K$2,1)-WEEKDAY(DATE($E$2,$K$2,1),2)+1+12),RESERVAS!$D$6:$D$203,">"&(DATE($E$2,$K$2,1)-WEEKDAY(DATE($E$2,$K$2,1),2)+1+12),RESERVAS!$I$6:$I$203,"<>Cancelada",RESERVAS!$I$6:$I$203,"<>Consulta")=1,"ALUGADA","CONFLITO"))&IF(COUNTIFS(RESERVAS!$C$6:$C$203,"<="&(DATE($E$2,$K$2,1)-WEEKDAY(DATE($E$2,$K$2,1),2)+1+12),RESERVAS!$D$6:$D$203,">"&(DATE($E$2,$K$2,1)-WEEKDAY(DATE($E$2,$K$2,1),2)+1+12),RESERVAS!$I$6:$I$203,"<>Cancelada",RESERVAS!$I$6:$I$203,"<>Consulta")=0,"",CHAR(10)&IFERROR(LOOKUP(2,1/((RESERVAS!$C$6:$C$203<=(DATE($E$2,$K$2,1)-WEEKDAY(DATE($E$2,$K$2,1),2)+1+12))*(RESERVAS!$D$6:$D$203>(DATE($E$2,$K$2,1)-WEEKDAY(DATE($E$2,$K$2,1),2)+1+12))*(RESERVAS!$I$6:$I$203<>"Cancelada")*(RESERVAS!$I$6:$I$203<>"Consulta")),RESERVAS!$B$6:$B$203),""))) -> 12 ALUGADA Louis Renan - Férias | G6: =IF(MONTH((DATE($E$2,$K$2,1)-WEEKDAY(DATE($E$2,$K$2,1),2)+1+13))<>$K$2,"",TEXT((DATE($E$2,$K$2,1)-WEEKDAY(DATE($E$2,$K$2,1),2)+1+13),"dd")&CHAR(10)&IF(COUNTIFS(RESERVAS!$C$6:$C$203,"<="&(DATE($E$2,$K$2,1)-WEEKDAY(DATE($E$2,$K$2,1),2)+1+13),RESERVAS!$D$6:$D$203,">"&(DATE($E$2,$K$2,1)-WEEKDAY(DATE($E$2,$K$2,1),2)+1+13),RESERVAS!$I$6:$I$203,"<>Cancelada",RESERVAS!$I$6:$I$203,"<>Consulta")=0,"DISPONÍVEL",IF(COUNTIFS(RESERVAS!$C$6:$C$203,"<="&(DATE($E$2,$K$2,1)-WEEKDAY(DATE($E$2,$K$2,1),2)+1+13),RESERVAS!$D$6:$D$203,">"&(DATE($E$2,$K$2,1)-WEEKDAY(DATE($E$2,$K$2,1),2)+1+13),RESERVAS!$I$6:$I$203,"<>Cancelada",RESERVAS!$I$6:$I$203,"<>Consulta")=1,"ALUGADA","CONFLITO"))&IF(COUNTIFS(RESERVAS!$C$6:$C$203,"<="&(DATE($E$2,$K$2,1)-WEEKDAY(DATE($E$2,$K$2,1),2)+1+13),RESERVAS!$D$6:$D$203,">"&(DATE($E$2,$K$2,1)-WEEKDAY(DATE($E$2,$K$2,1),2)+1+13),RESERVAS!$I$6:$I$203,"<>Cancelada",RESERVAS!$I$6:$I$203,"<>Consulta")=0,"",CHAR(10)&IFERROR(LOOKUP(2,1/((RESERVAS!$C$6:$C$203<=(DATE($E$2,$K$2,1)-WEEKDAY(DATE($E$2,$K$2,1),2)+1+13))*(RESERVAS!$D$6:$D$203>(DATE($E$2,$K$2,1)-WEEKDAY(DATE($E$2,$K$2,1),2)+1+13))*(RESERVAS!$I$6:$I$203<>"Cancelada")*(RESERVAS!$I$6:$I$203<>"Consulta")),RESERVAS!$B$6:$B$203),""))) -> 13 ALUGADA Louis Renan - Férias | I6: Custos diretos (R$) | J6: =SUMPRODUCT((RESERVAS!$C$6:$C$203<DATE($E$2,$K$2+1,1))*(RESERVAS!$D$6:$D$203>DATE($E$2,$K$2,1))*(RESERVAS!$I$6:$I$203<>"Cancelada")*(RESERVAS!$I$6:$I$203<>"Consulta")*RESERVAS!$T$6:$T$203*(((RESERVAS!$D$6:$D$203<DATE($E$2,$K$2+1,1))*RESERVAS!$D$6:$D$203+(RESERVAS!$D$6:$D$203>=DATE($E$2,$K$2+1,1))*DATE($E$2,$K$2+1,1))-((RESERVAS!$C$6:$C$203>DATE($E$2,$K$2,1))*RESERVAS!$C$6:$C$203+(RESERVAS!$C$6:$C$203<=DATE($E$2,$K$2,1))*DATE($E$2,$K$2,1)))) -> 32.05
A7: =IF(MONTH((DATE($E$2,$K$2,1)-WEEKDAY(DATE($E$2,$K$2,1),2)+1+14))<>$K$2,"",TEXT((DATE($E$2,$K$2,1)-WEEKDAY(DATE($E$2,$K$2,1),2)+1+14),"dd")&CHAR(10)&IF(COUNTIFS(RESERVAS!$C$6:$C$203,"<="&(DATE($E$2,$K$2,1)-WEEKDAY(DATE($E$2,$K$2,1),2)+1+14),RESERVAS!$D$6:$D$203,">"&(DATE($E$2,$K$2,1)-WEEKDAY(DATE($E$2,$K$2,1),2)+1+14),RESERVAS!$I$6:$I$203,"<>Cancelada",RESERVAS!$I$6:$I$203,"<>Consulta")=0,"DISPONÍVEL",IF(COUNTIFS(RESERVAS!$C$6:$C$203,"<="&(DATE($E$2,$K$2,1)-WEEKDAY(DATE($E$2,$K$2,1),2)+1+14),RESERVAS!$D$6:$D$203,">"&(DATE($E$2,$K$2,1)-WEEKDAY(DATE($E$2,$K$2,1),2)+1+14),RESERVAS!$I$6:$I$203,"<>Cancelada",RESERVAS!$I$6:$I$203,"<>Consulta")=1,"ALUGADA","CONFLITO"))&IF(COUNTIFS(RESERVAS!$C$6:$C$203,"<="&(DATE($E$2,$K$2,1)-WEEKDAY(DATE($E$2,$K$2,1),2)+1+14),RESERVAS!$D$6:$D$203,">"&(DATE($E$2,$K$2,1)-WEEKDAY(DATE($E$2,$K$2,1),2)+1+14),RESERVAS!$I$6:$I$203,"<>Cancelada",RESERVAS!$I$6:$I$203,"<>Consulta")=0,"",CHAR(10)&IFERROR(LOOKUP(2,1/((RESERVAS!$C$6:$C$203<=(DATE($E$2,$K$2,1)-WEEKDAY(DATE($E$2,$K$2,1),2)+1+14))*(RESERVAS!$D$6:$D$203>(DATE($E$2,$K$2,1)-WEEKDAY(DATE($E$2,$K$2,1),2)+1+14))*(RESERVAS!$I$6:$I$203<>"Cancelada")*(RESERVAS!$I$6:$I$203<>"Consulta")),RESERVAS!$B$6:$B$203),""))) -> 14 ALUGADA Louis Renan - Férias | B7: =IF(MONTH((DATE($E$2,$K$2,1)-WEEKDAY(DATE($E$2,$K$2,1),2)+1+15))<>$K$2,"",TEXT((DATE($E$2,$K$2,1)-WEEKDAY(DATE($E$2,$K$2,1),2)+1+15),"dd")&CHAR(10)&IF(COUNTIFS(RESERVAS!$C$6:$C$203,"<="&(DATE($E$2,$K$2,1)-WEEKDAY(DATE($E$2,$K$2,1),2)+1+15),RESERVAS!$D$6:$D$203,">"&(DATE($E$2,$K$2,1)-WEEKDAY(DATE($E$2,$K$2,1),2)+1+15),RESERVAS!$I$6:$I$203,"<>Cancelada",RESERVAS!$I$6:$I$203,"<>Consulta")=0,"DISPONÍVEL",IF(COUNTIFS(RESERVAS!$C$6:$C$203,"<="&(DATE($E$2,$K$2,1)-WEEKDAY(DATE($E$2,$K$2,1),2)+1+15),RESERVAS!$D$6:$D$203,">"&(DATE($E$2,$K$2,1)-WEEKDAY(DATE($E$2,$K$2,1),2)+1+15),RESERVAS!$I$6:$I$203,"<>Cancelada",RESERVAS!$I$6:$I$203,"<>Consulta")=1,"ALUGADA","CONFLITO"))&IF(COUNTIFS(RESERVAS!$C$6:$C$203,"<="&(DATE($E$2,$K$2,1)-WEEKDAY(DATE($E$2,$K$2,1),2)+1+15),RESERVAS!$D$6:$D$203,">"&(DATE($E$2,$K$2,1)-WEEKDAY(DATE($E$2,$K$2,1),2)+1+15),RESERVAS!$I$6:$I$203,"<>Cancelada",RESERVAS!$I$6:$I$203,"<>Consulta")=0,"",CHAR(10)&IFERROR(LOOKUP(2,1/((RESERVAS!$C$6:$C$203<=(DATE($E$2,$K$2,1)-WEEKDAY(DATE($E$2,$K$2,1),2)+1+15))*(RESERVAS!$D$6:$D$203>(DATE($E$2,$K$2,1)-WEEKDAY(DATE($E$2,$K$2,1),2)+1+15))*(RESERVAS!$I$6:$I$203<>"Cancelada")*(RESERVAS!$I$6:$I$203<>"Consulta")),RESERVAS!$B$6:$B$203),""))) -> 15 DISPONÍVEL | C7: =IF(MONTH((DATE($E$2,$K$2,1)-WEEKDAY(DATE($E$2,$K$2,1),2)+1+16))<>$K$2,"",TEXT((DATE($E$2,$K$2,1)-WEEKDAY(DATE($E$2,$K$2,1),2)+1+16),"dd")&CHAR(10)&IF(COUNTIFS(RESERVAS!$C$6:$C$203,"<="&(DATE($E$2,$K$2,1)-WEEKDAY(DATE($E$2,$K$2,1),2)+1+16),RESERVAS!$D$6:$D$203,">"&(DATE($E$2,$K$2,1)-WEEKDAY(DATE($E$2,$K$2,1),2)+1+16),RESERVAS!$I$6:$I$203,"<>Cancelada",RESERVAS!$I$6:$I$203,"<>Consulta")=0,"DISPONÍVEL",IF(COUNTIFS(RESERVAS!$C$6:$C$203,"<="&(DATE($E$2,$K$2,1)-WEEKDAY(DATE($E$2,$K$2,1),2)+1+16),RESERVAS!$D$6:$D$203,">"&(DATE($E$2,$K$2,1)-WEEKDAY(DATE($E$2,$K$2,1),2)+1+16),RESERVAS!$I$6:$I$203,"<>Cancelada",RESERVAS!$I$6:$I$203,"<>Consulta")=1,"ALUGADA","CONFLITO"))&IF(COUNTIFS(RESERVAS!$C$6:$C$203,"<="&(DATE($E$2,$K$2,1)-WEEKDAY(DATE($E$2,$K$2,1),2)+1+16),RESERVAS!$D$6:$D$203,">"&(DATE($E$2,$K$2,1)-WEEKDAY(DATE($E$2,$K$2,1),2)+1+16),RESERVAS!$I$6:$I$203,"<>Cancelada",RESERVAS!$I$6:$I$203,"<>Consulta")=0,"",CHAR(10)&IFERROR(LOOKUP(2,1/((RESERVAS!$C$6:$C$203<=(DATE($E$2,$K$2,1)-WEEKDAY(DATE($E$2,$K$2,1),2)+1+16))*(RESERVAS!$D$6:$D$203>(DATE($E$2,$K$2,1)-WEEKDAY(DATE($E$2,$K$2,1),2)+1+16))*(RESERVAS!$I$6:$I$203<>"Cancelada")*(RESERVAS!$I$6:$I$203<>"Consulta")),RESERVAS!$B$6:$B$203),""))) -> 16 DISPONÍVEL | D7: =IF(MONTH((DATE($E$2,$K$2,1)-WEEKDAY(DATE($E$2,$K$2,1),2)+1+17))<>$K$2,"",TEXT((DATE($E$2,$K$2,1)-WEEKDAY(DATE($E$2,$K$2,1),2)+1+17),"dd")&CHAR(10)&IF(COUNTIFS(RESERVAS!$C$6:$C$203,"<="&(DATE($E$2,$K$2,1)-WEEKDAY(DATE($E$2,$K$2,1),2)+1+17),RESERVAS!$D$6:$D$203,">"&(DATE($E$2,$K$2,1)-WEEKDAY(DATE($E$2,$K$2,1),2)+1+17),RESERVAS!$I$6:$I$203,"<>Cancelada",RESERVAS!$I$6:$I$203,"<>Consulta")=0,"DISPONÍVEL",IF(COUNTIFS(RESERVAS!$C$6:$C$203,"<="&(DATE($E$2,$K$2,1)-WEEKDAY(DATE($E$2,$K$2,1),2)+1+17),RESERVAS!$D$6:$D$203,">"&(DATE($E$2,$K$2,1)-WEEKDAY(DATE($E$2,$K$2,1),2)+1+17),RESERVAS!$I$6:$I$203,"<>Cancelada",RESERVAS!$I$6:$I$203,"<>Consulta")=1,"ALUGADA","CONFLITO"))&IF(COUNTIFS(RESERVAS!$C$6:$C$203,"<="&(DATE($E$2,$K$2,1)-WEEKDAY(DATE($E$2,$K$2,1),2)+1+17),RESERVAS!$D$6:$D$203,">"&(DATE($E$2,$K$2,1)-WEEKDAY(DATE($E$2,$K$2,1),2)+1+17),RESERVAS!$I$6:$I$203,"<>Cancelada",RESERVAS!$I$6:$I$203,"<>Consulta")=0,"",CHAR(10)&IFERROR(LOOKUP(2,1/((RESERVAS!$C$6:$C$203<=(DATE($E$2,$K$2,1)-WEEKDAY(DATE($E$2,$K$2,1),2)+1+17))*(RESERVAS!$D$6:$D$203>(DATE($E$2,$K$2,1)-WEEKDAY(DATE($E$2,$K$2,1),2)+1+17))*(RESERVAS!$I$6:$I$203<>"Cancelada")*(RESERVAS!$I$6:$I$203<>"Consulta")),RESERVAS!$B$6:$B$203),""))) -> 17 DISPONÍVEL | E7: =IF(MONTH((DATE($E$2,$K$2,1)-WEEKDAY(DATE($E$2,$K$2,1),2)+1+18))<>$K$2,"",TEXT((DATE($E$2,$K$2,1)-WEEKDAY(DATE($E$2,$K$2,1),2)+1+18),"dd")&CHAR(10)&IF(COUNTIFS(RESERVAS!$C$6:$C$203,"<="&(DATE($E$2,$K$2,1)-WEEKDAY(DATE($E$2,$K$2,1),2)+1+18),RESERVAS!$D$6:$D$203,">"&(DATE($E$2,$K$2,1)-WEEKDAY(DATE($E$2,$K$2,1),2)+1+18),RESERVAS!$I$6:$I$203,"<>Cancelada",RESERVAS!$I$6:$I$203,"<>Consulta")=0,"DISPONÍVEL",IF(COUNTIFS(RESERVAS!$C$6:$C$203,"<="&(DATE($E$2,$K$2,1)-WEEKDAY(DATE($E$2,$K$2,1),2)+1+18),RESERVAS!$D$6:$D$203,">"&(DATE($E$2,$K$2,1)-WEEKDAY(DATE($E$2,$K$2,1),2)+1+18),RESERVAS!$I$6:$I$203,"<>Cancelada",RESERVAS!$I$6:$I$203,"<>Consulta")=1,"ALUGADA","CONFLITO"))&IF(COUNTIFS(RESERVAS!$C$6:$C$203,"<="&(DATE($E$2,$K$2,1)-WEEKDAY(DATE($E$2,$K$2,1),2)+1+18),RESERVAS!$D$6:$D$203,">"&(DATE($E$2,$K$2,1)-WEEKDAY(DATE($E$2,$K$2,1),2)+1+18),RESERVAS!$I$6:$I$203,"<>Cancelada",RESERVAS!$I$6:$I$203,"<>Consulta")=0,"",CHAR(10)&IFERROR(LOOKUP(2,1/((RESERVAS!$C$6:$C$203<=(DATE($E$2,$K$2,1)-WEEKDAY(DATE($E$2,$K$2,1),2)+1+18))*(RESERVAS!$D$6:$D$203>(DATE($E$2,$K$2,1)-WEEKDAY(DATE($E$2,$K$2,1),2)+1+18))*(RESERVAS!$I$6:$I$203<>"Cancelada")*(RESERVAS!$I$6:$I$203<>"Consulta")),RESERVAS!$B$6:$B$203),""))) -> 18 DISPONÍVEL | F7: =IF(MONTH((DATE($E$2,$K$2,1)-WEEKDAY(DATE($E$2,$K$2,1),2)+1+19))<>$K$2,"",TEXT((DATE($E$2,$K$2,1)-WEEKDAY(DATE($E$2,$K$2,1),2)+1+19),"dd")&CHAR(10)&IF(COUNTIFS(RESERVAS!$C$6:$C$203,"<="&(DATE($E$2,$K$2,1)-WEEKDAY(DATE($E$2,$K$2,1),2)+1+19),RESERVAS!$D$6:$D$203,">"&(DATE($E$2,$K$2,1)-WEEKDAY(DATE($E$2,$K$2,1),2)+1+19),RESERVAS!$I$6:$I$203,"<>Cancelada",RESERVAS!$I$6:$I$203,"<>Consulta")=0,"DISPONÍVEL",IF(COUNTIFS(RESERVAS!$C$6:$C$203,"<="&(DATE($E$2,$K$2,1)-WEEKDAY(DATE($E$2,$K$2,1),2)+1+19),RESERVAS!$D$6:$D$203,">"&(DATE($E$2,$K$2,1)-WEEKDAY(DATE($E$2,$K$2,1),2)+1+19),RESERVAS!$I$6:$I$203,"<>Cancelada",RESERVAS!$I$6:$I$203,"<>Consulta")=1,"ALUGADA","CONFLITO"))&IF(COUNTIFS(RESERVAS!$C$6:$C$203,"<="&(DATE($E$2,$K$2,1)-WEEKDAY(DATE($E$2,$K$2,1),2)+1+19),RESERVAS!$D$6:$D$203,">"&(DATE($E$2,$K$2,1)-WEEKDAY(DATE($E$2,$K$2,1),2)+1+19),RESERVAS!$I$6:$I$203,"<>Cancelada",RESERVAS!$I$6:$I$203,"<>Consulta")=0,"",CHAR(10)&IFERROR(LOOKUP(2,1/((RESERVAS!$C$6:$C$203<=(DATE($E$2,$K$2,1)-WEEKDAY(DATE($E$2,$K$2,1),2)+1+19))*(RESERVAS!$D$6:$D$203>(DATE($E$2,$K$2,1)-WEEKDAY(DATE($E$2,$K$2,1),2)+1+19))*(RESERVAS!$I$6:$I$203<>"Cancelada")*(RESERVAS!$I$6:$I$203<>"Consulta")),RESERVAS!$B$6:$B$203),""))) -> 19 DISPONÍVEL | G7: =IF(MONTH((DATE($E$2,$K$2,1)-WEEKDAY(DATE($E$2,$K$2,1),2)+1+20))<>$K$2,"",TEXT((DATE($E$2,$K$2,1)-WEEKDAY(DATE($E$2,$K$2,1),2)+1+20),"dd")&CHAR(10)&IF(COUNTIFS(RESERVAS!$C$6:$C$203,"<="&(DATE($E$2,$K$2,1)-WEEKDAY(DATE($E$2,$K$2,1),2)+1+20),RESERVAS!$D$6:$D$203,">"&(DATE($E$2,$K$2,1)-WEEKDAY(DATE($E$2,$K$2,1),2)+1+20),RESERVAS!$I$6:$I$203,"<>Cancelada",RESERVAS!$I$6:$I$203,"<>Consulta")=0,"DISPONÍVEL",IF(COUNTIFS(RESERVAS!$C$6:$C$203,"<="&(DATE($E$2,$K$2,1)-WEEKDAY(DATE($E$2,$K$2,1),2)+1+20),RESERVAS!$D$6:$D$203,">"&(DATE($E$2,$K$2,1)-WEEKDAY(DATE($E$2,$K$2,1),2)+1+20),RESERVAS!$I$6:$I$203,"<>Cancelada",RESERVAS!$I$6:$I$203,"<>Consulta")=1,"ALUGADA","CONFLITO"))&IF(COUNTIFS(RESERVAS!$C$6:$C$203,"<="&(DATE($E$2,$K$2,1)-WEEKDAY(DATE($E$2,$K$2,1),2)+1+20),RESERVAS!$D$6:$D$203,">"&(DATE($E$2,$K$2,1)-WEEKDAY(DATE($E$2,$K$2,1),2)+1+20),RESERVAS!$I$6:$I$203,"<>Cancelada",RESERVAS!$I$6:$I$203,"<>Consulta")=0,"",CHAR(10)&IFERROR(LOOKUP(2,1/((RESERVAS!$C$6:$C$203<=(DATE($E$2,$K$2,1)-WEEKDAY(DATE($E$2,$K$2,1),2)+1+20))*(RESERVAS!$D$6:$D$203>(DATE($E$2,$K$2,1)-WEEKDAY(DATE($E$2,$K$2,1),2)+1+20))*(RESERVAS!$I$6:$I$203<>"Cancelada")*(RESERVAS!$I$6:$I$203<>"Consulta")),RESERVAS!$B$6:$B$203),""))) -> 20 DISPONÍVEL | I7: Despesas gerais (R$) | J7: =SUMIFS('DESPESAS CASA'!$D$6:$D$305,'DESPESAS CASA'!$A$6:$A$305,">="&DATE($E$2,$K$2,1),'DESPESAS CASA'!$A$6:$A$305,"<"&DATE($E$2,$K$2+1,1),'DESPESAS CASA'!$E$6:$E$305,"") -> 0
A8: =IF(MONTH((DATE($E$2,$K$2,1)-WEEKDAY(DATE($E$2,$K$2,1),2)+1+21))<>$K$2,"",TEXT((DATE($E$2,$K$2,1)-WEEKDAY(DATE($E$2,$K$2,1),2)+1+21),"dd")&CHAR(10)&IF(COUNTIFS(RESERVAS!$C$6:$C$203,"<="&(DATE($E$2,$K$2,1)-WEEKDAY(DATE($E$2,$K$2,1),2)+1+21),RESERVAS!$D$6:$D$203,">"&(DATE($E$2,$K$2,1)-WEEKDAY(DATE($E$2,$K$2,1),2)+1+21),RESERVAS!$I$6:$I$203,"<>Cancelada",RESERVAS!$I$6:$I$203,"<>Consulta")=0,"DISPONÍVEL",IF(COUNTIFS(RESERVAS!$C$6:$C$203,"<="&(DATE($E$2,$K$2,1)-WEEKDAY(DATE($E$2,$K$2,1),2)+1+21),RESERVAS!$D$6:$D$203,">"&(DATE($E$2,$K$2,1)-WEEKDAY(DATE($E$2,$K$2,1),2)+1+21),RESERVAS!$I$6:$I$203,"<>Cancelada",RESERVAS!$I$6:$I$203,"<>Consulta")=1,"ALUGADA","CONFLITO"))&IF(COUNTIFS(RESERVAS!$C$6:$C$203,"<="&(DATE($E$2,$K$2,1)-WEEKDAY(DATE($E$2,$K$2,1),2)+1+21),RESERVAS!$D$6:$D$203,">"&(DATE($E$2,$K$2,1)-WEEKDAY(DATE($E$2,$K$2,1),2)+1+21),RESERVAS!$I$6:$I$203,"<>Cancelada",RESERVAS!$I$6:$I$203,"<>Consulta")=0,"",CHAR(10)&IFERROR(LOOKUP(2,1/((RESERVAS!$C$6:$C$203<=(DATE($E$2,$K$2,1)-WEEKDAY(DATE($E$2,$K$2,1),2)+1+21))*(RESERVAS!$D$6:$D$203>(DATE($E$2,$K$2,1)-WEEKDAY(DATE($E$2,$K$2,1),2)+1+21))*(RESERVAS!$I$6:$I$203<>"Cancelada")*(RESERVAS!$I$6:$I$203<>"Consulta")),RESERVAS!$B$6:$B$203),""))) -> 21 DISPONÍVEL | B8: =IF(MONTH((DATE($E$2,$K$2,1)-WEEKDAY(DATE($E$2,$K$2,1),2)+1+22))<>$K$2,"",TEXT((DATE($E$2,$K$2,1)-WEEKDAY(DATE($E$2,$K$2,1),2)+1+22),"dd")&CHAR(10)&IF(COUNTIFS(RESERVAS!$C$6:$C$203,"<="&(DATE($E$2,$K$2,1)-WEEKDAY(DATE($E$2,$K$2,1),2)+1+22),RESERVAS!$D$6:$D$203,">"&(DATE($E$2,$K$2,1)-WEEKDAY(DATE($E$2,$K$2,1),2)+1+22),RESERVAS!$I$6:$I$203,"<>Cancelada",RESERVAS!$I$6:$I$203,"<>Consulta")=0,"DISPONÍVEL",IF(COUNTIFS(RESERVAS!$C$6:$C$203,"<="&(DATE($E$2,$K$2,1)-WEEKDAY(DATE($E$2,$K$2,1),2)+1+22),RESERVAS!$D$6:$D$203,">"&(DATE($E$2,$K$2,1)-WEEKDAY(DATE($E$2,$K$2,1),2)+1+22),RESERVAS!$I$6:$I$203,"<>Cancelada",RESERVAS!$I$6:$I$203,"<>Consulta")=1,"ALUGADA","CONFLITO"))&IF(COUNTIFS(RESERVAS!$C$6:$C$203,"<="&(DATE($E$2,$K$2,1)-WEEKDAY(DATE($E$2,$K$2,1),2)+1+22),RESERVAS!$D$6:$D$203,">"&(DATE($E$2,$K$2,1)-WEEKDAY(DATE($E$2,$K$2,1),2)+1+22),RESERVAS!$I$6:$I$203,"<>Cancelada",RESERVAS!$I$6:$I$203,"<>Consulta")=0,"",CHAR(10)&IFERROR(LOOKUP(2,1/((RESERVAS!$C$6:$C$203<=(DATE($E$2,$K$2,1)-WEEKDAY(DATE($E$2,$K$2,1),2)+1+22))*(RESERVAS!$D$6:$D$203>(DATE($E$2,$K$2,1)-WEEKDAY(DATE($E$2,$K$2,1),2)+1+22))*(RESERVAS!$I$6:$I$203<>"Cancelada")*(RESERVAS!$I$6:$I$203<>"Consulta")),RESERVAS!$B$6:$B$203),""))) -> 22 DISPONÍVEL | C8: =IF(MONTH((DATE($E$2,$K$2,1)-WEEKDAY(DATE($E$2,$K$2,1),2)+1+23))<>$K$2,"",TEXT((DATE($E$2,$K$2,1)-WEEKDAY(DATE($E$2,$K$2,1),2)+1+23),"dd")&CHAR(10)&IF(COUNTIFS(RESERVAS!$C$6:$C$203,"<="&(DATE($E$2,$K$2,1)-WEEKDAY(DATE($E$2,$K$2,1),2)+1+23),RESERVAS!$D$6:$D$203,">"&(DATE($E$2,$K$2,1)-WEEKDAY(DATE($E$2,$K$2,1),2)+1+23),RESERVAS!$I$6:$I$203,"<>Cancelada",RESERVAS!$I$6:$I$203,"<>Consulta")=0,"DISPONÍVEL",IF(COUNTIFS(RESERVAS!$C$6:$C$203,"<="&(DATE($E$2,$K$2,1)-WEEKDAY(DATE($E$2,$K$2,1),2)+1+23),RESERVAS!$D$6:$D$203,">"&(DATE($E$2,$K$2,1)-WEEKDAY(DATE($E$2,$K$2,1),2)+1+23),RESERVAS!$I$6:$I$203,"<>Cancelada",RESERVAS!$I$6:$I$203,"<>Consulta")=1,"ALUGADA","CONFLITO"))&IF(COUNTIFS(RESERVAS!$C$6:$C$203,"<="&(DATE($E$2,$K$2,1)-WEEKDAY(DATE($E$2,$K$2,1),2)+1+23),RESERVAS!$D$6:$D$203,">"&(DATE($E$2,$K$2,1)-WEEKDAY(DATE($E$2,$K$2,1),2)+1+23),RESERVAS!$I$6:$I$203,"<>Cancelada",RESERVAS!$I$6:$I$203,"<>Consulta")=0,"",CHAR(10)&IFERROR(LOOKUP(2,1/((RESERVAS!$C$6:$C$203<=(DATE($E$2,$K$2,1)-WEEKDAY(DATE($E$2,$K$2,1),2)+1+23))*(RESERVAS!$D$6:$D$203>(DATE($E$2,$K$2,1)-WEEKDAY(DATE($E$2,$K$2,1),2)+1+23))*(RESERVAS!$I$6:$I$203<>"Cancelada")*(RESERVAS!$I$6:$I$203<>"Consulta")),RESERVAS!$B$6:$B$203),""))) -> 23 DISPONÍVEL | D8: =IF(MONTH((DATE($E$2,$K$2,1)-WEEKDAY(DATE($E$2,$K$2,1),2)+1+24))<>$K$2,"",TEXT((DATE($E$2,$K$2,1)-WEEKDAY(DATE($E$2,$K$2,1),2)+1+24),"dd")&CHAR(10)&IF(COUNTIFS(RESERVAS!$C$6:$C$203,"<="&(DATE($E$2,$K$2,1)-WEEKDAY(DATE($E$2,$K$2,1),2)+1+24),RESERVAS!$D$6:$D$203,">"&(DATE($E$2,$K$2,1)-WEEKDAY(DATE($E$2,$K$2,1),2)+1+24),RESERVAS!$I$6:$I$203,"<>Cancelada",RESERVAS!$I$6:$I$203,"<>Consulta")=0,"DISPONÍVEL",IF(COUNTIFS(RESERVAS!$C$6:$C$203,"<="&(DATE($E$2,$K$2,1)-WEEKDAY(DATE($E$2,$K$2,1),2)+1+24),RESERVAS!$D$6:$D$203,">"&(DATE($E$2,$K$2,1)-WEEKDAY(DATE($E$2,$K$2,1),2)+1+24),RESERVAS!$I$6:$I$203,"<>Cancelada",RESERVAS!$I$6:$I$203,"<>Consulta")=1,"ALUGADA","CONFLITO"))&IF(COUNTIFS(RESERVAS!$C$6:$C$203,"<="&(DATE($E$2,$K$2,1)-WEEKDAY(DATE($E$2,$K$2,1),2)+1+24),RESERVAS!$D$6:$D$203,">"&(DATE($E$2,$K$2,1)-WEEKDAY(DATE($E$2,$K$2,1),2)+1+24),RESERVAS!$I$6:$I$203,"<>Cancelada",RESERVAS!$I$6:$I$203,"<>Consulta")=0,"",CHAR(10)&IFERROR(LOOKUP(2,1/((RESERVAS!$C$6:$C$203<=(DATE($E$2,$K$2,1)-WEEKDAY(DATE($E$2,$K$2,1),2)+1+24))*(RESERVAS!$D$6:$D$203>(DATE($E$2,$K$2,1)-WEEKDAY(DATE($E$2,$K$2,1),2)+1+24))*(RESERVAS!$I$6:$I$203<>"Cancelada")*(RESERVAS!$I$6:$I$203<>"Consulta")),RESERVAS!$B$6:$B$203),""))) -> 24 DISPONÍVEL | E8: =IF(MONTH((DATE($E$2,$K$2,1)-WEEKDAY(DATE($E$2,$K$2,1),2)+1+25))<>$K$2,"",TEXT((DATE($E$2,$K$2,1)-WEEKDAY(DATE($E$2,$K$2,1),2)+1+25),"dd")&CHAR(10)&IF(COUNTIFS(RESERVAS!$C$6:$C$203,"<="&(DATE($E$2,$K$2,1)-WEEKDAY(DATE($E$2,$K$2,1),2)+1+25),RESERVAS!$D$6:$D$203,">"&(DATE($E$2,$K$2,1)-WEEKDAY(DATE($E$2,$K$2,1),2)+1+25),RESERVAS!$I$6:$I$203,"<>Cancelada",RESERVAS!$I$6:$I$203,"<>Consulta")=0,"DISPONÍVEL",IF(COUNTIFS(RESERVAS!$C$6:$C$203,"<="&(DATE($E$2,$K$2,1)-WEEKDAY(DATE($E$2,$K$2,1),2)+1+25),RESERVAS!$D$6:$D$203,">"&(DATE($E$2,$K$2,1)-WEEKDAY(DATE($E$2,$K$2,1),2)+1+25),RESERVAS!$I$6:$I$203,"<>Cancelada",RESERVAS!$I$6:$I$203,"<>Consulta")=1,"ALUGADA","CONFLITO"))&IF(COUNTIFS(RESERVAS!$C$6:$C$203,"<="&(DATE($E$2,$K$2,1)-WEEKDAY(DATE($E$2,$K$2,1),2)+1+25),RESERVAS!$D$6:$D$203,">"&(DATE($E$2,$K$2,1)-WEEKDAY(DATE($E$2,$K$2,1),2)+1+25),RESERVAS!$I$6:$I$203,"<>Cancelada",RESERVAS!$I$6:$I$203,"<>Consulta")=0,"",CHAR(10)&IFERROR(LOOKUP(2,1/((RESERVAS!$C$6:$C$203<=(DATE($E$2,$K$2,1)-WEEKDAY(DATE($E$2,$K$2,1),2)+1+25))*(RESERVAS!$D$6:$D$203>(DATE($E$2,$K$2,1)-WEEKDAY(DATE($E$2,$K$2,1),2)+1+25))*(RESERVAS!$I$6:$I$203<>"Cancelada")*(RESERVAS!$I$6:$I$203<>"Consulta")),RESERVAS!$B$6:$B$203),""))) -> 25 DISPONÍVEL | F8: =IF(MONTH((DATE($E$2,$K$2,1)-WEEKDAY(DATE($E$2,$K$2,1),2)+1+26))<>$K$2,"",TEXT((DATE($E$2,$K$2,1)-WEEKDAY(DATE($E$2,$K$2,1),2)+1+26),"dd")&CHAR(10)&IF(COUNTIFS(RESERVAS!$C$6:$C$203,"<="&(DATE($E$2,$K$2,1)-WEEKDAY(DATE($E$2,$K$2,1),2)+1+26),RESERVAS!$D$6:$D$203,">"&(DATE($E$2,$K$2,1)-WEEKDAY(DATE($E$2,$K$2,1),2)+1+26),RESERVAS!$I$6:$I$203,"<>Cancelada",RESERVAS!$I$6:$I$203,"<>Consulta")=0,"DISPONÍVEL",IF(COUNTIFS(RESERVAS!$C$6:$C$203,"<="&(DATE($E$2,$K$2,1)-WEEKDAY(DATE($E$2,$K$2,1),2)+1+26),RESERVAS!$D$6:$D$203,">"&(DATE($E$2,$K$2,1)-WEEKDAY(DATE($E$2,$K$2,1),2)+1+26),RESERVAS!$I$6:$I$203,"<>Cancelada",RESERVAS!$I$6:$I$203,"<>Consulta")=1,"ALUGADA","CONFLITO"))&IF(COUNTIFS(RESERVAS!$C$6:$C$203,"<="&(DATE($E$2,$K$2,1)-WEEKDAY(DATE($E$2,$K$2,1),2)+1+26),RESERVAS!$D$6:$D$203,">"&(DATE($E$2,$K$2,1)-WEEKDAY(DATE($E$2,$K$2,1),2)+1+26),RESERVAS!$I$6:$I$203,"<>Cancelada",RESERVAS!$I$6:$I$203,"<>Consulta")=0,"",CHAR(10)&IFERROR(LOOKUP(2,1/((RESERVAS!$C$6:$C$203<=(DATE($E$2,$K$2,1)-WEEKDAY(DATE($E$2,$K$2,1),2)+1+26))*(RESERVAS!$D$6:$D$203>(DATE($E$2,$K$2,1)-WEEKDAY(DATE($E$2,$K$2,1),2)+1+26))*(RESERVAS!$I$6:$I$203<>"Cancelada")*(RESERVAS!$I$6:$I$203<>"Consulta")),RESERVAS!$B$6:$B$203),""))) -> 26 DISPONÍVEL | G8: =IF(MONTH((DATE($E$2,$K$2,1)-WEEKDAY(DATE($E$2,$K$2,1),2)+1+27))<>$K$2,"",TEXT((DATE($E$2,$K$2,1)-WEEKDAY(DATE($E$2,$K$2,1),2)+1+27),"dd")&CHAR(10)&IF(COUNTIFS(RESERVAS!$C$6:$C$203,"<="&(DATE($E$2,$K$2,1)-WEEKDAY(DATE($E$2,$K$2,1),2)+1+27),RESERVAS!$D$6:$D$203,">"&(DATE($E$2,$K$2,1)-WEEKDAY(DATE($E$2,$K$2,1),2)+1+27),RESERVAS!$I$6:$I$203,"<>Cancelada",RESERVAS!$I$6:$I$203,"<>Consulta")=0,"DISPONÍVEL",IF(COUNTIFS(RESERVAS!$C$6:$C$203,"<="&(DATE($E$2,$K$2,1)-WEEKDAY(DATE($E$2,$K$2,1),2)+1+27),RESERVAS!$D$6:$D$203,">"&(DATE($E$2,$K$2,1)-WEEKDAY(DATE($E$2,$K$2,1),2)+1+27),RESERVAS!$I$6:$I$203,"<>Cancelada",RESERVAS!$I$6:$I$203,"<>Consulta")=1,"ALUGADA","CONFLITO"))&IF(COUNTIFS(RESERVAS!$C$6:$C$203,"<="&(DATE($E$2,$K$2,1)-WEEKDAY(DATE($E$2,$K$2,1),2)+1+27),RESERVAS!$D$6:$D$203,">"&(DATE($E$2,$K$2,1)-WEEKDAY(DATE($E$2,$K$2,1),2)+1+27),RESERVAS!$I$6:$I$203,"<>Cancelada",RESERVAS!$I$6:$I$203,"<>Consulta")=0,"",CHAR(10)&IFERROR(LOOKUP(2,1/((RESERVAS!$C$6:$C$203<=(DATE($E$2,$K$2,1)-WEEKDAY(DATE($E$2,$K$2,1),2)+1+27))*(RESERVAS!$D$6:$D$203>(DATE($E$2,$K$2,1)-WEEKDAY(DATE($E$2,$K$2,1),2)+1+27))*(RESERVAS!$I$6:$I$203<>"Cancelada")*(RESERVAS!$I$6:$I$203<>"Consulta")),RESERVAS!$B$6:$B$203),""))) -> 27 DISPONÍVEL | I8: Lucro final (R$) | J8: =J5-J6-J7 -> 2767.95
A9: =IF(MONTH((DATE($E$2,$K$2,1)-WEEKDAY(DATE($E$2,$K$2,1),2)+1+28))<>$K$2,"",TEXT((DATE($E$2,$K$2,1)-WEEKDAY(DATE($E$2,$K$2,1),2)+1+28),"dd")&CHAR(10)&IF(COUNTIFS(RESERVAS!$C$6:$C$203,"<="&(DATE($E$2,$K$2,1)-WEEKDAY(DATE($E$2,$K$2,1),2)+1+28),RESERVAS!$D$6:$D$203,">"&(DATE($E$2,$K$2,1)-WEEKDAY(DATE($E$2,$K$2,1),2)+1+28),RESERVAS!$I$6:$I$203,"<>Cancelada",RESERVAS!$I$6:$I$203,"<>Consulta")=0,"DISPONÍVEL",IF(COUNTIFS(RESERVAS!$C$6:$C$203,"<="&(DATE($E$2,$K$2,1)-WEEKDAY(DATE($E$2,$K$2,1),2)+1+28),RESERVAS!$D$6:$D$203,">"&(DATE($E$2,$K$2,1)-WEEKDAY(DATE($E$2,$K$2,1),2)+1+28),RESERVAS!$I$6:$I$203,"<>Cancelada",RESERVAS!$I$6:$I$203,"<>Consulta")=1,"ALUGADA","CONFLITO"))&IF(COUNTIFS(RESERVAS!$C$6:$C$203,"<="&(DATE($E$2,$K$2,1)-WEEKDAY(DATE($E$2,$K$2,1),2)+1+28),RESERVAS!$D$6:$D$203,">"&(DATE($E$2,$K$2,1)-WEEKDAY(DATE($E$2,$K$2,1),2)+1+28),RESERVAS!$I$6:$I$203,"<>Cancelada",RESERVAS!$I$6:$I$203,"<>Consulta")=0,"",CHAR(10)&IFERROR(LOOKUP(2,1/((RESERVAS!$C$6:$C$203<=(DATE($E$2,$K$2,1)-WEEKDAY(DATE($E$2,$K$2,1),2)+1+28))*(RESERVAS!$D$6:$D$203>(DATE($E$2,$K$2,1)-WEEKDAY(DATE($E$2,$K$2,1),2)+1+28))*(RESERVAS!$I$6:$I$203<>"Cancelada")*(RESERVAS!$I$6:$I$203<>"Consulta")),RESERVAS!$B$6:$B$203),""))) -> 28 DISPONÍVEL | B9: =IF(MONTH((DATE($E$2,$K$2,1)-WEEKDAY(DATE($E$2,$K$2,1),2)+1+29))<>$K$2,"",TEXT((DATE($E$2,$K$2,1)-WEEKDAY(DATE($E$2,$K$2,1),2)+1+29),"dd")&CHAR(10)&IF(COUNTIFS(RESERVAS!$C$6:$C$203,"<="&(DATE($E$2,$K$2,1)-WEEKDAY(DATE($E$2,$K$2,1),2)+1+29),RESERVAS!$D$6:$D$203,">"&(DATE($E$2,$K$2,1)-WEEKDAY(DATE($E$2,$K$2,1),2)+1+29),RESERVAS!$I$6:$I$203,"<>Cancelada",RESERVAS!$I$6:$I$203,"<>Consulta")=0,"DISPONÍVEL",IF(COUNTIFS(RESERVAS!$C$6:$C$203,"<="&(DATE($E$2,$K$2,1)-WEEKDAY(DATE($E$2,$K$2,1),2)+1+29),RESERVAS!$D$6:$D$203,">"&(DATE($E$2,$K$2,1)-WEEKDAY(DATE($E$2,$K$2,1),2)+1+29),RESERVAS!$I$6:$I$203,"<>Cancelada",RESERVAS!$I$6:$I$203,"<>Consulta")=1,"ALUGADA","CONFLITO"))&IF(COUNTIFS(RESERVAS!$C$6:$C$203,"<="&(DATE($E$2,$K$2,1)-WEEKDAY(DATE($E$2,$K$2,1),2)+1+29),RESERVAS!$D$6:$D$203,">"&(DATE($E$2,$K$2,1)-WEEKDAY(DATE($E$2,$K$2,1),2)+1+29),RESERVAS!$I$6:$I$203,"<>Cancelada",RESERVAS!$I$6:$I$203,"<>Consulta")=0,"",CHAR(10)&IFERROR(LOOKUP(2,1/((RESERVAS!$C$6:$C$203<=(DATE($E$2,$K$2,1)-WEEKDAY(DATE($E$2,$K$2,1),2)+1+29))*(RESERVAS!$D$6:$D$203>(DATE($E$2,$K$2,1)-WEEKDAY(DATE($E$2,$K$2,1),2)+1+29))*(RESERVAS!$I$6:$I$203<>"Cancelada")*(RESERVAS!$I$6:$I$203<>"Consulta")),RESERVAS!$B$6:$B$203),""))) -> 29 DISPONÍVEL | C9: =IF(MONTH((DATE($E$2,$K$2,1)-WEEKDAY(DATE($E$2,$K$2,1),2)+1+30))<>$K$2,"",TEXT((DATE($E$2,$K$2,1)-WEEKDAY(DATE($E$2,$K$2,1),2)+1+30),"dd")&CHAR(10)&IF(COUNTIFS(RESERVAS!$C$6:$C$203,"<="&(DATE($E$2,$K$2,1)-WEEKDAY(DATE($E$2,$K$2,1),2)+1+30),RESERVAS!$D$6:$D$203,">"&(DATE($E$2,$K$2,1)-WEEKDAY(DATE($E$2,$K$2,1),2)+1+30),RESERVAS!$I$6:$I$203,"<>Cancelada",RESERVAS!$I$6:$I$203,"<>Consulta")=0,"DISPONÍVEL",IF(COUNTIFS(RESERVAS!$C$6:$C$203,"<="&(DATE($E$2,$K$2,1)-WEEKDAY(DATE($E$2,$K$2,1),2)+1+30),RESERVAS!$D$6:$D$203,">"&(DATE($E$2,$K$2,1)-WEEKDAY(DATE($E$2,$K$2,1),2)+1+30),RESERVAS!$I$6:$I$203,"<>Cancelada",RESERVAS!$I$6:$I$203,"<>Consulta")=1,"ALUGADA","CONFLITO"))&IF(COUNTIFS(RESERVAS!$C$6:$C$203,"<="&(DATE($E$2,$K$2,1)-WEEKDAY(DATE($E$2,$K$2,1),2)+1+30),RESERVAS!$D$6:$D$203,">"&(DATE($E$2,$K$2,1)-WEEKDAY(DATE($E$2,$K$2,1),2)+1+30),RESERVAS!$I$6:$I$203,"<>Cancelada",RESERVAS!$I$6:$I$203,"<>Consulta")=0,"",CHAR(10)&IFERROR(LOOKUP(2,1/((RESERVAS!$C$6:$C$203<=(DATE($E$2,$K$2,1)-WEEKDAY(DATE($E$2,$K$2,1),2)+1+30))*(RESERVAS!$D$6:$D$203>(DATE($E$2,$K$2,1)-WEEKDAY(DATE($E$2,$K$2,1),2)+1+30))*(RESERVAS!$I$6:$I$203<>"Cancelada")*(RESERVAS!$I$6:$I$203<>"Consulta")),RESERVAS!$B$6:$B$203),""))) -> 30 DISPONÍVEL | D9: =IF(MONTH((DATE($E$2,$K$2,1)-WEEKDAY(DATE($E$2,$K$2,1),2)+1+31))<>$K$2,"",TEXT((DATE($E$2,$K$2,1)-WEEKDAY(DATE($E$2,$K$2,1),2)+1+31),"dd")&CHAR(10)&IF(COUNTIFS(RESERVAS!$C$6:$C$203,"<="&(DATE($E$2,$K$2,1)-WEEKDAY(DATE($E$2,$K$2,1),2)+1+31),RESERVAS!$D$6:$D$203,">"&(DATE($E$2,$K$2,1)-WEEKDAY(DATE($E$2,$K$2,1),2)+1+31),RESERVAS!$I$6:$I$203,"<>Cancelada",RESERVAS!$I$6:$I$203,"<>Consulta")=0,"DISPONÍVEL",IF(COUNTIFS(RESERVAS!$C$6:$C$203,"<="&(DATE($E$2,$K$2,1)-WEEKDAY(DATE($E$2,$K$2,1),2)+1+31),RESERVAS!$D$6:$D$203,">"&(DATE($E$2,$K$2,1)-WEEKDAY(DATE($E$2,$K$2,1),2)+1+31),RESERVAS!$I$6:$I$203,"<>Cancelada",RESERVAS!$I$6:$I$203,"<>Consulta")=1,"ALUGADA","CONFLITO"))&IF(COUNTIFS(RESERVAS!$C$6:$C$203,"<="&(DATE($E$2,$K$2,1)-WEEKDAY(DATE($E$2,$K$2,1),2)+1+31),RESERVAS!$D$6:$D$203,">"&(DATE($E$2,$K$2,1)-WEEKDAY(DATE($E$2,$K$2,1),2)+1+31),RESERVAS!$I$6:$I$203,"<>Cancelada",RESERVAS!$I$6:$I$203,"<>Consulta")=0,"",CHAR(10)&IFERROR(LOOKUP(2,1/((RESERVAS!$C$6:$C$203<=(DATE($E$2,$K$2,1)-WEEKDAY(DATE($E$2,$K$2,1),2)+1+31))*(RESERVAS!$D$6:$D$203>(DATE($E$2,$K$2,1)-WEEKDAY(DATE($E$2,$K$2,1),2)+1+31))*(RESERVAS!$I$6:$I$203<>"Cancelada")*(RESERVAS!$I$6:$I$203<>"Consulta")),RESERVAS!$B$6:$B$203),""))) | E9: =IF(MONTH((DATE($E$2,$K$2,1)-WEEKDAY(DATE($E$2,$K$2,1),2)+1+32))<>$K$2,"",TEXT((DATE($E$2,$K$2,1)-WEEKDAY(DATE($E$2,$K$2,1),2)+1+32),"dd")&CHAR(10)&IF(COUNTIFS(RESERVAS!$C$6:$C$203,"<="&(DATE($E$2,$K$2,1)-WEEKDAY(DATE($E$2,$K$2,1),2)+1+32),RESERVAS!$D$6:$D$203,">"&(DATE($E$2,$K$2,1)-WEEKDAY(DATE($E$2,$K$2,1),2)+1+32),RESERVAS!$I$6:$I$203,"<>Cancelada",RESERVAS!$I$6:$I$203,"<>Consulta")=0,"DISPONÍVEL",IF(COUNTIFS(RESERVAS!$C$6:$C$203,"<="&(DATE($E$2,$K$2,1)-WEEKDAY(DATE($E$2,$K$2,1),2)+1+32),RESERVAS!$D$6:$D$203,">"&(DATE($E$2,$K$2,1)-WEEKDAY(DATE($E$2,$K$2,1),2)+1+32),RESERVAS!$I$6:$I$203,"<>Cancelada",RESERVAS!$I$6:$I$203,"<>Consulta")=1,"ALUGADA","CONFLITO"))&IF(COUNTIFS(RESERVAS!$C$6:$C$203,"<="&(DATE($E$2,$K$2,1)-WEEKDAY(DATE($E$2,$K$2,1),2)+1+32),RESERVAS!$D$6:$D$203,">"&(DATE($E$2,$K$2,1)-WEEKDAY(DATE($E$2,$K$2,1),2)+1+32),RESERVAS!$I$6:$I$203,"<>Cancelada",RESERVAS!$I$6:$I$203,"<>Consulta")=0,"",CHAR(10)&IFERROR(LOOKUP(2,1/((RESERVAS!$C$6:$C$203<=(DATE($E$2,$K$2,1)-WEEKDAY(DATE($E$2,$K$2,1),2)+1+32))*(RESERVAS!$D$6:$D$203>(DATE($E$2,$K$2,1)-WEEKDAY(DATE($E$2,$K$2,1),2)+1+32))*(RESERVAS!$I$6:$I$203<>"Cancelada")*(RESERVAS!$I$6:$I$203<>"Consulta")),RESERVAS!$B$6:$B$203),""))) | F9: =IF(MONTH((DATE($E$2,$K$2,1)-WEEKDAY(DATE($E$2,$K$2,1),2)+1+33))<>$K$2,"",TEXT((DATE($E$2,$K$2,1)-WEEKDAY(DATE($E$2,$K$2,1),2)+1+33),"dd")&CHAR(10)&IF(COUNTIFS(RESERVAS!$C$6:$C$203,"<="&(DATE($E$2,$K$2,1)-WEEKDAY(DATE($E$2,$K$2,1),2)+1+33),RESERVAS!$D$6:$D$203,">"&(DATE($E$2,$K$2,1)-WEEKDAY(DATE($E$2,$K$2,1),2)+1+33),RESERVAS!$I$6:$I$203,"<>Cancelada",RESERVAS!$I$6:$I$203,"<>Consulta")=0,"DISPONÍVEL",IF(COUNTIFS(RESERVAS!$C$6:$C$203,"<="&(DATE($E$2,$K$2,1)-WEEKDAY(DATE($E$2,$K$2,1),2)+1+33),RESERVAS!$D$6:$D$203,">"&(DATE($E$2,$K$2,1)-WEEKDAY(DATE($E$2,$K$2,1),2)+1+33),RESERVAS!$I$6:$I$203,"<>Cancelada",RESERVAS!$I$6:$I$203,"<>Consulta")=1,"ALUGADA","CONFLITO"))&IF(COUNTIFS(RESERVAS!$C$6:$C$203,"<="&(DATE($E$2,$K$2,1)-WEEKDAY(DATE($E$2,$K$2,1),2)+1+33),RESERVAS!$D$6:$D$203,">"&(DATE($E$2,$K$2,1)-WEEKDAY(DATE($E$2,$K$2,1),2)+1+33),RESERVAS!$I$6:$I$203,"<>Cancelada",RESERVAS!$I$6:$I$203,"<>Consulta")=0,"",CHAR(10)&IFERROR(LOOKUP(2,1/((RESERVAS!$C$6:$C$203<=(DATE($E$2,$K$2,1)-WEEKDAY(DATE($E$2,$K$2,1),2)+1+33))*(RESERVAS!$D$6:$D$203>(DATE($E$2,$K$2,1)-WEEKDAY(DATE($E$2,$K$2,1),2)+1+33))*(RESERVAS!$I$6:$I$203<>"Cancelada")*(RESERVAS!$I$6:$I$203<>"Consulta")),RESERVAS!$B$6:$B$203),""))) | G9: =IF(MONTH((DATE($E$2,$K$2,1)-WEEKDAY(DATE($E$2,$K$2,1),2)+1+34))<>$K$2,"",TEXT((DATE($E$2,$K$2,1)-WEEKDAY(DATE($E$2,$K$2,1),2)+1+34),"dd")&CHAR(10)&IF(COUNTIFS(RESERVAS!$C$6:$C$203,"<="&(DATE($E$2,$K$2,1)-WEEKDAY(DATE($E$2,$K$2,1),2)+1+34),RESERVAS!$D$6:$D$203,">"&(DATE($E$2,$K$2,1)-WEEKDAY(DATE($E$2,$K$2,1),2)+1+34),RESERVAS!$I$6:$I$203,"<>Cancelada",RESERVAS!$I$6:$I$203,"<>Consulta")=0,"DISPONÍVEL",IF(COUNTIFS(RESERVAS!$C$6:$C$203,"<="&(DATE($E$2,$K$2,1)-WEEKDAY(DATE($E$2,$K$2,1),2)+1+34),RESERVAS!$D$6:$D$203,">"&(DATE($E$2,$K$2,1)-WEEKDAY(DATE($E$2,$K$2,1),2)+1+34),RESERVAS!$I$6:$I$203,"<>Cancelada",RESERVAS!$I$6:$I$203,"<>Consulta")=1,"ALUGADA","CONFLITO"))&IF(COUNTIFS(RESERVAS!$C$6:$C$203,"<="&(DATE($E$2,$K$2,1)-WEEKDAY(DATE($E$2,$K$2,1),2)+1+34),RESERVAS!$D$6:$D$203,">"&(DATE($E$2,$K$2,1)-WEEKDAY(DATE($E$2,$K$2,1),2)+1+34),RESERVAS!$I$6:$I$203,"<>Cancelada",RESERVAS!$I$6:$I$203,"<>Consulta")=0,"",CHAR(10)&IFERROR(LOOKUP(2,1/((RESERVAS!$C$6:$C$203<=(DATE($E$2,$K$2,1)-WEEKDAY(DATE($E$2,$K$2,1),2)+1+34))*(RESERVAS!$D$6:$D$203>(DATE($E$2,$K$2,1)-WEEKDAY(DATE($E$2,$K$2,1),2)+1+34))*(RESERVAS!$I$6:$I$203<>"Cancelada")*(RESERVAS!$I$6:$I$203<>"Consulta")),RESERVAS!$B$6:$B$203),""))) | I9: Diárias alugadas | J9: =SUMPRODUCT((RESERVAS!$C$6:$C$203<DATE($E$2,$K$2+1,1))*(RESERVAS!$D$6:$D$203>DATE($E$2,$K$2,1))*(RESERVAS!$I$6:$I$203<>"Cancelada")*(RESERVAS!$I$6:$I$203<>"Consulta")*(((RESERVAS!$D$6:$D$203<DATE($E$2,$K$2+1,1))*RESERVAS!$D$6:$D$203+(RESERVAS!$D$6:$D$203>=DATE($E$2,$K$2+1,1))*DATE($E$2,$K$2+1,1))-((RESERVAS!$C$6:$C$203>DATE($E$2,$K$2,1))*RESERVAS!$C$6:$C$203+(RESERVAS!$C$6:$C$203<=DATE($E$2,$K$2,1))*DATE($E$2,$K$2,1)))) -> 8
A10: =IF(MONTH((DATE($E$2,$K$2,1)-WEEKDAY(DATE($E$2,$K$2,1),2)+1+35))<>$K$2,"",TEXT((DATE($E$2,$K$2,1)-WEEKDAY(DATE($E$2,$K$2,1),2)+1+35),"dd")&CHAR(10)&IF(COUNTIFS(RESERVAS!$C$6:$C$203,"<="&(DATE($E$2,$K$2,1)-WEEKDAY(DATE($E$2,$K$2,1),2)+1+35),RESERVAS!$D$6:$D$203,">"&(DATE($E$2,$K$2,1)-WEEKDAY(DATE($E$2,$K$2,1),2)+1+35),RESERVAS!$I$6:$I$203,"<>Cancelada",RESERVAS!$I$6:$I$203,"<>Consulta")=0,"DISPONÍVEL",IF(COUNTIFS(RESERVAS!$C$6:$C$203,"<="&(DATE($E$2,$K$2,1)-WEEKDAY(DATE($E$2,$K$2,1),2)+1+35),RESERVAS!$D$6:$D$203,">"&(DATE($E$2,$K$2,1)-WEEKDAY(DATE($E$2,$K$2,1),2)+1+35),RESERVAS!$I$6:$I$203,"<>Cancelada",RESERVAS!$I$6:$I$203,"<>Consulta")=1,"ALUGADA","CONFLITO"))&IF(COUNTIFS(RESERVAS!$C$6:$C$203,"<="&(DATE($E$2,$K$2,1)-WEEKDAY(DATE($E$2,$K$2,1),2)+1+35),RESERVAS!$D$6:$D$203,">"&(DATE($E$2,$K$2,1)-WEEKDAY(DATE($E$2,$K$2,1),2)+1+35),RESERVAS!$I$6:$I$203,"<>Cancelada",RESERVAS!$I$6:$I$203,"<>Consulta")=0,"",CHAR(10)&IFERROR(LOOKUP(2,1/((RESERVAS!$C$6:$C$203<=(DATE($E$2,$K$2,1)-WEEKDAY(DATE($E$2,$K$2,1),2)+1+35))*(RESERVAS!$D$6:$D$203>(DATE($E$2,$K$2,1)-WEEKDAY(DATE($E$2,$K$2,1),2)+1+35))*(RESERVAS!$I$6:$I$203<>"Cancelada")*(RESERVAS!$I$6:$I$203<>"Consulta")),RESERVAS!$B$6:$B$203),""))) | B10: =IF(MONTH((DATE($E$2,$K$2,1)-WEEKDAY(DATE($E$2,$K$2,1),2)+1+36))<>$K$2,"",TEXT((DATE($E$2,$K$2,1)-WEEKDAY(DATE($E$2,$K$2,1),2)+1+36),"dd")&CHAR(10)&IF(COUNTIFS(RESERVAS!$C$6:$C$203,"<="&(DATE($E$2,$K$2,1)-WEEKDAY(DATE($E$2,$K$2,1),2)+1+36),RESERVAS!$D$6:$D$203,">"&(DATE($E$2,$K$2,1)-WEEKDAY(DATE($E$2,$K$2,1),2)+1+36),RESERVAS!$I$6:$I$203,"<>Cancelada",RESERVAS!$I$6:$I$203,"<>Consulta")=0,"DISPONÍVEL",IF(COUNTIFS(RESERVAS!$C$6:$C$203,"<="&(DATE($E$2,$K$2,1)-WEEKDAY(DATE($E$2,$K$2,1),2)+1+36),RESERVAS!$D$6:$D$203,">"&(DATE($E$2,$K$2,1)-WEEKDAY(DATE($E$2,$K$2,1),2)+1+36),RESERVAS!$I$6:$I$203,"<>Cancelada",RESERVAS!$I$6:$I$203,"<>Consulta")=1,"ALUGADA","CONFLITO"))&IF(COUNTIFS(RESERVAS!$C$6:$C$203,"<="&(DATE($E$2,$K$2,1)-WEEKDAY(DATE($E$2,$K$2,1),2)+1+36),RESERVAS!$D$6:$D$203,">"&(DATE($E$2,$K$2,1)-WEEKDAY(DATE($E$2,$K$2,1),2)+1+36),RESERVAS!$I$6:$I$203,"<>Cancelada",RESERVAS!$I$6:$I$203,"<>Consulta")=0,"",CHAR(10)&IFERROR(LOOKUP(2,1/((RESERVAS!$C$6:$C$203<=(DATE($E$2,$K$2,1)-WEEKDAY(DATE($E$2,$K$2,1),2)+1+36))*(RESERVAS!$D$6:$D$203>(DATE($E$2,$K$2,1)-WEEKDAY(DATE($E$2,$K$2,1),2)+1+36))*(RESERVAS!$I$6:$I$203<>"Cancelada")*(RESERVAS!$I$6:$I$203<>"Consulta")),RESERVAS!$B$6:$B$203),""))) | C10: =IF(MONTH((DATE($E$2,$K$2,1)-WEEKDAY(DATE($E$2,$K$2,1),2)+1+37))<>$K$2,"",TEXT((DATE($E$2,$K$2,1)-WEEKDAY(DATE($E$2,$K$2,1),2)+1+37),"dd")&CHAR(10)&IF(COUNTIFS(RESERVAS!$C$6:$C$203,"<="&(DATE($E$2,$K$2,1)-WEEKDAY(DATE($E$2,$K$2,1),2)+1+37),RESERVAS!$D$6:$D$203,">"&(DATE($E$2,$K$2,1)-WEEKDAY(DATE($E$2,$K$2,1),2)+1+37),RESERVAS!$I$6:$I$203,"<>Cancelada",RESERVAS!$I$6:$I$203,"<>Consulta")=0,"DISPONÍVEL",IF(COUNTIFS(RESERVAS!$C$6:$C$203,"<="&(DATE($E$2,$K$2,1)-WEEKDAY(DATE($E$2,$K$2,1),2)+1+37),RESERVAS!$D$6:$D$203,">"&(DATE($E$2,$K$2,1)-WEEKDAY(DATE($E$2,$K$2,1),2)+1+37),RESERVAS!$I$6:$I$203,"<>Cancelada",RESERVAS!$I$6:$I$203,"<>Consulta")=1,"ALUGADA","CONFLITO"))&IF(COUNTIFS(RESERVAS!$C$6:$C$203,"<="&(DATE($E$2,$K$2,1)-WEEKDAY(DATE($E$2,$K$2,1),2)+1+37),RESERVAS!$D$6:$D$203,">"&(DATE($E$2,$K$2,1)-WEEKDAY(DATE($E$2,$K$2,1),2)+1+37),RESERVAS!$I$6:$I$203,"<>Cancelada",RESERVAS!$I$6:$I$203,"<>Consulta")=0,"",CHAR(10)&IFERROR(LOOKUP(2,1/((RESERVAS!$C$6:$C$203<=(DATE($E$2,$K$2,1)-WEEKDAY(DATE($E$2,$K$2,1),2)+1+37))*(RESERVAS!$D$6:$D$203>(DATE($E$2,$K$2,1)-WEEKDAY(DATE($E$2,$K$2,1),2)+1+37))*(RESERVAS!$I$6:$I$203<>"Cancelada")*(RESERVAS!$I$6:$I$203<>"Consulta")),RESERVAS!$B$6:$B$203),""))) | D10: =IF(MONTH((DATE($E$2,$K$2,1)-WEEKDAY(DATE($E$2,$K$2,1),2)+1+38))<>$K$2,"",TEXT((DATE($E$2,$K$2,1)-WEEKDAY(DATE($E$2,$K$2,1),2)+1+38),"dd")&CHAR(10)&IF(COUNTIFS(RESERVAS!$C$6:$C$203,"<="&(DATE($E$2,$K$2,1)-WEEKDAY(DATE($E$2,$K$2,1),2)+1+38),RESERVAS!$D$6:$D$203,">"&(DATE($E$2,$K$2,1)-WEEKDAY(DATE($E$2,$K$2,1),2)+1+38),RESERVAS!$I$6:$I$203,"<>Cancelada",RESERVAS!$I$6:$I$203,"<>Consulta")=0,"DISPONÍVEL",IF(COUNTIFS(RESERVAS!$C$6:$C$203,"<="&(DATE($E$2,$K$2,1)-WEEKDAY(DATE($E$2,$K$2,1),2)+1+38),RESERVAS!$D$6:$D$203,">"&(DATE($E$2,$K$2,1)-WEEKDAY(DATE($E$2,$K$2,1),2)+1+38),RESERVAS!$I$6:$I$203,"<>Cancelada",RESERVAS!$I$6:$I$203,"<>Consulta")=1,"ALUGADA","CONFLITO"))&IF(COUNTIFS(RESERVAS!$C$6:$C$203,"<="&(DATE($E$2,$K$2,1)-WEEKDAY(DATE($E$2,$K$2,1),2)+1+38),RESERVAS!$D$6:$D$203,">"&(DATE($E$2,$K$2,1)-WEEKDAY(DATE($E$2,$K$2,1),2)+1+38),RESERVAS!$I$6:$I$203,"<>Cancelada",RESERVAS!$I$6:$I$203,"<>Consulta")=0,"",CHAR(10)&IFERROR(LOOKUP(2,1/((RESERVAS!$C$6:$C$203<=(DATE($E$2,$K$2,1)-WEEKDAY(DATE($E$2,$K$2,1),2)+1+38))*(RESERVAS!$D$6:$D$203>(DATE($E$2,$K$2,1)-WEEKDAY(DATE($E$2,$K$2,1),2)+1+38))*(RESERVAS!$I$6:$I$203<>"Cancelada")*(RESERVAS!$I$6:$I$203<>"Consulta")),RESERVAS!$B$6:$B$203),""))) | E10: =IF(MONTH((DATE($E$2,$K$2,1)-WEEKDAY(DATE($E$2,$K$2,1),2)+1+39))<>$K$2,"",TEXT((DATE($E$2,$K$2,1)-WEEKDAY(DATE($E$2,$K$2,1),2)+1+39),"dd")&CHAR(10)&IF(COUNTIFS(RESERVAS!$C$6:$C$203,"<="&(DATE($E$2,$K$2,1)-WEEKDAY(DATE($E$2,$K$2,1),2)+1+39),RESERVAS!$D$6:$D$203,">"&(DATE($E$2,$K$2,1)-WEEKDAY(DATE($E$2,$K$2,1),2)+1+39),RESERVAS!$I$6:$I$203,"<>Cancelada",RESERVAS!$I$6:$I$203,"<>Consulta")=0,"DISPONÍVEL",IF(COUNTIFS(RESERVAS!$C$6:$C$203,"<="&(DATE($E$2,$K$2,1)-WEEKDAY(DATE($E$2,$K$2,1),2)+1+39),RESERVAS!$D$6:$D$203,">"&(DATE($E$2,$K$2,1)-WEEKDAY(DATE($E$2,$K$2,1),2)+1+39),RESERVAS!$I$6:$I$203,"<>Cancelada",RESERVAS!$I$6:$I$203,"<>Consulta")=1,"ALUGADA","CONFLITO"))&IF(COUNTIFS(RESERVAS!$C$6:$C$203,"<="&(DATE($E$2,$K$2,1)-WEEKDAY(DATE($E$2,$K$2,1),2)+1+39),RESERVAS!$D$6:$D$203,">"&(DATE($E$2,$K$2,1)-WEEKDAY(DATE($E$2,$K$2,1),2)+1+39),RESERVAS!$I$6:$I$203,"<>Cancelada",RESERVAS!$I$6:$I$203,"<>Consulta")=0,"",CHAR(10)&IFERROR(LOOKUP(2,1/((RESERVAS!$C$6:$C$203<=(DATE($E$2,$K$2,1)-WEEKDAY(DATE($E$2,$K$2,1),2)+1+39))*(RESERVAS!$D$6:$D$203>(DATE($E$2,$K$2,1)-WEEKDAY(DATE($E$2,$K$2,1),2)+1+39))*(RESERVAS!$I$6:$I$203<>"Cancelada")*(RESERVAS!$I$6:$I$203<>"Consulta")),RESERVAS!$B$6:$B$203),""))) | F10: =IF(MONTH((DATE($E$2,$K$2,1)-WEEKDAY(DATE($E$2,$K$2,1),2)+1+40))<>$K$2,"",TEXT((DATE($E$2,$K$2,1)-WEEKDAY(DATE($E$2,$K$2,1),2)+1+40),"dd")&CHAR(10)&IF(COUNTIFS(RESERVAS!$C$6:$C$203,"<="&(DATE($E$2,$K$2,1)-WEEKDAY(DATE($E$2,$K$2,1),2)+1+40),RESERVAS!$D$6:$D$203,">"&(DATE($E$2,$K$2,1)-WEEKDAY(DATE($E$2,$K$2,1),2)+1+40),RESERVAS!$I$6:$I$203,"<>Cancelada",RESERVAS!$I$6:$I$203,"<>Consulta")=0,"DISPONÍVEL",IF(COUNTIFS(RESERVAS!$C$6:$C$203,"<="&(DATE($E$2,$K$2,1)-WEEKDAY(DATE($E$2,$K$2,1),2)+1+40),RESERVAS!$D$6:$D$203,">"&(DATE($E$2,$K$2,1)-WEEKDAY(DATE($E$2,$K$2,1),2)+1+40),RESERVAS!$I$6:$I$203,"<>Cancelada",RESERVAS!$I$6:$I$203,"<>Consulta")=1,"ALUGADA","CONFLITO"))&IF(COUNTIFS(RESERVAS!$C$6:$C$203,"<="&(DATE($E$2,$K$2,1)-WEEKDAY(DATE($E$2,$K$2,1),2)+1+40),RESERVAS!$D$6:$D$203,">"&(DATE($E$2,$K$2,1)-WEEKDAY(DATE($E$2,$K$2,1),2)+1+40),RESERVAS!$I$6:$I$203,"<>Cancelada",RESERVAS!$I$6:$I$203,"<>Consulta")=0,"",CHAR(10)&IFERROR(LOOKUP(2,1/((RESERVAS!$C$6:$C$203<=(DATE($E$2,$K$2,1)-WEEKDAY(DATE($E$2,$K$2,1),2)+1+40))*(RESERVAS!$D$6:$D$203>(DATE($E$2,$K$2,1)-WEEKDAY(DATE($E$2,$K$2,1),2)+1+40))*(RESERVAS!$I$6:$I$203<>"Cancelada")*(RESERVAS!$I$6:$I$203<>"Consulta")),RESERVAS!$B$6:$B$203),""))) | G10: =IF(MONTH((DATE($E$2,$K$2,1)-WEEKDAY(DATE($E$2,$K$2,1),2)+1+41))<>$K$2,"",TEXT((DATE($E$2,$K$2,1)-WEEKDAY(DATE($E$2,$K$2,1),2)+1+41),"dd")&CHAR(10)&IF(COUNTIFS(RESERVAS!$C$6:$C$203,"<="&(DATE($E$2,$K$2,1)-WEEKDAY(DATE($E$2,$K$2,1),2)+1+41),RESERVAS!$D$6:$D$203,">"&(DATE($E$2,$K$2,1)-WEEKDAY(DATE($E$2,$K$2,1),2)+1+41),RESERVAS!$I$6:$I$203,"<>Cancelada",RESERVAS!$I$6:$I$203,"<>Consulta")=0,"DISPONÍVEL",IF(COUNTIFS(RESERVAS!$C$6:$C$203,"<="&(DATE($E$2,$K$2,1)-WEEKDAY(DATE($E$2,$K$2,1),2)+1+41),RESERVAS!$D$6:$D$203,">"&(DATE($E$2,$K$2,1)-WEEKDAY(DATE($E$2,$K$2,1),2)+1+41),RESERVAS!$I$6:$I$203,"<>Cancelada",RESERVAS!$I$6:$I$203,"<>Consulta")=1,"ALUGADA","CONFLITO"))&IF(COUNTIFS(RESERVAS!$C$6:$C$203,"<="&(DATE($E$2,$K$2,1)-WEEKDAY(DATE($E$2,$K$2,1),2)+1+41),RESERVAS!$D$6:$D$203,">"&(DATE($E$2,$K$2,1)-WEEKDAY(DATE($E$2,$K$2,1),2)+1+41),RESERVAS!$I$6:$I$203,"<>Cancelada",RESERVAS!$I$6:$I$203,"<>Consulta")=0,"",CHAR(10)&IFERROR(LOOKUP(2,1/((RESERVAS!$C$6:$C$203<=(DATE($E$2,$K$2,1)-WEEKDAY(DATE($E$2,$K$2,1),2)+1+41))*(RESERVAS!$D$6:$D$203>(DATE($E$2,$K$2,1)-WEEKDAY(DATE($E$2,$K$2,1),2)+1+41))*(RESERVAS!$I$6:$I$203<>"Cancelada")*(RESERVAS!$I$6:$I$203<>"Consulta")),RESERVAS!$B$6:$B$203),""))) | I10: Ocupação | J10: =IF(DAY(EOMONTH(DATE($E$2,$K$2,1),0))=0,0,J9/DAY(EOMONTH(DATE($E$2,$K$2,1),0))) -> 0.26666667
I12: LEGENDA
I13: DISPONÍVEL | J13: Dia livre
I14: ALUGADA | J14: Dia ocupado
I15: CONFLITO | J15: Reservas sobrepostas

Sheet RESERVAS
A1: RESERVAS — CONTROLE AUTOMÁTICO DE LOCAÇÃO
A3: Preencha apenas as células amarelas. O restante é calculado automaticamente. A data de saída (check-out) não conta como diária. Datas já comprometidas ficam BLOQUEADAS para novos lançamentos, inclusive coincidência com entrada ou saída de outra reserva. Preencha também o campo Imóvel com Casa Cinza ou Casa Laranja.
AG4: Média de pessoas
A5: ID | B5: Cliente / hóspede | C5: Entrada | D5: Saída | E5: Diárias | F5: Valor diária (R$) | G5: Receita bruta (R$) | H5: Período / motivo | I5: Status | J5: Canal | K5: Água (R$) | L5: Luz (R$) | M5: Limpeza (R$) | N5: Diarista (R$) | O5: Manutenção (R$) | P5: Investimento / reposição (R$) | Q5: Taxas / comissão (R$) | R5: Outros custos (R$) | S5: Custos diretos (R$) | T5: Custo por diária (R$) | U5: Lucro líquido (R$) | V5: Lucro por diária (R$) | W5: Margem líquida | X5: Valor recebido (R$) | Y5: Saldo a receber (R$) | Z5: Alerta | AA5: Observações | AB5: Imóvel | AC5: Adultos | AD5: Crinças | AE5: Total | AG5: Casa Cinza | AH5: Casa Laranja
A6: =IF(B6="","","LOC-"&TEXT(ROW()-5,"000")) -> LOC-001 | B6: Carlos - Natal/Ano Novo | C6: 46381 | D6: 46391 | E6: =IF(OR(B6="",C6="",D6=""),0,MAX(0,D6-C6)) -> 10 | F6: 1100 | G6: =IF(OR(B6="",E6=0,F6=""),0,E6*F6) -> 11000 | H6: Natal / Réveillon | I6: Confirmada | J6: Direto | K6: 0 | L6: 0 | M6: 0 | N6: 0 | O6: 0 | P6: =4490*2 -> 8980 | Q6: 0 | R6: 0 | S6: =IF(B6="",0,SUM(K6:R6)+SUMIFS('DESPESAS CASA'!$D$6:$D$305,'DESPESAS CASA'!$E$6:$E$305,A6))-P6 -> 0 | T6: =IF(OR(B6="",E6=0),0,S6/E6) -> 0 | U6: =IF(B6="",0,G6-S6) -> 11000 | V6: =IF(OR(B6="",E6=0),0,U6/E6) -> 1100 | W6: =IF(OR(B6="",G6=0),0,U6/G6) -> 1 | X6: =2200*2 -> 4400 | Y6: =IF(B6="",0,IFERROR(MAX(0,G6-X6),G6)) -> 6600 | Z6: =IF(B6="","",IF(COUNTIFS($C$6:$C$203,"<"&D6,$D$6:$D$203,">"&C6,$I$6:$I$203,"<>Cancelada",$I$6:$I$203,"<>Consulta",$AB$6:$AB$203,$AB6)>1,"CONFLITO","OK")) -> OK | AA6: 25/12/2026 a 04/01/2027 = 10 diárias | AB6: Casa Cinza | AC6: 0 | AD6: 0 | AE6: =IF((AC6+AD6)=0,"",AC6+AD6) | AG6: =IFERROR(SUMIF($AB$6:$AB$1000,AG$5,$AE$6:$AE$1000)/COUNTIFS($AB$6:$AB$1000,AG$5,$AE$6:$AE$1000,">0"),"") -> 3.8571429 | AH6: =IFERROR(SUMIF($AB$6:$AB$1000,AH$5,$AE$6:$AE$1000)/COUNTIFS($AB$6:$AB$1000,AH$5,$AE$6:$AE$1000,">0"),"") -> 5
A7: =IF(B7="","","LOC-"&TEXT(ROW()-5,"000")) -> LOC-002 | B7: Regina - 7 de Setembro | C7: 46269 | D7: 46273 | E7: =IF(OR(B7="",C7="",D7=""),0,MAX(0,D7-C7)) -> 4 | F7: 700 | G7: =IF(OR(B7="",E7=0,F7=""),0,E7*F7) -> 2800 | H7: Feriado | I7: Concluída | J7: Airbnb | Q7: =2800-2767.95 -> 32.05 | S7: =IF(B7="",0,SUM(K7:R7)+SUMIFS('DESPESAS CASA'!$D$6:$D$305,'DESPESAS CASA'!$E$6:$E$305,A7))-P7 -> 32.05 | T7: =IF(OR(B7="",E7=0),0,S7/E7) -> 8.0125 | U7: =IF(B7="",0,G7-S7) -> 2767.95 | V7: =IF(OR(B7="",E7=0),0,U7/E7) -> 691.9875 | W7: =IF(OR(B7="",G7=0),0,U7/G7) -> 0.98855357 | X7: =G7 -> 2800 | Y7: =IF(B7="",0,IFERROR(MAX(0,G7-X7),G7)) -> 0 | Z7: =IF(B7="","",IF(COUNTIFS($C$6:$C$203,"<"&D7,$D$6:$D$203,">"&C7,$I$6:$I$203,"<>Cancelada",$I$6:$I$203,"<>Consulta",$AB$6:$AB$203,$AB7)>1,"CONFLITO","OK")) -> OK | AB7: Casa Cinza | AE7: =IF((AC7+AD7)=0,"",AC7+AD7)
A8: =IF(B8="","","LOC-"&TEXT(ROW()-5,"000")) -> LOC-003 | B8: Louis Renan - Férias | C8: 46276 | D8: 46280 | E8: =IF(OR(B8="",C8="",D8=""),0,MAX(0,D8-C8)) -> 4 | F8: 0 | G8: =IF(OR(B8="",E8=0,F8=""),0,E8*F8) -> 0 | H8: Férias | I8: Concluída | J8: Cortesia | S8: =IF(B8="",0,SUM(K8:R8)+SUMIFS('DESPESAS CASA'!$D$6:$D$305,'DESPESAS CASA'!$E$6:$E$305,A8))-P8 -> 0 | T8: =IF(OR(B8="",E8=0),0,S8/E8) -> 0 | U8: =IF(B8="",0,G8-S8) -> 0 | V8: =IF(OR(B8="",E8=0),0,U8/E8) -> 0 | W8: =IF(OR(B8="",G8=0),0,U8/G8) -> 0 | Y8: =IF(B8="",0,IFERROR(MAX(0,G8-X8),G8)) -> 0 | Z8: =IF(B8="","",IF(COUNTIFS($C$6:$C$203,"<"&D8,$D$6:$D$203,">"&C8,$I$6:$I$203,"<>Cancelada",$I$6:$I$203,"<>Consulta",$AB$6:$AB$203,$AB8)>1,"CONFLITO","OK")) -> OK | AB8: Casa Cinza | AC8: 4 | AD8: 0 | AE8: =IF((AC8+AD8)=0,"",AC8+AD8) -> 4
A9: =IF(B9="","","LOC-"&TEXT(ROW()-5,"000")) -> LOC-004 | B9: Miguel - Ano Novo | C9: 46384 | D9: 46385 | E9: =IF(OR(B9="",C9="",D9=""),0,MAX(0,D9-C9)) -> 1 | F9: 0 | G9: =IF(OR(B9="",E9=0,F9=""),0,E9*F9) -> 0 | H9: Réveillon | I9: Confirmada | J9: Cortesia | S9: =IF(B9="",0,SUM(K9:R9)+SUMIFS('DESPESAS CASA'!$D$6:$D$305,'DESPESAS CASA'!$E$6:$E$305,A9))-P9 -> 0 | T9: =IF(OR(B9="",E9=0),0,S9/E9) -> 0 | U9: =IF(B9="",0,G9-S9) -> 0 | V9: =IF(OR(B9="",E9=0),0,U9/E9) -> 0 | W9: =IF(OR(B9="",G9=0),0,U9/G9) -> 0 | Y9: =IF(B9="",0,IFERROR(MAX(0,G9-X9),G9)) -> 0 | Z9: =IF(B9="","",IF(COUNTIFS($C$6:$C$203,"<"&D9,$D$6:$D$203,">"&C9,$I$6:$I$203,"<>Cancelada",$I$6:$I$203,"<>Consulta",$AB$6:$AB$203,$AB9)>1,"CONFLITO","OK")) -> OK | AB9: Casa Laranja | AC9: 5 | AE9: =IF((AC9+AD9)=0,"",AC9+AD9) -> 5
A10: =IF(B10="","","LOC-"&TEXT(ROW()-5,"000")) -> LOC-005 | B10: Miguel - Férias | C10: 46385 | D10: 46391 | E10: =IF(OR(B10="",C10="",D10=""),0,MAX(0,D10-C10)) -> 6 | F10: 1100 | G10: =IF(OR(B10="",E10=0,F10=""),0,E10*F10) -> 6600 | H10: Réveillon | I10: Confirmada | J10: Direto | S10: =IF(B10="",0,SUM(K10:R10)+SUMIFS('DESPESAS CASA'!$D$6:$D$305,'DESPESAS CASA'!$E$6:$E$305,A10))-P10 -> 0 | T10: =IF(OR(B10="",E10=0),0,S10/E10) -> 0 | U10: =IF(B10="",0,G10-S10) -> 6600 | V10: =IF(OR(B10="",E10=0),0,U10/E10) -> 1100 | W10: =IF(OR(B10="",G10=0),0,U10/G10) -> 1 | X10: 3925 | Y10: =IF(B10="",0,IFERROR(MAX(0,G10-X10),G10)) -> 2675 | Z10: =IF(B10="","",IF(COUNTIFS($C$6:$C$203,"<"&D10,$D$6:$D$203,">"&C10,$I$6:$I$203,"<>Cancelada",$I$6:$I$203,"<>Consulta",$AB$6:$AB$203,$AB10)>1,"CONFLITO","OK")) -> OK | AB10: Casa Laranja | AC10: 5 | AE10: =IF((AC10+AD10)=0,"",AC10+AD10) -> 5
A11: =IF(B11="","","LOC-"&TEXT(ROW()-5,"000")) -> LOC-006 | B11: Miguel - Férias | C11: 46391 | D11: 46401 | E11: =IF(OR(B11="",C11="",D11=""),0,MAX(0,D11-C11)) -> 10 | F11: 910 | G11: =IF(OR(B11="",E11=0,F11=""),0,E11*F11) -> 9100 | H11: Férias | I11: Confirmada | J11: Direto | S11: =IF(B11="",0,SUM(K11:R11)+SUMIFS('DESPESAS CASA'!$D$6:$D$305,'DESPESAS CASA'!$E$6:$E$305,A11))-P11 -> 0 | T11: =IF(OR(B11="",E11=0),0,S11/E11) -> 0 | U11: =IF(B11="",0,G11-S11) -> 9100 | V11: =IF(OR(B11="",E11=0),0,U11/E11) -> 910 | W11: =IF(OR(B11="",G11=0),0,U11/G11) -> 1 | Y11: =IF(B11="",0,IFERROR(MAX(0,G11-X11),G11)) -> 9100 | Z11: =IF(B11="","",IF(COUNTIFS($C$6:$C$203,"<"&D11,$D$6:$D$203,">"&C11,$I$6:$I$203,"<>Cancelada",$I$6:$I$203,"<>Consulta",$AB$6:$AB$203,$AB11)>1,"CONFLITO","OK")) -> OK | AB11: Casa Cinza | AC11: 5 | AE11: =IF((AC11+AD11)=0,"",AC11+AD11) -> 5
A12: =IF(B12="","","LOC-"&TEXT(ROW()-5,"000")) -> LOC-007 | B12: Luiz Moran | C12: 46305 | D12: 46314 | E12: =IF(OR(B12="",C12="",D12=""),0,MAX(0,D12-C12)) -> 9 | F12: =3874.25/E12 -> 430.47222 | G12: =IF(OR(B12="",E12=0,F12=""),0,E12*F12) -> 3874.25 | H12: Feriado | I12: Confirmada | J12: Airbnb | S12: =IF(B12="",0,SUM(K12:R12)+SUMIFS('DESPESAS CASA'!$D$6:$D$305,'DESPESAS CASA'!$E$6:$E$305,A12))-P12 -> 0 | T12: =IF(OR(B12="",E12=0),0,S12/E12) -> 0 | U12: =IF(B12="",0,G12-S12) -> 3874.25 | V12: =IF(OR(B12="",E12=0),0,U12/E12) -> 430.47222 | W12: =IF(OR(B12="",G12=0),0,U12/G12) -> 1 | X12: 3874.25 | Y12: =IF(B12="",0,IFERROR(MAX(0,G12-X12),G12)) -> 0 | Z12: =IF(B12="","",IF(COUNTIFS($C$6:$C$203,"<"&D12,$D$6:$D$203,">"&C12,$I$6:$I$203,"<>Cancelada",$I$6:$I$203,"<>Consulta",$AB$6:$AB$203,$AB12)>1,"CONFLITO","OK")) -> OK | AB12: Casa Cinza | AC12: 2 | AE12: =IF((AC12+AD12)=0,"",AC12+AD12) -> 2
A13: =IF(B13="","","LOC-"&TEXT(ROW()-5,"000")) -> LOC-008 | B13: Rodrigo Sengik | C13: 46329 | D13: 46344 | E13: =IF(OR(B13="",C13="",D13=""),0,MAX(0,D13-C13)) -> 15 | F13: =6396.57/E13 -> 426.438 | G13: =IF(OR(B13="",E13=0,F13=""),0,E13*F13) -> 6396.57 | H13: Férias | I13: Confirmada | J13: Airbnb | S13: =IF(B13="",0,SUM(K13:R13)+SUMIFS('DESPESAS CASA'!$D$6:$D$305,'DESPESAS CASA'!$E$6:$E$305,A13))-P13 -> 0 | T13: =IF(OR(B13="",E13=0),0,S13/E13) -> 0 | U13: =IF(B13="",0,G13-S13) -> 6396.57 | V13: =IF(OR(B13="",E13=0),0,U13/E13) -> 426.438 | W13: =IF(OR(B13="",G13=0),0,U13/G13) -> 1 | Y13: =IF(B13="",0,IFERROR(MAX(0,G13-X13),G13)) -> 6396.57 | Z13: =IF(B13="","",IF(COUNTIFS($C$6:$C$203,"<"&D13,$D$6:$D$203,">"&C13,$I$6:$I$203,"<>Cancelada",$I$6:$I$203,"<>Consulta",$AB$6:$AB$203,$AB13)>1,"CONFLITO","OK")) -> OK | AB13: Casa Cinza | AC13: 1 | AD13: 1 | AE13: =IF((AC13+AD13)=0,"",AC13+AD13) -> 2
A14: =IF(B14="","","LOC-"&TEXT(ROW()-5,"000")) -> LOC-009 | B14: Gean Michel | C14: 46325 | D14: 46329 | E14: =IF(OR(B14="",C14="",D14=""),0,MAX(0,D14-C14)) -> 4 | F14: =2070.85/E14 -> 517.7125 | G14: =IF(OR(B14="",E14=0,F14=""),0,E14*F14) -> 2070.85 | H14: Feriado | I14: Confirmada | J14: Airbnb | S14: =IF(B14="",0,SUM(K14:R14)+SUMIFS('DESPESAS CASA'!$D$6:$D$305,'DESPESAS CASA'!$E$6:$E$305,A14))-P14 -> 0 | T14: =IF(OR(B14="",E14=0),0,S14/E14) -> 0 | U14: =IF(B14="",0,G14-S14) -> 2070.85 | V14: =IF(OR(B14="",E14=0),0,U14/E14) -> 517.7125 | W14: =IF(OR(B14="",G14=0),0,U14/G14) -> 1 | Y14: =IF(B14="",0,IFERROR(MAX(0,G14-X14),G14)) -> 2070.85 | Z14: =IF(B14="","",IF(COUNTIFS($C$6:$C$203,"<"&D14,$D$6:$D$203,">"&C14,$I$6:$I$203,"<>Cancelada",$I$6:$I$203,"<>Consulta",$AB$6:$AB$203,$AB14)>1,"CONFLITO","OK")) -> OK | AB14: Casa Cinza | AC14: 3 | AD14: 2 | AE14: =IF((AC14+AD14)=0,"",AC14+AD14) -> 5
A15: =IF(B15="","","LOC-"&TEXT(ROW()-5,"000")) -> LOC-010 | B15: Renan Brito | C15: 46299 | D15: 46300 | E15: =IF(OR(B15="",C15="",D15=""),0,MAX(0,D15-C15)) -> 1 | F15: 0 | G15: =IF(OR(B15="",E15=0,F15=""),0,E15*F15) -> 0 | H15: Normal | I15: Concluída | J15: Cortesia | S15: =IF(B15="",0,SUM(K15:R15)+SUMIFS('DESPESAS CASA'!$D$6:$D$305,'DESPESAS CASA'!$E$6:$E$305,A15))-P15 -> 0 | T15: =IF(OR(B15="",E15=0),0,S15/E15) -> 0 | U15: =IF(B15="",0,G15-S15) -> 0 | V15: =IF(OR(B15="",E15=0),0,U15/E15) -> 0 | W15: =IF(OR(B15="",G15=0),0,U15/G15) -> 0 | Y15: =IF(B15="",0,IFERROR(MAX(0,G15-X15),G15)) -> 0 | Z15: =IF(B15="","",IF(COUNTIFS($C$6:$C$203,"<"&D15,$D$6:$D$203,">"&C15,$I$6:$I$203,"<>Cancelada",$I$6:$I$203,"<>Consulta",$AB$6:$AB$203,$AB15)>1,"CONFLITO","OK")) -> OK | AB15: Casa Cinza | AC15: 4 | AE15: =IF((AC15+AD15)=0,"",AC15+AD15) -> 4
A16: =IF(B16="","","LOC-"&TEXT(ROW()-5,"000")) -> LOC-011 | B16: Nicole | C16: 46372 | D16: 46377 | E16: =IF(OR(B16="",C16="",D16=""),0,MAX(0,D16-C16)) -> 5 | F16: =2400/E16 -> 480 | G16: =IF(OR(B16="",E16=0,F16=""),0,E16*F16) -> 2400 | H16: Normal | I16: Confirmada | J16: Airbnb | S16: =IF(B16="",0,SUM(K16:R16)+SUMIFS('DESPESAS CASA'!$D$6:$D$305,'DESPESAS CASA'!$E$6:$E$305,A16))-P16 -> 0 | T16: =IF(OR(B16="",E16=0),0,S16/E16) -> 0 | U16: =IF(B16="",0,G16-S16) -> 2400 | V16: =IF(OR(B16="",E16=0),0,U16/E16) -> 480 | W16: =IF(OR(B16="",G16=0),0,U16/G16) -> 1 | Y16: =IF(B16="",0,IFERROR(MAX(0,G16-X16),G16)) -> 2400 | Z16: =IF(B16="","",IF(COUNTIFS($C$6:$C$203,"<"&D16,$D$6:$D$203,">"&C16,$I$6:$I$203,"<>Cancelada",$I$6:$I$203,"<>Consulta",$AB$6:$AB$203,$AB16)>1,"CONFLITO","OK")) -> OK | AB16: Casa Cinza | AC16: 5 | AE16: =IF((AC16+AD16)=0,"",AC16+AD16) -> 5
A17: =IF(B17="","","LOC-"&TEXT(ROW()-5,"000")) -> LOC-012 | B17: Ana Paula | C17: 46402 | D17: 46407 | E17: =IF(OR(B17="",C17="",D17=""),0,MAX(0,D17-C17)) -> 5 | F17: =3884/E17 -> 776.8 | G17: =IF(OR(B17="",E17=0,F17=""),0,E17*F17) -> 3884 | H17: Normal | I17: Confirmada | J17: Airbnb | S17: =IF(B17="",0,SUM(K17:R17)+SUMIFS('DESPESAS CASA'!$D$6:$D$305,'DESPESAS CASA'!$E$6:$E$305,A17))-P17 -> 0 | T17: =IF(OR(B17="",E17=0),0,S17/E17) -> 0 | U17: =IF(B17="",0,G17-S17) -> 3884 | V17: =IF(OR(B17="",E17=0),0,U17/E17) -> 776.8 | W17: =IF(OR(B17="",G17=0),0,U17/G17) -> 1 | Y17: =IF(B17="",0,IFERROR(MAX(0,G17-X17),G17)) -> 3884 | Z17: =IF(B17="","",IF(COUNTIFS($C$6:$C$203,"<"&D17,$D$6:$D$203,">"&C17,$I$6:$I$203,"<>Cancelada",$I$6:$I$203,"<>Consulta",$AB$6:$AB$203,$AB17)>1,"CONFLITO","OK")) -> OK | AE17: =IF((AC17+AD17)=0,"",AC17+AD17)
A18: =IF(B18="","","LOC-"&TEXT(ROW()-5,"000")) | E18: =IF(OR(B18="",C18="",D18=""),0,MAX(0,D18-C18)) -> 0 | G18: =IF(OR(B18="",E18=0,F18=""),0,E18*F18) -> 0 | S18: =IF(B18="",0,SUM(K18:R18)+SUMIFS('DESPESAS CASA'!$D$6:$D$305,'DESPESAS CASA'!$E$6:$E$305,A18))-P18 -> 0 | T18: =IF(OR(B18="",E18=0),0,S18/E18) -> 0 | U18: =IF(B18="",0,G18-S18) -> 0 | V18: =IF(OR(B18="",E18=0),0,U18/E18) -> 0 | W18: =IF(OR(B18="",G18=0),0,U18/G18) -> 0 | Y18: =IF(B18="",0,IFERROR(MAX(0,G18-X18),G18)) -> 0 | Z18: =IF(B18="","",IF(COUNTIFS($C$6:$C$203,"<"&D18,$D$6:$D$203,">"&C18,$I$6:$I$203,"<>Cancelada",$I$6:$I$203,"<>Consulta",$AB$6:$AB$203,$AB18)>1,"CONFLITO","OK")) | AE18: =IF((AC18+AD18)=0,"",AC18+AD18)
A19: =IF(B19="","","LOC-"&TEXT(ROW()-5,"000")) | E19: =IF(OR(B19="",C19="",D19=""),0,MAX(0,D19-C19)) -> 0 | G19: =IF(OR(B19="",E19=0,F19=""),0,E19*F19) -> 0 | S19: =IF(B19="",0,SUM(K19:R19)+SUMIFS('DESPESAS CASA'!$D$6:$D$305,'DESPESAS CASA'!$E$6:$E$305,A19))-P19 -> 0 | T19: =IF(OR(B19="",E19=0),0,S19/E19) -> 0 | U19: =IF(B19="",0,G19-S19) -> 0 | V19: =IF(OR(B19="",E19=0),0,U19/E19) -> 0 | W19: =IF(OR(B19="",G19=0),0,U19/G19) -> 0 | Y19: =IF(B19="",0,IFERROR(MAX(0,G19-X19),G19)) -> 0 | Z19: =IF(B19="","",IF(COUNTIFS($C$6:$C$203,"<"&D19,$D$6:$D$203,">"&C19,$I$6:$I$203,"<>Cancelada",$I$6:$I$203,"<>Consulta",$AB$6:$AB$203,$AB19)>1,"CONFLITO","OK")) | AE19: =IF((AC19+AD19)=0,"",AC19+AD19)
A20: =IF(B20="","","LOC-"&TEXT(ROW()-5,"000")) | E20: =IF(OR(B20="",C20="",D20=""),0,MAX(0,D20-C20)) -> 0 | G20: =IF(OR(B20="",E20=0,F20=""),0,E20*F20) -> 0 | S20: =IF(B20="",0,SUM(K20:R20)+SUMIFS('DESPESAS CASA'!$D$6:$D$305,'DESPESAS CASA'!$E$6:$E$305,A20))-P20 -> 0 | T20: =IF(OR(B20="",E20=0),0,S20/E20) -> 0 | U20: =IF(B20="",0,G20-S20) -> 0 | V20: =IF(OR(B20="",E20=0),0,U20/E20) -> 0 | W20: =IF(OR(B20="",G20=0),0,U20/G20) -> 0 | Y20: =IF(B20="",0,IFERROR(MAX(0,G20-X20),G20)) -> 0 | Z20: =IF(B20="","",IF(COUNTIFS($C$6:$C$203,"<"&D20,$D$6:$D$203,">"&C20,$I$6:$I$203,"<>Cancelada",$I$6:$I$203,"<>Consulta",$AB$6:$AB$203,$AB20)>1,"CONFLITO","OK")) | AE20: =IF((AC20+AD20)=0,"",AC20+AD20)
A21: =IF(B21="","","LOC-"&TEXT(ROW()-5,"000")) | E21: =IF(OR(B21="",C21="",D21=""),0,MAX(0,D21-C21)) -> 0 | G21: =IF(OR(B21="",E21=0,F21=""),0,E21*F21) -> 0 | S21: =IF(B21="",0,SUM(K21:R21)+SUMIFS('DESPESAS CASA'!$D$6:$D$305,'DESPESAS CASA'!$E$6:$E$305,A21))-P21 -> 0 | T21: =IF(OR(B21="",E21=0),0,S21/E21) -> 0 | U21: =IF(B21="",0,G21-S21) -> 0 | V21: =IF(OR(B21="",E21=0),0,U21/E21) -> 0 | W21: =IF(OR(B21="",G21=0),0,U21/G21) -> 0 | Y21: =IF(B21="",0,IFERROR(MAX(0,G21-X21),G21)) -> 0 | Z21: =IF(B21="","",IF(COUNTIFS($C$6:$C$203,"<"&D21,$D$6:$D$203,">"&C21,$I$6:$I$203,"<>Cancelada",$I$6:$I$203,"<>Consulta",$AB$6:$AB$203,$AB21)>1,"CONFLITO","OK")) | AE21: =IF((AC21+AD21)=0,"",AC21+AD21)
A22: =IF(B22="","","LOC-"&TEXT(ROW()-5,"000")) | E22: =IF(OR(B22="",C22="",D22=""),0,MAX(0,D22-C22)) -> 0 | G22: =IF(OR(B22="",E22=0,F22=""),0,E22*F22) -> 0 | S22: =IF(B22="",0,SUM(K22:R22)+SUMIFS('DESPESAS CASA'!$D$6:$D$305,'DESPESAS CASA'!$E$6:$E$305,A22))-P22 -> 0 | T22: =IF(OR(B22="",E22=0),0,S22/E22) -> 0 | U22: =IF(B22="",0,G22-S22) -> 0 | V22: =IF(OR(B22="",E22=0),0,U22/E22) -> 0 | W22: =IF(OR(B22="",G22=0),0,U22/G22) -> 0 | Y22: =IF(B22="",0,IFERROR(MAX(0,G22-X22),G22)) -> 0 | Z22: =IF(B22="","",IF(COUNTIFS($C$6:$C$203,"<"&D22,$D$6:$D$203,">"&C22,$I$6:$I$203,"<>Cancelada",$I$6:$I$203,"<>Consulta",$AB$6:$AB$203,$AB22)>1,"CONFLITO","OK")) | AE22: =IF((AC22+AD22)=0,"",AC22+AD22)
A23: =IF(B23="","","LOC-"&TEXT(ROW()-5,"000")) | E23: =IF(OR(B23="",C23="",D23=""),0,MAX(0,D23-C23)) -> 0 | G23: =IF(OR(B23="",E23=0,F23=""),0,E23*F23) -> 0 | S23: =IF(B23="",0,SUM(K23:R23)+SUMIFS('DESPESAS CASA'!$D$6:$D$305,'DESPESAS CASA'!$E$6:$E$305,A23))-P23 -> 0 | T23: =IF(OR(B23="",E23=0),0,S23/E23) -> 0 | U23: =IF(B23="",0,G23-S23) -> 0 | V23: =IF(OR(B23="",E23=0),0,U23/E23) -> 0 | W23: =IF(OR(B23="",G23=0),0,U23/G23) -> 0 | Y23: =IF(B23="",0,IFERROR(MAX(0,G23-X23),G23)) -> 0 | Z23: =IF(B23="","",IF(COUNTIFS($C$6:$C$203,"<"&D23,$D$6:$D$203,">"&C23,$I$6:$I$203,"<>Cancelada",$I$6:$I$203,"<>Consulta",$AB$6:$AB$203,$AB23)>1,"CONFLITO","OK")) | AE23: =IF((AC23+AD23)=0,"",AC23+AD23)
A24: =IF(B24="","","LOC-"&TEXT(ROW()-5,"000")) | E24: =IF(OR(B24="",C24="",D24=""),0,MAX(0,D24-C24)) -> 0 | G24: =IF(OR(B24="",E24=0,F24=""),0,E24*F24) -> 0 | S24: =IF(B24="",0,SUM(K24:R24)+SUMIFS('DESPESAS CASA'!$D$6:$D$305,'DESPESAS CASA'!$E$6:$E$305,A24))-P24 -> 0 | T24: =IF(OR(B24="",E24=0),0,S24/E24) -> 0 | U24: =IF(B24="",0,G24-S24) -> 0 | V24: =IF(OR(B24="",E24=0),0,U24/E24) -> 0 | W24: =IF(OR(B24="",G24=0),0,U24/G24) -> 0 | Y24: =IF(B24="",0,IFERROR(MAX(0,G24-X24),G24)) -> 0 | Z24: =IF(B24="","",IF(COUNTIFS($C$6:$C$203,"<"&D24,$D$6:$D$203,">"&C24,$I$6:$I$203,"<>Cancelada",$I$6:$I$203,"<>Consulta",$AB$6:$AB$203,$AB24)>1,"CONFLITO","OK")) | AE24: =IF((AC24+AD24)=0,"",AC24+AD24)
A25: =IF(B25="","","LOC-"&TEXT(ROW()-5,"000")) | E25: =IF(OR(B25="",C25="",D25=""),0,MAX(0,D25-C25)) -> 0 | G25: =IF(OR(B25="",E25=0,F25=""),0,E25*F25) -> 0 | S25: =IF(B25="",0,SUM(K25:R25)+SUMIFS('DESPESAS CASA'!$D$6:$D$305,'DESPESAS CASA'!$E$6:$E$305,A25))-P25 -> 0 | T25: =IF(OR(B25="",E25=0),0,S25/E25) -> 0 | U25: =IF(B25="",0,G25-S25) -> 0 | V25: =IF(OR(B25="",E25=0),0,U25/E25) -> 0 | W25: =IF(OR(B25="",G25=0),0,U25/G25) -> 0 | Y25: =IF(B25="",0,IFERROR(MAX(0,G25-X25),G25)) -> 0 | Z25: =IF(B25="","",IF(COUNTIFS($C$6:$C$203,"<"&D25,$D$6:$D$203,">"&C25,$I$6:$I$203,"<>Cancelada",$I$6:$I$203,"<>Consulta",$AB$6:$AB$203,$AB25)>1,"CONFLITO","OK")) | AE25: =IF((AC25+AD25)=0,"",AC25+AD25)
A26: =IF(B26="","","LOC-"&TEXT(ROW()-5,"000")) | E26: =IF(OR(B26="",C26="",D26=""),0,MAX(0,D26-C26)) -> 0 | G26: =IF(OR(B26="",E26=0,F26=""),0,E26*F26) -> 0 | S26: =IF(B26="",0,SUM(K26:R26)+SUMIFS('DESPESAS CASA'!$D$6:$D$305,'DESPESAS CASA'!$E$6:$E$305,A26))-P26 -> 0 | T26: =IF(OR(B26="",E26=0),0,S26/E26) -> 0 | U26: =IF(B26="",0,G26-S26) -> 0 | V26: =IF(OR(B26="",E26=0),0,U26/E26) -> 0 | W26: =IF(OR(B26="",G26=0),0,U26/G26) -> 0 | Y26: =IF(B26="",0,IFERROR(MAX(0,G26-X26),G26)) -> 0 | Z26: =IF(B26="","",IF(COUNTIFS($C$6:$C$203,"<"&D26,$D$6:$D$203,">"&C26,$I$6:$I$203,"<>Cancelada",$I$6:$I$203,"<>Consulta",$AB$6:$AB$203,$AB26)>1,"CONFLITO","OK")) | AE26: =IF((AC26+AD26)=0,"",AC26+AD26)
A27: =IF(B27="","","LOC-"&TEXT(ROW()-5,"000")) | E27: =IF(OR(B27="",C27="",D27=""),0,MAX(0,D27-C27)) -> 0 | G27: =IF(OR(B27="",E27=0,F27=""),0,E27*F27) -> 0 | S27: =IF(B27="",0,SUM(K27:R27)+SUMIFS('DESPESAS CASA'!$D$6:$D$305,'DESPESAS CASA'!$E$6:$E$305,A27))-P27 -> 0 | T27: =IF(OR(B27="",E27=0),0,S27/E27) -> 0 | U27: =IF(B27="",0,G27-S27) -> 0 | V27: =IF(OR(B27="",E27=0),0,U27/E27) -> 0 | W27: =IF(OR(B27="",G27=0),0,U27/G27) -> 0 | Y27: =IF(B27="",0,IFERROR(MAX(0,G27-X27),G27)) -> 0 | Z27: =IF(B27="","",IF(COUNTIFS($C$6:$C$203,"<"&D27,$D$6:$D$203,">"&C27,$I$6:$I$203,"<>Cancelada",$I$6:$I$203,"<>Consulta",$AB$6:$AB$203,$AB27)>1,"CONFLITO","OK")) | AE27: =IF((AC27+AD27)=0,"",AC27+AD27)
A28: =IF(B28="","","LOC-"&TEXT(ROW()-5,"000")) | E28: =IF(OR(B28="",C28="",D28=""),0,MAX(0,D28-C28)) -> 0 | G28: =IF(OR(B28="",E28=0,F28=""),0,E28*F28) -> 0 | S28: =IF(B28="",0,SUM(K28:R28)+SUMIFS('DESPESAS CASA'!$D$6:$D$305,'DESPESAS CASA'!$E$6:$E$305,A28))-P28 -> 0 | T28: =IF(OR(B28="",E28=0),0,S28/E28) -> 0 | U28: =IF(B28="",0,G28-S28) -> 0 | V28: =IF(OR(B28="",E28=0),0,U28/E28) -> 0 | W28: =IF(OR(B28="",G28=0),0,U28/G28) -> 0 | Y28: =IF(B28="",0,IFERROR(MAX(0,G28-X28),G28)) -> 0 | Z28: =IF(B28="","",IF(COUNTIFS($C$6:$C$203,"<"&D28,$D$6:$D$203,">"&C28,$I$6:$I$203,"<>Cancelada",$I$6:$I$203,"<>Consulta",$AB$6:$AB$203,$AB28)>1,"CONFLITO","OK")) | AE28: =IF((AC28+AD28)=0,"",AC28+AD28)
A29: =IF(B29="","","LOC-"&TEXT(ROW()-5,"000")) | E29: =IF(OR(B29="",C29="",D29=""),0,MAX(0,D29-C29)) -> 0 | G29: =IF(OR(B29="",E29=0,F29=""),0,E29*F29) -> 0 | S29: =IF(B29="",0,SUM(K29:R29)+SUMIFS('DESPESAS CASA'!$D$6:$D$305,'DESPESAS CASA'!$E$6:$E$305,A29))-P29 -> 0 | T29: =IF(OR(B29="",E29=0),0,S29/E29) -> 0 | U29: =IF(B29="",0,G29-S29) -> 0 | V29: =IF(OR(B29="",E29=0),0,U29/E29) -> 0 | W29: =IF(OR(B29="",G29=0),0,U29/G29) -> 0 | Y29: =IF(B29="",0,IFERROR(MAX(0,G29-X29),G29)) -> 0 | Z29: =IF(B29="","",IF(COUNTIFS($C$6:$C$203,"<"&D29,$D$6:$D$203,">"&C29,$I$6:$I$203,"<>Cancelada",$I$6:$I$203,"<>Consulta",$AB$6:$AB$203,$AB29)>1,"CONFLITO","OK")) | AE29: =IF((AC29+AD29)=0,"",AC29+AD29)
... A203: =IF(B203="","","LOC-"&TEXT(ROW()-5,"000")) | E203: =IF(OR(B203="",C203="",D203=""),0,MAX(0,D203-C203)) -> 0 | G203: =IF(OR(B203="",E203=0,F203=""),0,E203*F203) -> 0 | S203: =IF(B203="",0,SUM(K203:R203)+SUMIFS('DESPESAS CASA'!$D$6:$D$305,'DESPESAS CASA'!$E$6:$E$305,A203))-P203 -> 0 | T203: =IF(OR(B203="",E203=0),0,S203/E203) -> 0 | U203: =IF(B203="",0,G203-S203) -> 0 | V203: =IF(OR(B203="",E203=0),0,U203/E203) -> 0 | W203: =IF(OR(B203="",G203=0),0,U203/G203) -> 0 | Y203: =IF(B203="",0,IFERROR(MAX(0,G203-X203),G203)) -> 0 | Z203: =IF(B203="","",IF(COUNTIFS($C$6:$C$203,"<"&D203,$D$6:$D$203,">"&C203,$I$6:$I$203,"<>Cancelada",$I$6:$I$203,"<>Consulta",$AB$6:$AB$203,$AB203)>1,"CONFLITO","OK")) | AE203: =IF((AC203+AD203)=0,"",AC203+AD203)

Sheet DESPESAS CASA
A1: DESPESAS GERAIS DA CASA
A3: Registre aqui as despesas da casa. Quando uma despesa pertencer a uma locação, selecione o ID em "Reserva relacionada (ID)". O valor será incorporado automaticamente aos custos, lucro e demais indicadores daquela locação. Deixe o ID em branco quando a despesa for geral da casa.
A5: Data | B5: Categoria | C5: Descrição | D5: Valor | E5: Reserva relacionada (ID) | F5: Observações | G5: Imóvel
E6: LOC-001 | G6: Casa Cinza

Sheet LISTAS
A1: LISTAS DE APOIO
A3: Mês | B3: Nº | D3: Período / motivo | E3: Status | F3: Canal | G3: Imóvel
A4: Janeiro | B4: 1 | D4: Normal | E4: Consulta | F4: Direto | G4: Casa Cinza
A5: Fevereiro | B5: 2 | D5: Férias | E5: Pré-reserva | F5: Airbnb | G5: Casa Laranja
A6: Março | B6: 3 | D6: Feriado | E6: Confirmada | F6: Booking
A7: Abril | B7: 4 | D7: Natal | E7: Concluída | F7: Imobiliária
A8: Maio | B8: 5 | D8: Réveillon | E8: Cancelada | F8: Indicação
A9: Junho | B9: 6 | D9: Natal / Réveillon | F9: Cortesia
A10: Julho | B10: 7 | D10: Carnaval | F10: Outro
A11: Agosto | B11: 8 | D11: Páscoa
A12: Setembro | B12: 9 | D12: Temporada de verão
A13: Outubro | B13: 10 | D13: Final de semana prolongado
A14: Novembro | B14: 11 | D14: Evento local
A15: Dezembro | B15: 12 | D15: Outro

Sheet PGTOS
B2: ID da locação | C2: Hóspede | D2: Valor (R$) | E2: Situação do controle | F2: CONTROLE DE PAGAMENTOS | R2: PARÂMETROS EDITÁVEIS
B3: {=_xlfn._xlws.FILTER(CHOOSE({1,2,3},RESERVAS!A6:A203,RESERVAS!B6:B203,RESERVAS!G6:G203),(RESERVAS!J6:J203="Direto")*(RESERVAS!J6:J203<>"Cortesia"),"")} -> LOC-001 | C3: Carlos - Natal/Ano Novo | D3: 11000 | E3: {=_xlfn.LET(_xlpm.ids,_xlfn._xlws.FILTER(RESERVAS!A6:A203,(RESERVAS!J6:J203="Direto")*(RESERVAS!J6:J203<>"Cortesia"),""),IF(_xlpm.ids="","",IF((COUNTIF($S$4,_xlpm.ids)+COUNTIF($V$4:$V$5,_xlpm.ids))>0,"Configurado","Configurar pagamento")))} -> Configurado | F3: ID da locação | G3: Hóspede | H3: Total contrato | I3: Parcela | J3: Vencimento | K3: Valor previsto | L3: Valor pago | M3: Data pagamento | N3: Status | O3: Saldo em aberto | P3: Alerta prazo | R3: CARLOS | S3: Valor / Data | V3: MIGUEL | W3: Vencimento | X3: Valor previsto | Y3: Valor pago | Z3: Data pagamento
B4: LOC-005 | C4: Miguel - Férias | D4: 6600 | E4: Configurado | F4: =IF(1<=$S$8,$S$4,"") -> LOC-001 | G4: =IF(F4="","",_xlfn.XLOOKUP(F4,RESERVAS!$A$6:$A$203,RESERVAS!$B$6:$B$203,"")) -> Carlos - Natal/Ano Novo | H4: =IF(F4="","",$S$7) -> 11000 | I4: =IF(F4="","",1&" de "&$S$8) -> 1 de 5 | J4: =IF(F4="","",EDATE($S$5,0)) -> 46251 | K4: =IF(F4="","",MIN($S$6,MAX(0,$S$7-$S$6*(1-1)))) -> 2200 | L4: 2200 | M4: 46251 | N4: =IF(F4="","",IF(AND(ISNUMBER(L4),L4>=K4),"Pago",IF(J4<TODAY(),"Atrasado","A vencer"))) -> Pago | O4: =IF(F4="","",MAX(0,H4-SUM($L$4:L4))) -> 8800 | P4: =IF(F4="","",IF(MAX($J$4:$J$15)>_xlfn.XLOOKUP($S$4,RESERVAS!$A$6:$A$203,RESERVAS!$D$6:$D$203),"ALERTA: última parcela após a saída","OK")) -> OK | R4: ID da locação | S4: LOC-001 | V4: LOC-005
B5: LOC-006 | C5: Miguel - Férias | D5: 9100 | E5: Configurado | F5: =IF(2<=$S$8,$S$4,"") -> LOC-001 | G5: =IF(F5="","",_xlfn.XLOOKUP(F5,RESERVAS!$A$6:$A$203,RESERVAS!$B$6:$B$203,"")) -> Carlos - Natal/Ano Novo | H5: =IF(F5="","",$S$7) -> 11000 | I5: =IF(F5="","",2&" de "&$S$8) -> 2 de 5 | J5: =IF(F5="","",EDATE($S$5,1)) -> 46282 | K5: =IF(F5="","",MIN($S$6,MAX(0,$S$7-$S$6*(2-1)))) -> 2200 | L5: 2200 | M5: 46275 | N5: =IF(F5="","",IF(AND(ISNUMBER(L5),L5>=K5),"Pago",IF(J5<TODAY(),"Atrasado","A vencer"))) -> Pago | O5: =IF(F5="","",MAX(0,H5-SUM($L$4:L5))) -> 6600 | P5: =IF(F5="","",IF(MAX($J$4:$J$15)>_xlfn.XLOOKUP($S$4,RESERVAS!$A$6:$A$203,RESERVAS!$D$6:$D$203),"ALERTA: última parcela após a saída","OK")) -> OK | R5: Primeiro vencimento | S5: 46251 | V5: LOC-006
F6: =IF(3<=$S$8,$S$4,"") -> LOC-001 | G6: =IF(F6="","",_xlfn.XLOOKUP(F6,RESERVAS!$A$6:$A$203,RESERVAS!$B$6:$B$203,"")) -> Carlos - Natal/Ano Novo | H6: =IF(F6="","",$S$7) -> 11000 | I6: =IF(F6="","",3&" de "&$S$8) -> 3 de 5 | J6: =IF(F6="","",EDATE($S$5,2)) -> 46312 | K6: =IF(F6="","",MIN($S$6,MAX(0,$S$7-$S$6*(3-1)))) -> 2200 | L6: 2200 | M6: 46305 | N6: =IF(F6="","",IF(AND(ISNUMBER(L6),L6>=K6),"Pago",IF(J6<TODAY(),"Atrasado","A vencer"))) -> Pago | O6: =IF(F6="","",MAX(0,H6-SUM($L$4:L6))) -> 4400 | P6: =IF(F6="","",IF(MAX($J$4:$J$15)>_xlfn.XLOOKUP($S$4,RESERVAS!$A$6:$A$203,RESERVAS!$D$6:$D$203),"ALERTA: última parcela após a saída","OK")) -> OK | R6: Parcela mensal | S6: 2200
F7: =IF(4<=$S$8,$S$4,"") -> LOC-001 | G7: =IF(F7="","",_xlfn.XLOOKUP(F7,RESERVAS!$A$6:$A$203,RESERVAS!$B$6:$B$203,"")) -> Carlos - Natal/Ano Novo | H7: =IF(F7="","",$S$7) -> 11000 | I7: =IF(F7="","",4&" de "&$S$8) -> 4 de 5 | J7: =IF(F7="","",EDATE($S$5,3)) -> 46343 | K7: =IF(F7="","",MIN($S$6,MAX(0,$S$7-$S$6*(4-1)))) -> 2200 | L7: =IF(F7="","",IF($S$14="","",$S$14)) | M7: =IF(F7="","",IF($T$14="","",$T$14)) | N7: =IF(F7="","",IF(AND(ISNUMBER(L7),L7>=K7),"Pago",IF(J7<TODAY(),"Atrasado","A vencer"))) -> A vencer | O7: =IF(F7="","",MAX(0,H7-SUM($L$4:L7))) -> 4400 | P7: =IF(F7="","",IF(MAX($J$4:$J$15)>_xlfn.XLOOKUP($S$4,RESERVAS!$A$6:$A$203,RESERVAS!$D$6:$D$203),"ALERTA: última parcela após a saída","OK")) -> OK | R7: Total contrato | S7: =SUMIFS(RESERVAS!$G$6:$G$203,RESERVAS!$A$6:$A$203,S4) -> 11000 | V7: 1 | W7: 46283 | X7: 3925 | Y7: 3925 | Z7: 46283
F8: =IF(5<=$S$8,$S$4,"") -> LOC-001 | G8: =IF(F8="","",_xlfn.XLOOKUP(F8,RESERVAS!$A$6:$A$203,RESERVAS!$B$6:$B$203,"")) -> Carlos - Natal/Ano Novo | H8: =IF(F8="","",$S$7) -> 11000 | I8: =IF(F8="","",5&" de "&$S$8) -> 5 de 5 | J8: =IF(F8="","",EDATE($S$5,4)) -> 46373 | K8: =IF(F8="","",MIN($S$6,MAX(0,$S$7-$S$6*(5-1)))) -> 2200 | L8: =IF(F8="","",IF($S$15="","",$S$15)) | M8: =IF(F8="","",IF($T$15="","",$T$15)) | N8: =IF(F8="","",IF(AND(ISNUMBER(L8),L8>=K8),"Pago",IF(J8<TODAY(),"Atrasado","A vencer"))) -> A vencer | O8: =IF(F8="","",MAX(0,H8-SUM($L$4:L8))) -> 4400 | P8: =IF(F8="","",IF(MAX($J$4:$J$15)>_xlfn.XLOOKUP($S$4,RESERVAS!$A$6:$A$203,RESERVAS!$D$6:$D$203),"ALERTA: última parcela após a saída","OK")) -> OK | R8: Quantidade parcelas | S8: 5 | V8: 2 | W8: 46376 | X8: 8831.25
F9: =IF(6<=$S$8,$S$4,"") | G9: =IF(F9="","",_xlfn.XLOOKUP(F9,RESERVAS!$A$6:$A$203,RESERVAS!$B$6:$B$203,"")) | H9: =IF(F9="","",$S$7) | I9: =IF(F9="","",6&" de "&$S$8) | J9: =IF(F9="","",EDATE($S$5,5)) | K9: =IF(F9="","",MIN($S$6,MAX(0,$S$7-$S$6*(6-1)))) | L9: =IF(F9="","",IF($S$16="","",$S$16)) | M9: =IF(F9="","",IF($T$16="","",$T$16)) | N9: =IF(F9="","",IF(AND(ISNUMBER(L9),L9>=K9),"Pago",IF(J9<TODAY(),"Atrasado","A vencer"))) | O9: =IF(F9="","",MAX(0,H9-SUM($L$4:L9))) | P9: =IF(F9="","",IF(MAX($J$4:$J$15)>_xlfn.XLOOKUP($S$4,RESERVAS!$A$6:$A$203,RESERVAS!$D$6:$D$203),"ALERTA: última parcela após a saída","OK")) | V9: 3 | W9: 46399 | X9: 2943.75
F10: =IF(7<=$S$8,$S$4,"") | G10: =IF(F10="","",_xlfn.XLOOKUP(F10,RESERVAS!$A$6:$A$203,RESERVAS!$B$6:$B$203,"")) | H10: =IF(F10="","",$S$7) | I10: =IF(F10="","",7&" de "&$S$8) | J10: =IF(F10="","",EDATE($S$5,6)) | K10: =IF(F10="","",MIN($S$6,MAX(0,$S$7-$S$6*(7-1)))) | L10: =IF(F10="","",IF($S$17="","",$S$17)) | M10: =IF(F10="","",IF($T$17="","",$T$17)) | N10: =IF(F10="","",IF(AND(ISNUMBER(L10),L10>=K10),"Pago",IF(J10<TODAY(),"Atrasado","A vencer"))) | O10: =IF(F10="","",MAX(0,H10-SUM($L$4:L10))) | P10: =IF(F10="","",IF(MAX($J$4:$J$15)>_xlfn.XLOOKUP($S$4,RESERVAS!$A$6:$A$203,RESERVAS!$D$6:$D$203),"ALERTA: última parcela após a saída","OK"))
F11: =IF(8<=$S$8,$S$4,"") | G11: =IF(F11="","",_xlfn.XLOOKUP(F11,RESERVAS!$A$6:$A$203,RESERVAS!$B$6:$B$203,"")) | H11: =IF(F11="","",$S$7) | I11: =IF(F11="","",8&" de "&$S$8) | J11: =IF(F11="","",EDATE($S$5,7)) | K11: =IF(F11="","",MIN($S$6,MAX(0,$S$7-$S$6*(8-1)))) | L11: =IF(F11="","",IF($S$18="","",$S$18)) | M11: =IF(F11="","",IF($T$18="","",$T$18)) | N11: =IF(F11="","",IF(AND(ISNUMBER(L11),L11>=K11),"Pago",IF(J11<TODAY(),"Atrasado","A vencer"))) | O11: =IF(F11="","",MAX(0,H11-SUM($L$4:L11))) | P11: =IF(F11="","",IF(MAX($J$4:$J$15)>_xlfn.XLOOKUP($S$4,RESERVAS!$A$6:$A$203,RESERVAS!$D$6:$D$203),"ALERTA: última parcela após a saída","OK"))
F12: =IF(9<=$S$8,$S$4,"") | G12: =IF(F12="","",_xlfn.XLOOKUP(F12,RESERVAS!$A$6:$A$203,RESERVAS!$B$6:$B$203,"")) | H12: =IF(F12="","",$S$7) | I12: =IF(F12="","",9&" de "&$S$8) | J12: =IF(F12="","",EDATE($S$5,8)) | K12: =IF(F12="","",MIN($S$6,MAX(0,$S$7-$S$6*(9-1)))) | L12: =IF(F12="","",IF($S$19="","",$S$19)) | M12: =IF(F12="","",IF($T$19="","",$T$19)) | N12: =IF(F12="","",IF(AND(ISNUMBER(L12),L12>=K12),"Pago",IF(J12<TODAY(),"Atrasado","A vencer"))) | O12: =IF(F12="","",MAX(0,H12-SUM($L$4:L12))) | P12: =IF(F12="","",IF(MAX($J$4:$J$15)>_xlfn.XLOOKUP($S$4,RESERVAS!$A$6:$A$203,RESERVAS!$D$6:$D$203),"ALERTA: última parcela após a saída","OK"))
F13: =IF(10<=$S$8,$S$4,"") | G13: =IF(F13="","",_xlfn.XLOOKUP(F13,RESERVAS!$A$6:$A$203,RESERVAS!$B$6:$B$203,"")) | H13: =IF(F13="","",$S$7) | I13: =IF(F13="","",10&" de "&$S$8) | J13: =IF(F13="","",EDATE($S$5,9)) | K13: =IF(F13="","",MIN($S$6,MAX(0,$S$7-$S$6*(10-1)))) | L13: =IF(F13="","",IF($S$20="","",$S$20)) | M13: =IF(F13="","",IF($T$20="","",$T$20)) | N13: =IF(F13="","",IF(AND(ISNUMBER(L13),L13>=K13),"Pago",IF(J13<TODAY(),"Atrasado","A vencer"))) | O13: =IF(F13="","",MAX(0,H13-SUM($L$4:L13))) | P13: =IF(F13="","",IF(MAX($J$4:$J$15)>_xlfn.XLOOKUP($S$4,RESERVAS!$A$6:$A$203,RESERVAS!$D$6:$D$203),"ALERTA: última parcela após a saída","OK"))
F14: =IF(11<=$S$8,$S$4,"") | G14: =IF(F14="","",_xlfn.XLOOKUP(F14,RESERVAS!$A$6:$A$203,RESERVAS!$B$6:$B$203,"")) | H14: =IF(F14="","",$S$7) | I14: =IF(F14="","",11&" de "&$S$8) | J14: =IF(F14="","",EDATE($S$5,10)) | K14: =IF(F14="","",MIN($S$6,MAX(0,$S$7-$S$6*(11-1)))) | L14: =IF(F14="","",IF($S$21="","",$S$21)) | M14: =IF(F14="","",IF($T$21="","",$T$21)) | N14: =IF(F14="","",IF(AND(ISNUMBER(L14),L14>=K14),"Pago",IF(J14<TODAY(),"Atrasado","A vencer"))) | O14: =IF(F14="","",MAX(0,H14-SUM($L$4:L14))) | P14: =IF(F14="","",IF(MAX($J$4:$J$15)>_xlfn.XLOOKUP($S$4,RESERVAS!$A$6:$A$203,RESERVAS!$D$6:$D$203),"ALERTA: última parcela após a saída","OK"))
F15: =IF(12<=$S$8,$S$4,"") | G15: =IF(F15="","",_xlfn.XLOOKUP(F15,RESERVAS!$A$6:$A$203,RESERVAS!$B$6:$B$203,"")) | H15: =IF(F15="","",$S$7) | I15: =IF(F15="","",12&" de "&$S$8) | J15: =IF(F15="","",EDATE($S$5,11)) | K15: =IF(F15="","",MIN($S$6,MAX(0,$S$7-$S$6*(12-1)))) | L15: =IF(F15="","",IF($S$22="","",$S$22)) | M15: =IF(F15="","",IF($T$22="","",$T$22)) | N15: =IF(F15="","",IF(AND(ISNUMBER(L15),L15>=K15),"Pago",IF(J15<TODAY(),"Atrasado","A vencer"))) | O15: =IF(F15="","",MAX(0,H15-SUM($L$4:L15))) | P15: =IF(F15="","",IF(MAX($J$4:$J$15)>_xlfn.XLOOKUP($S$4,RESERVAS!$A$6:$A$203,RESERVAS!$D$6:$D$203),"ALERTA: última parcela após a saída","OK"))
F17: =IF(W7="","",$V$4&" + "&$V$5) -> LOC-005 + LOC-006 | G17: =IF(F17="","",_xlfn.XLOOKUP($V$4,RESERVAS!$A$6:$A$203,RESERVAS!$B$6:$B$203,"")) -> Miguel - Férias | H17: =IF(F17="","",SUMIFS(RESERVAS!$G$6:$G$203,RESERVAS!$A$6:$A$203,$V$4)+SUMIFS(RESERVAS!$G$6:$G$203,RESERVAS!$A$6:$A$203,$V$5)) -> 15700 | I17: =IF(F17="","",1&" de "&COUNT($W$7:$W$9)) -> 1 de 3 | J17: =IF(F17="","",W7) -> 46283 | K17: =IF(F17="","",X7) -> 3925 | L17: =IF(F17="","",IF(Y7="","",Y7)) -> 3925 | M17: =IF(F17="","",IF(Z7="","",Z7)) -> 46283 | N17: =IF(F17="","",IF(AND(ISNUMBER(L17),L17>=K17),"Pago",IF(J17<TODAY(),"Atrasado","A vencer"))) -> Pago | O17: =IF(F17="","",MAX(0,H17-SUM($L$17:L17))) -> 11775 | P17: =IF(F17="","",IF(MAX($J$17:$J$19)>MAX(_xlfn.XLOOKUP($V$4,RESERVAS!$A$6:$A$203,RESERVAS!$D$6:$D$203),_xlfn.XLOOKUP($V$5,RESERVAS!$A$6:$A$203,RESERVAS!$D$6:$D$203)),"ALERTA: última parcela após a saída","OK")) -> OK
F18: =IF(W8="","",$V$4&" + "&$V$5) -> LOC-005 + LOC-006 | G18: =IF(F18="","",_xlfn.XLOOKUP($V$4,RESERVAS!$A$6:$A$203,RESERVAS!$B$6:$B$203,"")) -> Miguel - Férias | H18: =IF(F18="","",SUMIFS(RESERVAS!$G$6:$G$203,RESERVAS!$A$6:$A$203,$V$4)+SUMIFS(RESERVAS!$G$6:$G$203,RESERVAS!$A$6:$A$203,$V$5)) -> 15700 | I18: =IF(F18="","",2&" de "&COUNT($W$7:$W$9)) -> 2 de 3 | J18: =IF(F18="","",W8) -> 46376 | K18: =IF(F18="","",X8) -> 8831.25 | L18: =IF(F18="","",IF(Y8="","",Y8)) | M18: =IF(F18="","",IF(Z8="","",Z8)) | N18: =IF(F18="","",IF(AND(ISNUMBER(L18),L18>=K18),"Pago",IF(J18<TODAY(),"Atrasado","A vencer"))) -> A vencer | O18: =IF(F18="","",MAX(0,H18-SUM($L$17:L18))) -> 11775 | P18: =IF(F18="","",IF(MAX($J$17:$J$19)>MAX(_xlfn.XLOOKUP($V$4,RESERVAS!$A$6:$A$203,RESERVAS!$D$6:$D$203),_xlfn.XLOOKUP($V$5,RESERVAS!$A$6:$A$203,RESERVAS!$D$6:$D$203)),"ALERTA: última parcela após a saída","OK")) -> OK
F19: =IF(W9="","",$V$4&" + "&$V$5) -> LOC-005 + LOC-006 | G19: =IF(F19="","",_xlfn.XLOOKUP($V$4,RESERVAS!$A$6:$A$203,RESERVAS!$B$6:$B$203,"")) -> Miguel - Férias | H19: =IF(F19="","",SUMIFS(RESERVAS!$G$6:$G$203,RESERVAS!$A$6:$A$203,$V$4)+SUMIFS(RESERVAS!$G$6:$G$203,RESERVAS!$A$6:$A$203,$V$5)) -> 15700 | I19: =IF(F19="","",3&" de "&COUNT($W$7:$W$9)) -> 3 de 3 | J19: =IF(F19="","",W9) -> 46399 | K19: =IF(F19="","",X9) -> 2943.75 | L19: =IF(F19="","",IF(Y9="","",Y9)) | M19: =IF(F19="","",IF(Z9="","",Z9)) | N19: =IF(F19="","",IF(AND(ISNUMBER(L19),L19>=K19),"Pago",IF(J19<TODAY(),"Atrasado","A vencer"))) -> A vencer | O19: =IF(F19="","",MAX(0,H19-SUM($L$17:L19))) -> 11775 | P19: =IF(F19="","",IF(MAX($J$17:$J$19)>MAX(_xlfn.XLOOKUP($V$4,RESERVAS!$A$6:$A$203,RESERVAS!$D$6:$D$203),_xlfn.XLOOKUP($V$5,RESERVAS!$A$6:$A$203,RESERVAS!$D$6:$D$203)),"ALERTA: última parcela após a saída","OK")) -> OK
